Workbook

Sheet Events 2026
AA1: Cheltuieli
A2: Data | B2: Tip Event | C2: Specific | D2: Locatie | E2: Descriere | F2: Nr. Ctr. | G2: Total | H2: Valuta | I2: Avans | J2: Valuta | K2: 0.01 | L2: TCH | M2: Profit | N2: Fond | O2: %fond | P2: DivPH | Q2: AlteDiv | R2: %DIV | S2: Phaser | T2: Calcul Artist | U2: Artist Real | V2: Restul | W2: Valuta | Y2: Detalii | AA2: Prezent | AB2: Pret | AC2: Tehnici | AD2: Pret | AE2: Drum | AF2: Pret | AG2: Lumini | AH2: Pret | AI2: DJ | AJ2: Pret | AK2: Extra | AL2: Pret
A3: Ianuarie
A4: Februarie
A5: Martie
A6: Aprilie
A7: Mai
A8: 30 | B8: Privat | C8: Nunta | D8: Plaja Noua | F8: 228 | G8: 3850 | H8: EUR | I8: 350 | J8: EUR | K8: =round(G8*1%,0) -> 39 | L8: =sum(AB8+AD8+AF8+AH8+AJ8+AL8) -> 440 | M8: =G8-K8-L8 -> 3371 | N8: =round(O8*M8+I8,0) -> 687 | O8: 0.1 | P8: =round(R8*(M8-N8),0) -> 268 | Q8: =round(R8*AD8,0) -> 24 | R8: 0.1 | S8: =round(M8-N8-P8-Q8,0) -> 2392 | T8: =S8/5 -> 478.4 | U8: =round(T8,-1) -> 480 | V8: =5*(T8-U8) -> -8 | AA8: Backline | AB8: 200 | AD8: 240
A9: Iunie
A10: 6 | B10: Privat | C10: Nunta | D10: Pallazo | F10: 219 | G10: 4450 | H10: EUR | I10: 450 | J10: EUR | K10: =round(G10*1%,0) -> 45 | L10: =sum(AB10+AD10+AF10+AH10+AJ10+AL10) -> 1040 | M10: =G10-K10-L10 -> 3365 | N10: =round(O10*M10+I10,0) -> 787 | O10: 0.1 | P10: =round(R10*(M10-N10),0) -> 258 | Q10: =round(R10*AD10,0) -> 24 | R10: 0.1 | S10: =round(M10-N10-P10-Q10,0) -> 2296 | T10: =S10/5 -> 459.2 | U10: =round(T10,-1) -> 460 | V10: =5*(T10-U10) -> -4 | AA10: Backline | AB10: 200 | AD10: 240 | AI10: Flavius | AJ10: 600
A11: Iulie
A12: 25 | B12: Privat | C12: Nunta | D12: Luxury Events Ballroom @ Cunta | F12: 237 | G12: 4050 | H12: EUR | I12: 400 | J12: EUR | K12: =round(G12*1%,0) -> 41 | L12: =sum(AB12+AD12+AF12+AH12+AJ12+AL12) -> 440 | M12: =G12-K12-L12 -> 3569 | N12: =round(O12*M12+I12,0) -> 757 | O12: 0.1 | P12: =round(R12*(M12-N12),0) -> 281 | Q12: =round(R12*AD12,0) -> 24 | R12: 0.1 | S12: =round(M12-N12-P12-Q12,0) -> 2507 | T12: =S12/5 -> 501.4 | U12: =round(T12,-1) -> 500 | V12: =5*(T12-U12) -> 7 | AA12: Backline | AB12: 200 | AD12: 240
A13: August
A14: 22 | B14: Privat | C14: Nunta | D14: Province | F14: 229 | G14: 4950 | H14: EUR | I14: 450 | J14: EUR | K14: =round(G14*1%,0) -> 50 | L14: =sum(AB14+AD14+AF14+AH14+AJ14+AL14) -> 1240 | M14: =G14-K14-L14 -> 3660 | N14: =round(O14*M14+I14,0) -> 816 | O14: 0.1 | P14: =round(R14*(M14-N14),0) -> 284 | Q14: =round(R14*AD14,0) -> 24 | R14: 0.1 | S14: =round(M14-N14-P14-Q14,0) -> 2536 | T14: =S14/5 -> 507.2 | U14: =round(T14,-1) -> 510 | V14: =5*(T14-U14) -> -14 | AA14: Sistem Full | AB14: 400 | AD14: 240 | AG14: Flavius | AH14: 600
A15: Septembrie
A16: 19 | B16: Privat | C16: Nunta | D16: Domeniul Lupas | F16: 234 | G16: 3950 | H16: EUR | I16: 350 | J16: EUR | K16: =round(G16*1%,0) -> 40 | L16: =sum(AB16+AD16+AF16+AH16+AJ16+AL16) -> 540 | M16: =G16-K16-L16 -> 3370 | N16: =round(O16*M16+I16,0) -> 687 | O16: 0.1 | P16: =round(R16*(M16-N16),0) -> 268 | Q16: =round(R16*AD16,0) -> 24 | R16: 0.1 | S16: =round(M16-N16-P16-Q16,0) -> 2391 | T16: =S16/5 -> 478.2 | U16: =round(T16,-1) -> 480 | V16: =5*(T16-U16) -> -9 | AA16: Backline | AB16: 200 | AD16: 240 | AF16: 100
A17: 26 | B17: Privat | C17: Nunta | D17: Chrystal Ballroom Venue | F17: 235 | G17: 3850 | H17: EUR | I17: 350 | J17: EUR | K17: =round(G17*1%,0) -> 39 | L17: =sum(AB17+AD17+AF17+AH17+AJ17+AL17) -> 440 | M17: =G17-K17-L17 -> 3371 | N17: =round(O17*M17+I17,0) -> 687 | O17: 0.1 | P17: =round(R17*(M17-N17),0) -> 268 | Q17: =round(R17*AD17,0) -> 24 | R17: 0.1 | S17: =round(M17-N17-P17-Q17,0) -> 2392 | T17: =S17/5 -> 478.4 | U17: =round(T17,-1) -> 480 | V17: =5*(T17-U17) -> -8 | AA17: Backline | AB17: 200 | AD17: 240
A18: Octombrie
A19: 10 | B19: Privat | C19: Nunta | D19: Sala noua @ Flonta | F19: 239 | G19: 4100 | H19: EUR | I19: 400 | J19: EUR | K19: =round(G19*1%,0) -> 41 | L19: =sum(AB19+AD19+AF19+AH19+AJ19+AL19) -> 440 | M19: =G19-K19-L19 -> 3619 | N19: =round(O19*M19+I19,0) -> 762 | O19: 0.1 | P19: =round(R19*(M19-N19),0) -> 286 | Q19: =round(R19*AD19,0) -> 24 | R19: 0.1 | S19: =round(M19-N19-P19-Q19,0) -> 2547 | T19: =S19/5 -> 509.4 | U19: =round(T19,-1) -> 510 | V19: =5*(T19-U19) -> -3 | AA19: Backline | AB19: 200 | AD19: 240
A20: Decembrie
A22: TEST | K22: =round(G22*1%,0) -> 0 | L22: =sum(AB22+AD22+AF22+AH22+AJ22+AL22) -> 0 | M22: =G22-K22-L22 -> 0 | N22: =round(O22*M22+I22,0) -> 0 | O22: 0.1 | P22: =round(R22*(M22-N22),0) -> 0 | Q22: =round(R22*AD22,0) -> 0 | R22: 0.1 | S22: =round(M22-N22-P22-Q22,0) -> 0 | T22: =S22/5 -> 0 | U22: =round(T22,-1) -> 0 | V22: =5*(T22-U22) -> 0

Sheet Evenimente 2025
AA1: Cheltuieli
A2: Data | B2: Tip Event | C2: Specific | D2: Locatie | E2: Descriere | F2: Nr. Ctr. | G2: Total | H2: Valuta | I2: Avans | J2: Valuta | K2: 0.01 | L2: TCH | M2: Profit | N2: Fond | O2: %fond | P2: DivPH | Q2: AlteDiv | R2: %DIV | S2: Phaser | T2: Calcul Artist | U2: Artist Real | V2: Restul | W2: Valuta | Y2: Detalii | AA2: Prezent | AB2: Pret | AC2: Tehnici | AD2: Pret | AE2: Drum | AF2: Pret | AG2: Lumini | AH2: Pret | AI2: DJ | AJ2: Pret | AK2: Extra | AL2: Pret
A3: Ianuarie
A4: 13 | B4: Public | C4: Concert Phaser | D4: Livigno @ Italia | E4: Snow Fest Italia | G4: 0 | H4: RON | I4: 0 | J4: RON | K4: =round(G4*1%,0) -> 0 | L4: =sum(AB4+AD4+AF4+AH4+AJ4+AL4) -> 0 | M4: =G4-K4-L4 -> 0 | N4: =round(O4*M4+I4,0) -> 0 | O4: 0 | P4: =round(R4*(M4-N4),0) -> 0 | Q4: =round(R4*AD4,0) -> 0 | R4: 0.1 | S4: =round(M4-N4-P4-Q4,0) -> 0 | T4: =S4/5 -> 0 | U4: =round(T4,-1) -> 0 | V4: =5*(T4-U4) -> 0 | W4: RON | AA4: Backline | AB4: 0
A5: 15 | B5: Public | C5: Concert Phaser | D5: Livigno @ Italia | E5: Snow Fest Italia | G5: 0 | H5: RON | I5: 0 | J5: RON | K5: =round(G5*1%,0) -> 0 | L5: =sum(AB5+AD5+AF5+AH5+AJ5+AL5) -> 0 | M5: =G5-K5-L5 -> 0 | N5: =round(O5*M5+I5,0) -> 0 | O5: 0 | P5: =round(R5*(M5-N5),0) -> 0 | Q5: =round(R5*AD5,0) -> 0 | R5: 0.1 | S5: =round(M5-N5-P5-Q5,0) -> 0 | T5: =S5/5 -> 0 | U5: =round(T5,-1) -> 0 | V5: =5*(T5-U5) -> 0 | W5: RON | AA5: Backline | AB5: 0
A6: 31 | B6: Public | C6: Concert Phaser | D6: Kai @ Timisoara | G6: 6000 | H6: RON | I6: 0 | J6: RON | K6: =round(G6*1%,0) -> 60 | L6: =sum(AB6+AD6+AF6+AH6+AJ6+AL6) -> 2000 | M6: =G6-K6-L6 -> 3940 | N6: =round(O6*M6+I6,0) -> -39 | O6: -0.01 | P6: =round(R6*(M6-N6),0) -> 398 | Q6: =round(R6*AD6,0) -> 100 | R6: 0.1 | S6: =round(M6-N6-P6-Q6,0) -> 3481 | T6: =S6/5 -> 696.2 | U6: =round(T6,-1) -> 700 | V6: =5*(T6-U6) -> -19 | W6: RON | AA6: Backline | AB6: 1000 | AD6: 1000
A7: Februarie
A8: Martie
A9: 26 | B9: Public | C9: Concert Phaser | D9: Les Deux Alps @ Franta | E9: Snow Fest Franta | G9: 600 | H9: EUR | I9: 0 | J9: EUR | K9: 0 | L9: =sum(AB9+AD9+AF9+AH9+AJ9+AL9) -> 0 | M9: =G9-K9-L9 -> 600 | N9: =round(O9*M9+I9,0) -> 0 | O9: 0 | P9: =round(R9*(M9-N9),0) -> 0 | Q9: =round(R9*AD9,0) -> 0 | R9: 0 | S9: =round(M9-N9-P9-Q9,0) -> 600 | T9: =S9/5 -> 120 | U9: =round(T9,-1) -> 120 | V9: =5*(T9-U9) -> 0 | W9: EUR | AA9: Backline | AB9: 0
A10: 31 | B10: Public | C10: Concert Phaser | D10: Val Thorens @ Franta | E10: Snow Fest Franta | G10: 800 | H10: EUR | I10: 0 | J10: EUR | K10: 0 | L10: =sum(AB10+AD10+AF10+AH10+AJ10+AL10) -> 0 | M10: =G10-K10-L10 -> 800 | N10: =round(O10*M10+I10,0) -> 0 | O10: 0 | P10: =round(R10*(M10-N10),0) -> 0 | Q10: =round(R10*AD10,0) -> 0 | R10: 0 | S10: =round(M10-N10-P10-Q10,0) -> 800 | T10: =S10/5 -> 160 | U10: =round(T10,-1) -> 160 | V10: =5*(T10-U10) -> 0 | W10: EUR | AA10: Backline | AB10: 0
A11: Aprilie
A12: 12 | B12: Privat | C12: Extra | D12: Plaja Noua | E12: Targ de nunti | G12: 0 | H12: RON | I12: 0 | J12: RON | K12: =round(G12*1%,0) -> 0 | L12: =sum(AB12+AD12+AF12+AH12+AJ12+AL12) -> 500 | M12: =G12-K12-L12 -> -500 | N12: =round(O12*M12+I12,0) -> 0 | O12: 0 | P12: =round(R12*(M12-N12),0) -> -50 | Q12: =round(R12*AD12,0) -> 50 | R12: 0.1 | S12: 0 | T12: 0 | U12: 0 | V12: =5*(T12-U12) -> 0 | W12: RON | AA12: Backline | AB12: 0 | AD12: 500
A13: 12 | B13: Public | C13: Scena Mare | D13: Timisoara | E13: Targul de Pasti | G13: 10000 | H13: RON | J13: RON | K13: =round(G13*1%,0) -> 100 | L13: =sum(AB13+AD13+AF13+AH13+AJ13+AL13) -> 2000 | M13: =G13-K13-L13 -> 7900 | N13: =round(O13*M13+I13,0) -> 1106 | O13: 0.14 | P13: =round(R13*(M13-N13),0) -> 679 | Q13: =round(R13*AD13,0) -> 100 | R13: 0.1 | S13: =round(M13-N13-P13-Q13,0) -> 6015 | T13: =S13/5 -> 1203 | U13: =round(T13,-1) -> 1200 | V13: =5*(T13-U13) -> 15 | AA13: Backline | AB13: 1000 | AD13: 1000
A14: Mai
A15: 2 | B15: Privat | C15: Nunta | D15: Domeniile Streiului | F15: 212 | G15: 24105 | H15: EUR | I15: 2237 | J15: RON | K15: =round(I15*1%,0) -> 22 | L15: =sum(AB15+AD15+AF15+AH15+AJ15+AL15) -> 7000 | M15: =G15-K15-L15 -> 17083 | N15: =round(O15*M15+I15,0) -> 4372 | O15: 0.125 | P15: =round(R15*(M15-N15),0) -> 0 | Q15: =round(R15*AD15,0) -> 0 | R15: 0 | S15: =round(M15-N15-P15-Q15,0) -> 12711 | T15: =S15/5 -> 2542.2 | U15: =round(T15,-1) -> 2540 | V15: =5*(T15-U15) -> 11 | W15: RON | AA15: Sistem de sunet | AB15: 2000 | AD15: 1500 | AF15: 1000 | AI15: Flavius | AJ15: 2500
A16: 11 | B16: Privat | C16: Nunta | D16: Province | F16: 224 | G16: 17740 | H16: RON | I16: 1740 | J16: RON | K16: =round(I16*1%,0) -> 17 | L16: =sum(AB16+AD16+AF16+AH16+AJ16+AL16) -> 2250 | M16: =G16-K16-L16 -> 15473 | N16: =round(O16*M16+I16,0) -> 2823 | O16: 0.07 | P16: =round(R16*(M16-N16),0) -> 0 | Q16: =round(R16*AD16,0) -> 0 | R16: 0 | S16: =round(M16-N16-P16-Q16,0) -> 12650 | T16: =S16/5 -> 2530 | U16: =round(T16,-1) -> 2530 | V16: =5*(T16-U16) -> 0 | W16: RON | AA16: Backline | AB16: 1000 | AD16: 1000 | AF16: 250
A17: 23 | B17: Privat | C17: Botez | D17: Villa Trevi | G17: 3800 | H17: EUR | I17: 0 | J17: EUR | K17: =round(I17*1%,0) -> 0 | L17: =sum(AB17+AD17+AF17+AH17+AJ17+AL17) -> 650 | M17: =G17-K17-L17 -> 3150 | N17: =round(O17*M17+I17,0) -> 347 | O17: 0.11 | P17: =round(R17*(M17-N17),0) -> 0 | Q17: =round(R17*AD17,0) -> 0 | R17: 0 | S17: =round(M17-N17-P17-Q17,0) -> 2803 | T17: =S17/5 -> 560.6 | U17: =round(T17,-1) -> 560 | V17: =5*(T17-U17) -> 3 | AA17: Backline | AB17: 400 | AD17: 200 | AF17: 50
A18: 24 | B18: Privat | C18: Nunta | D18: Ivy Events | F18: 217 | G18: 4700 | H18: EUR | I18: 500 | J18: EUR | K18: =round(G18*1%,0) -> 47 | L18: =sum(AB18+AD18+AF18+AH18+AJ18+AL18) -> 800 | M18: =G18-K18-L18 -> 3853 | N18: =round(O18*M18+I18,0) -> 1078 | O18: 0.15 | P18: =round(R18*(M18-N18),0) -> 278 | Q18: =round(R18*AD18,0) -> 20 | R18: 0.1 | S18: =round(M18-N18-P18-Q18,0) -> 2477 | T18: =S18/5 -> 495.4 | U18: =round(T18,-1) -> 500 | V18: =5*(T18-U18) -> -23 | W18: EUR | AA18: Sistem de sunet | AB18: 400 | AD18: 200 | AG18: Flavius | AH18: 200
A19: 30 | B19: Privat | C19: Nunta | D19: Flonta | F19: 227 | G19: 3150 | H19: EUR | I19: 0 | J19: EUR | K19: =round(I19*1%,0) -> 0 | L19: =sum(AB19+AD19+AF19+AH19+AJ19+AL19) -> 600 | M19: =G19-K19-L19 -> 2550 | N19: =round(O19*M19+I19,0) -> 26 | O19: 0.01 | P19: =round(R19*(M19-N19),0) -> 0 | Q19: =round(R19*AD19,0) -> 0 | R19: 0 | S19: =round(M19-N19-P19-Q19,0) -> 2524 | T19: =S19/5 -> 504.8 | U19: =round(T19,-1) -> 500 | V19: =5*(T19-U19) -> 24 | W19: EUR | AA19: Sistem de sunet | AB19: 400 | AD19: 200
A20: 31 | B20: Privat | C20: Nunta | D20: Timeea @ Resita | F20: 189 | G20: 4300 | H20: EUR | I20: 0 | J20: EUR | K20: =round(I20*1%,0) -> 0 | L20: =sum(AB20+AD20+AF20+AH20+AJ20+AL20) -> 1450 | M20: =G20-K20-L20 -> 2850 | N20: =round(O20*M20+I20,0) -> 342 | O20: 0.12 | P20: =round(R20*(M20-N20),0) -> 0 | Q20: =round(R20*AD20,0) -> 0 | R20: 0 | S20: =round(M20-N20-P20-Q20,0) -> 2508 | T20: =S20/5 -> 501.6 | U20: =round(T20,-1) -> 500 | V20: =5*(T20-U20) -> 8 | W20: EUR | AA20: Sistem de sunet | AB20: 550 | AD20: 300 | AF20: 100 | AG20: Flavius | AH20: 500
A21: Iunie
A22: 8 | B22: Public | C22: Concert Phaser | D22: Bastion @ Timisoara | G22: 10000 | H22: RON | I22: 0 | J22: RON | K22: =round(G22*1%,0) -> 100 | L22: =sum(AB22+AD22+AF22+AH22+AJ22+AL22) -> 5900 | M22: =G22-K22-L22 -> 4000 | N22: =round(O22*M22+I22,0) -> -40 | O22: -0.01 | P22: =round(R22*(M22-N22),0) -> 404 | Q22: =round(R22*AD22,0) -> 150 | R22: 0.1 | S22: =round(M22-N22-P22-Q22,0) -> 3486 | T22: =S22/5 -> 697.2 | U22: =round(T22,-1) -> 700 | V22: =5*(T22-U22) -> -14 | W22: RON | AA22: Sistem de sunet | AB22: 2000 | AD22: 1500 | AK22: Cvartet | AL22: 2400
A23: 14 | B23: Privat | C23: Nunta | D23: Riviere Ballroom | F23: 218 | G23: 18065 | H23: RON | I23: 1715 | J23: RON | K23: =round(I23*1%,0) -> 17 | L23: =sum(AB23+AD23+AF23+AH23+AJ23+AL23) -> 2500 | M23: =G23-K23-L23 -> 15548 | N23: =round(O23*M23+I23,0) -> 3037 | O23: 0.085 | P23: =round(R23*(M23-N23),0) -> 0 | Q23: =round(R23*AD23,0) -> 0 | R23: 0 | S23: =round(M23-N23-P23-Q23,0) -> 12511 | T23: =S23/5 -> 2502.2 | U23: =round(T23,-1) -> 2500 | V23: =5*(T23-U23) -> 11 | W23: RON | AA23: Backline | AB23: 1000 | AD23: 1500
A24: 17 | B24: Privat | C24: Corporate | D24: Sky Restaurant | G24: 14912 | H24: RON | I24: 4312 | J24: RON | K24: =round(G24*1%,0) -> 149 | L24: =sum(AB24+AD24+AF24+AH24+AJ24+AL24) -> 2000 | M24: =G24-K24-L24 -> 12763 | N24: =round(O24*M24+I24,0) -> 4312 | O24: 0 | P24: =round(R24*(M24-N24),0) -> 845 | Q24: =round(R24*AD24,0) -> 100 | R24: 0.1 | S24: =round(M24-N24-P24-Q24,0) -> 7506 | T24: =S24/5 -> 1501.2 | U24: =round(T24,-1) -> 1500 | V24: =5*(T24-U24) -> 6 | W24: RON | AA24: Backline | AB24: 1000 | AD24: 1000
A25: 21 | B25: Public | C25: Scena Mare | D25: Timisoara | G25: 10000 | H25: RON | I25: 0 | J25: RON | K25: =round(G25*1%,0) -> 100 | L25: =sum(AB25+AD25+AF25+AH25+AJ25+AL25) -> 2000 | M25: =G25-K25-L25 -> 7900 | N25: =round(O25*M25+I25,0) -> 1106 | O25: 0.14 | P25: =round(R25*(M25-N25),0) -> 679 | Q25: =round(R25*AD25,0) -> 100 | R25: 0.1 | S25: =round(M25-N25-P25-Q25,0) -> 6015 | T25: =S25/5 -> 1203 | U25: =round(T25,-1) -> 1200 | V25: =5*(T25-U25) -> 15 | W25: RON | AA25: Backline | AB25: 1000 | AD25: 1000
A26: 22 | B26: Public | C26: Scena Mare | D26: Muzeul Satului | E26: Flight Festival | G26: 6000 | H26: RON | I26: 0 | J26: RON | K26: =round(G26*1%,0) -> 60 | L26: =sum(AB26+AD26+AF26+AH26+AJ26+AL26) -> 2750 | M26: =G26-K26-L26 -> 3190 | N26: =round(O26*M26+I26,0) -> 191 | O26: 0.06 | P26: =round(R26*(M26-N26),0) -> 0 | Q26: =round(R26*AD26,0) -> 0 | R26: 0 | S26: =round(M26-N26-P26-Q26,0) -> 2999 | T26: =S26/5 -> 599.8 | U26: =round(T26,-1) -> 600 | V26: =5*(T26-U26) -> -1 | W26: RON | AA26: Backline | AB26: 1000 | AD26: 1750
A27: 23 | B27: Privat | C27: Corporate | D27: Corpul diplomatic @ Bucuresti | G27: 19349 | H27: RON | I27: 6719 | J27: RON | K27: =round(G27*1%,0) -> 193 | L27: =sum(AB27+AD27+AF27+AH27+AJ27+AL27) -> 4500 | M27: =G27-K27-L27 -> 14656 | N27: =round(O27*M27+I27,0) -> 563 | O27: -0.42 | P27: =round(R27*(M27-N27),0) -> 1409 | Q27: =round(R27*AD27,0) -> 200 | R27: 0.1 | S27: =round(M27-N27-P27-Q27,0) -> 12484 | T27: =S27/5 -> 2496.8 | U27: =round(T27,-1) -> 2500 | V27: =5*(T27-U27) -> -16 | W27: RON | AA27: Backline | AB27: 1000 | AD27: 2000 | AF27: 1500
A28: Iulie
A29: 5 | B29: Privat | C29: Corporate | D29: Hotel Timisoara | E29: LifeCare | G29: 11392 | H29: RON | I29: 1257 | J29: RON | K29: =round(G29*1%,0) -> 114 | L29: =sum(AB29+AD29+AF29+AH29+AJ29+AL29) -> 2000 | M29: =G29-K29-L29 -> 9278 | N29: =round(O29*M29+I29,0) -> 2231 | O29: 0.105 | P29: =round(R29*(M29-N29),0) -> 705 | Q29: =round(R29*AD29,0) -> 100 | R29: 0.1 | S29: =round(M29-N29-P29-Q29,0) -> 6242 | T29: =S29/5 -> 1248.4 | U29: =round(T29,-1) -> 1250 | V29: =5*(T29-U29) -> -8 | W29: RON | AA29: Backline | AB29: 1000 | AD29: 1000
A30: 6 | B30: Privat | C30: Nunta | D30: Province | F30: 226 | G30: 4350 | H30: EUR | I30: 0 | J30: EUR | K30: =round(I30*1%,0) -> 0 | L30: =sum(AB30+AD30+AF30+AH30+AJ30+AL30) -> 1250 | M30: =G30-K30-L30 -> 3100 | N30: =round(O30*M30+I30,0) -> 589 | O30: 0.19 | P30: =round(R30*(M30-N30),0) -> 0 | Q30: =round(R30*AD30,0) -> 0 | R30: 0 | S30: =round(M30-N30-P30-Q30,0) -> 2511 | T30: =S30/5 -> 502.2 | U30: =round(T30,-1) -> 500 | V30: =5*(T30-U30) -> 11 | W30: EUR | AA30: Sistem de sunet | AB30: 400 | AD30: 200 | AF30: 50 | AG30: Flavius | AH30: 500 | AK30: Podium | AL30: 100
A31: August
A32: 16 | B32: Privat | C32: Nunta | D32: Convention Center @ Timisoara | F32: 207 | G32: 27771 | H32: RON | I32: 2585 | J32: RON | K32: =round(G32*1%,0) -> 278 | L32: =sum(AB32+AD32+AF32+AH32+AJ32+AL32) -> 8750 | M32: =G32-K32-L32 -> 18743 | N32: =round(O32*M32+I32,0) -> 4647 | O32: 0.11 | P32: =round(R32*(M32-N32),0) -> 1410 | Q32: =round(R32*AD32,0) -> 200 | R32: 0.1 | S32: =round(M32-N32-P32-Q32,0) -> 12486 | T32: =S32/5 -> 2497.2 | U32: =round(T32,-1) -> 2500 | V32: =5*(T32-U32) -> -14 | W32: RON | AA32: Sistem de sunet | AB32: 2000 | AD32: 2000 | AG32: Flavius | AH32: 2075 | AI32: Flavius | AJ32: 2075 | AK32: Podium | AL32: 600
A33: 30 | B33: Privat | C33: Nunta | D33: Hotel Tresor @ Timisoara | F33: 225 | G33: 3350 | H33: EUR | I33: 350 | J33: EUR | K33: =round(G33*1%,0) -> 34 | L33: =sum(AB33+AD33+AF33+AH33+AJ33+AL33) -> 400 | M33: =G33-K33-L33 -> 2916 | N33: =round(O33*M33+I33,0) -> 408 | O33: 0.02 | P33: =round(R33*(M33-N33),0) -> 0 | Q33: =round(R33*AD33,0) -> 0 | R33: 0 | S33: =round(M33-N33-P33-Q33,0) -> 2508 | T33: =S33/5 -> 501.6 | U33: =round(T33,-1) -> 500 | V33: =5*(T33-U33) -> 8 | W33: EUR | AA33: Backline | AB33: 200 | AD33: 200
A34: Septembrie
A35: 6 | B35: Privat | C35: Nunta | D35: Heaven Outdoor | F35: 237 | G35: 16250 | H35: RON | I35: 1750 | J35: RON | K35: =round(I35*1%,0) -> 18 | L35: =sum(AB35+AD35+AF35+AH35+AJ35+AL35) -> 4950 | M35: =G35-K35-L35 -> 11282 | N35: =round(O35*M35+I35,0) -> 3781 | O35: 0.18 | P35: =round(R35*(M35-N35),0) -> 0 | Q35: =round(R35*AD35,0) -> 0 | R35: 0 | S35: =round(M35-N35-P35-Q35,0) -> 7501 | T35: =S35/5 -> 1500.2 | U35: =round(T35,-1) -> 1500 | V35: =5*(T35-U35) -> 1 | W35: RON | AA35: Backline | AB35: 2250 | AD35: 2000 | AK35: Podium | AL35: 700
A36: 6 | B36: Public | C36: Scena Mare | D36: Giarmata | E36: Zilele Orasului | G36: 10000 | H36: RON | I36: 0 | J36: RON | K36: =round(G36*1%,0) -> 100 | L36: =sum(AB36+AD36+AF36+AH36+AJ36+AL36) -> 2500 | M36: =G36-K36-L36 -> 7400 | N36: =round(O36*M36+I36,0) -> 370 | O36: 0.05 | P36: =round(R36*(M36-N36),0) -> 703 | Q36: =round(R36*AD36,0) -> 100 | R36: 0.1 | S36: =round(M36-N36-P36-Q36,0) -> 6227 | T36: =S36/5 -> 1245.4 | U36: =round(T36,-1) -> 1250 | V36: =5*(T36-U36) -> -23 | W36: RON | AA36: Backline | AB36: 1000 | AD36: 1000 | AK36: in-ear + tobe | AL36: 500
A37: 13 | B37: Privat | C37: Nunta | D37: Continental | F37: 194 | G37: 3450 | H37: EUR | I37: 300 | J37: EUR | K37: =round(I37*1%,0) -> 3 | L37: =sum(AB37+AD37+AF37+AH37+AJ37+AL37) -> 400 | M37: =G37-K37-L37 -> 3047 | N37: =round(O37*M37+I37,0) -> 544 | O37: 0.08 | P37: =round(R37*(M37-N37),0) -> 0 | Q37: =round(R37*AD37,0) -> 0 | R37: 0 | S37: =round(M37-N37-P37-Q37,0) -> 2503 | T37: =S37/5 -> 500.6 | U37: =round(T37,-1) -> 500 | V37: =5*(T37-U37) -> 3 | W37: EUR | AA37: Backline | AB37: 200 | AD37: 200
A38: 20 | B38: Privat | C38: Nunta | D38: Palazzo Events | F38: 211 | G38: 19240 | H38: EUR | I38: 1740 | J38: RON | K38: =round(I38*1%,0) -> 17 | L38: =sum(AB38+AD38+AF38+AH38+AJ38+AL38) -> 2000 | M38: =G38-K38-L38 -> 17223 | N38: =round(O38*M38+I38,0) -> 4737 | O38: 0.174 | P38: =round(R38*(M38-N38),0) -> 0 | Q38: =round(R38*AD38,0) -> 0 | R38: 0 | S38: =round(M38-N38-P38-Q38,0) -> 12486 | T38: =S38/5 -> 2497.2 | U38: =round(T38,-1) -> 2500 | V38: =5*(T38-U38) -> -14 | W38: RON | AA38: Backline | AB38: 1000 | AD38: 1000
A39: 27 | B39: Privat | C39: Nunta | D39: Province | F39: 209 | G39: 5500 | H39: EUR | I39: 500 | J39: EUR | K39: =round(I39*1%,0) -> 5 | L39: =sum(AB39+AD39+AF39+AH39+AJ39+AL39) -> 1850 | M39: =G39-K39-L39 -> 3645 | N39: =round(O39*M39+I39,0) -> 1229 | O39: 0.2 | P39: =round(R39*(M39-N39),0) -> 0 | Q39: =round(R39*AD39,0) -> 0 | R39: 0 | S39: =round(M39-N39-P39-Q39,0) -> 2416 | T39: =S39/5 -> 483.2 | U39: =round(T39,-1) -> 480 | V39: =5*(T39-U39) -> 16 | W39: EUR | AA39: Sistem de sunet | AB39: 400 | AD39: 400 | AF39: 50 | AG39: Flavius | AH39: 400 | AI39: Flavius | AJ39: 500 | AK39: Podium | AL39: 100
A40: Octombrie
A41: 4 | B41: Privat | C41: Nunta | D41: Province | F41: 215 | G41: 4700 | H41: EUR | I41: 400 | J41: EUR | K41: =round(I41*1%,0) -> 4 | L41: =sum(AB41+AD41+AF41+AH41+AJ41+AL41) -> 1100 | M41: =G41-K41-L41 -> 3596 | N41: =round(O41*M41+I41,0) -> 1119 | O41: 0.2 | P41: =round(R41*(M41-N41),0) -> 0 | Q41: =round(R41*AD41,0) -> 0 | R41: 0 | S41: =round(M41-N41-P41-Q41,0) -> 2477 | T41: =S41/5 -> 495.4 | U41: =round(T41,-1) -> 500 | V41: =5*(T41-U41) -> -23 | W41: EUR | AA41: Sistem de sunet | AB41: 400 | AD41: 200 | AF41: 50 | AG41: Flavius | AH41: 450
A42: 11 | B42: Privat | C42: Nunta | D42: Queen Mary @ Oradea | F42: 232 | G42: 20614 | H42: RON | I42: 2026 | J42: RON | K42: =round(G42*1%,0) -> 206 | L42: =sum(AB42+AD42+AF42+AH42+AJ42+AL42) -> 3250 | M42: =G42-K42-L42 -> 17158 | N42: =round(O42*M42+I42,0) -> 3141 | O42: 0.065 | P42: =round(R42*(M42-N42),0) -> 1402 | Q42: =round(R42*AD42,0) -> 125 | R42: 0.1 | S42: =round(M42-N42-P42-Q42,0) -> 12490 | T42: =S42/5 -> 2498 | U42: =round(T42,-1) -> 2500 | V42: =5*(T42-U42) -> -10 | W42: RON | AA42: Backline | AB42: 1000 | AD42: 1250 | AF42: 1000
A43: 18 | B43: Public | C43: Scena Mare | D43: Shopping City | E43: Kuky | G43: 0 | H43: RON | I43: 0 | J43: RON | K43: 0 | L43: =sum(AB43+AD43+AF43+AH43+AJ43+AL43) -> 2500 | M43: =G43-K43-L43 -> -2500 | N43: -2500 | O43: 0 | P43: =round(R43*(M43-N43),0) -> 0 | Q43: =round(R43*AD43,0) -> 0 | R43: 0 | S43: =round(M43-N43-P43-Q43,0) -> 0 | T43: =S43/5 -> 0 | U43: =round(T43,-1) -> 0 | V43: =5*(T43-U43) -> 0 | W43: RON | AA43: Backline | AB43: 1000 | AD43: 1500
A44: Noiembrie
A45: 1 | B45: Privat | C45: Nunta | D45: Ivy | G45: 25000 | H45: RON | I45: 0 | J45: RON | K45: =round(I45*1%,0) -> 0 | L45: =sum(AB45+AD45+AF45+AH45+AJ45+AL45) -> 8750 | M45: =G45-K45-L45 -> 16250 | N45: =round(O45*M45+I45,0) -> 0 | O45: 0 | P45: =round(R45*(M45-N45),0) -> 0 | Q45: =round(R45*AD45,0) -> 0 | R45: 0 | S45: =round(M45-N45-P45-Q45,0) -> 16250 | T45: =S45/5 -> 3250 | U45: =round(T45,-1) -> 3250 | V45: =5*(T45-U45) -> 0 | W45: RON | AA45: Sistem de sunet | AB45: 2000 | AD45: 2000 | AG45: Flavius | AH45: 2250 | AI45: Flavius | AJ45: 2500
A46: Decembrie
A47: 12 | B47: Privat | C47: Corporate | D47: Congress Hall | E47: Porsche | G47: 2950 | H47: EUR | J47: EUR | K47: =round(G47*1%,0) -> 30 | L47: =sum(AB47+AD47+AF47+AH47+AJ47+AL47) -> 400 | M47: =G47-K47-L47 -> 2520 | N47: =round(O47*M47+I47,0) -> 252 | O47: 0.1 | P47: =round(R47*(M47-N47),0) -> 227 | Q47: =round(R47*AD47,0) -> 20 | R47: 0.1 | S47: =round(M47-N47-P47-Q47,0) -> 2021 | T47: =S47/5 -> 404.2 | U47: =round(T47,-1) -> 400 | V47: =5*(T47-U47) -> 21 | AA47: Backline | AB47: 200 | AD47: 200
A48: 18 | B48: Privat | C48: Corporate | D48: Stage Pub | E48: Vestmed | G48: 9161 | H48: RON | I48: 0 | J48: RON | K48: =round(G48*1%,0) -> 92 | L48: =sum(AB48+AD48+AF48+AH48+AJ48+AL48) -> 2000 | M48: =G48-K48-L48 -> 7069 | N48: =round(O48*M48+I48,0) -> 0 | O48: 0 | P48: =round(R48*(M48-N48),0) -> 707 | Q48: =round(R48*AD48,0) -> 100 | R48: 0.1 | S48: =round(M48-N48-P48-Q48,0) -> 6262 | T48: =S48/5 -> 1252.4 | U48: =round(T48,-1) -> 1250 | V48: =5*(T48-U48) -> 12 | AA48: Backline | AB48: 1000 | AD48: 1000
A49: 19 | B49: Public | C49: Concert Phaser | D49: Kai @ Timisoara | G49: 6000 | H49: RON | I49: 0 | J49: RON | K49: =round(G49*1%,0) -> 60 | L49: =sum(AB49+AD49+AF49+AH49+AJ49+AL49) -> 2000 | M49: =G49-K49-L49 -> 3940 | N49: =round(O49*M49+I49,0) -> 0 | O49: 0 | P49: =round(R49*(M49-N49),0) -> 394 | Q49: =round(R49*AD49,0) -> 100 | R49: 0.1 | S49: =round(M49-N49-P49-Q49,0) -> 3446 | T49: =S49/5 -> 689.2 | U49: =round(T49,-1) -> 690 | V49: =5*(T49-U49) -> -4 | AA49: Backline | AB49: 1000 | AD49: 1000
A50: 21 | B50: Public | C50: Scena Mare | D50: Muzeul Satului | E50: Targ de Craciun | G50: 10000 | H50: RON | I50: 0 | J50: RON | K50: =round(G50*1%,0) -> 100 | L50: =sum(AB50+AD50+AF50+AH50+AJ50+AL50) -> 2000 | M50: =G50-K50-L50 -> 7900 | N50: =round(O50*M50+I50,0) -> 790 | O50: 0.1 | P50: =round(R50*(M50-N50),0) -> 711 | Q50: =round(R50*AD50,0) -> 100 | R50: 0.1 | S50: =round(M50-N50-P50-Q50,0) -> 6299 | T50: =S50/5 -> 1259.8 | U50: =round(T50,-1) -> 1260 | V50: =5*(T50-U50) -> -1 | AA50: Backline | AB50: 1000 | AD50: 1000
A51: 31 | B51: Public | C51: Scena Mare | D51: Piata Victoriei | E51: Revelion | G51: 15000 | H51: RON | I51: 0 | J51: RON | K51: =round(G51*1%,0) -> 150 | L51: =sum(AB51+AD51+AF51+AH51+AJ51+AL51) -> 2000 | M51: =G51-K51-L51 -> 12850 | N51: =round(O51*M51+I51,0) -> 0 | O51: 0 | P51: =round(R51*(M51-N51),0) -> 1285 | Q51: =round(R51*AD51,0) -> 100 | R51: 0.1 | S51: =round(M51-N51-P51-Q51,0) -> 11465 | T51: =S51/5 -> 2293 | U51: =round(T51,-1) -> 2290 | V51: =5*(T51-U51) -> 15 | AA51: Backline | AB51: 1000 | AD51: 1000
A53: TEST | K53: =round(G53*1%,0) -> 0 | L53: =sum(AB53+AD53+AF53+AH53+AJ53+AL53) -> 0 | M53: =G53-K53-L53 -> 0 | N53: =round(O53*M53+I53,0) -> 0 | O53: 0.1 | P53: =round(R53*(M53-N53),0) -> 0 | Q53: =round(R53*AD53,0) -> 0 | R53: 0.1 | S53: =round(M53-N53-P53-Q53,0) -> 0 | T53: =S53/5 -> 0 | U53: =round(T53,-1) -> 0 | V53: =5*(T53-U53) -> 0

Sheet Onorariu Artist 2025
F1: Onorariu Artist
A2: Data | B2: Tip Event | C2: Specific | D2: Locatie | E2: Descriere | F2: POSIBIL | G2: REAL | H2: Valuta | I2: Carina | J2: Arni | K2: Radu | L2: Sebi | M2: Luci
A3: Ianuarie
A4: 13 | B4: Public | C4: Concert Phaser | D4: Livigno @ Italia | E4: Snow Fest Italia | F4: 0 | G4: 0 | H4: RON | I4: 0 | J4: 0 | K4: 0 | L4: 0 | M4: 0
A5: 15 | B5: Public | C5: Concert Phaser | D5: Livigno @ Italia | E5: Snow Fest Italia | F5: 0 | G5: 0 | H5: RON | I5: 0 | J5: 0 | K5: 0 | L5: 0 | M5: 0
A6: 31 | B6: Public | C6: Concert Phaser | D6: Kai @ Timisoara | F6: 530 | G6: 700 | H6: RON | I6: 700 | J6: 700 | K6: 700 | L6: 700 | M6: 700
A7: Februarie
A8: Martie
A9: 26 | B9: Public | C9: Concert Phaser | D9: Les Deux Alps @ Franta | E9: Snow Fest Franta | F9: 200 | G9: 200 | H9: EUR | I9: 100 | J9: 100 | K9: 100 | L9: 200 | M9: 100
A10: 31 | B10: Public | C10: Concert Phaser | D10: Val Thorens @ Franta | E10: Snow Fest Franta | F10: 200 | G10: 200 | H10: EUR | I10: 100 | J10: 200 | K10: 100 | L10: 200 | M10: 100
A11: Aprilie
A12: 12 | B12: Public | C12: Extra | D12: Plaja Noua | E12: Targ de nunti | F12: 0 | G12: 0 | H12: RON | I12: 0 | J12: 0 | K12: 0 | L12: 0 | M12: 0
A13: 12 | B13: Public | C13: Scena Mare | D13: Timisoara | E13: Targul de Pasti | F13: 1400 | G13: 1200 | H13: RON | I13: 1200 | J13: 1200 | K13: 1200 | L13: 1200 | M13: 1200
A14: Mai
A15: 2 | B15: Privat | C15: Nunta | D15: Domeniile Streiului | F15: 2930 | G15: 2500 | H15: RON | I15: 2500 | J15: 2500 | K15: 2500 | L15: 2500 | M15: 2500
A16: 11 | B16: Privat | C16: Nunta | D16: Province | F16: 2710 | G16: 2500 | H16: RON | I16: 2500 | J16: 2500 | K16: 2500 | L16: 2500 | M16: 2500
A17: 23 | B17: Privat | C17: Botez | D17: Villa Trevi | F17: 620 | G17: 550 | H17: EUR | I17: 550 | J17: 550 | K17: 550 | L17: 550 | M17: 550
A18: 24 | B18: Privat | C18: Nunta | D18: Ivy Events | F18: 610 | G18: 500 | H18: EUR | I18: 500 | J18: 500 | K18: 500 | L18: 500 | M18: 500
A19: 30 | B19: Privat | C19: Nunta | D19: Flonta LakeSide | F19: 500 | G19: 500 | H19: EUR | I19: 500 | J19: 500 | K19: 500 | L19: 500 | M19: 500
A20: 31 | B20: Privat | C20: Nunta | D20: Timeea @ Resita | F20: 590 | G20: 500 | H20: EUR | I20: 500 | J20: 500 | K20: 500 | L20: 500 | M20: 500
A21: Iunie
A22: 8 | B22: Public | C22: Concert Phaser | D22: Bastion | F22: 690 | G22: 700 | H22: RON | I22: 700 | J22: 700 | K22: 700 | L22: 700 | M22: 700
A23: 14 | B23: Privat | C23: Nunta | D23: Riviere Ballroom | F23: 2770 | G23: 2500 | H23: RON | I23: 2500 | J23: 2500 | K23: 2500 | L23: 2500 | M23: 2500
A24: 17 | B24: Privat | C24: Corporate | D24: Sky Restaurant | F24: 1500 | G24: 1500 | H24: RON | I24: 1500 | J24: 1500 | K24: 1500 | L24: 1500 | M24: 1500
A25: 21 | B25: Public | C25: Scena Mare | D25: Timisoara | F25: 1400 | G25: 1200 | H25: RON | I25: 1200 | J25: 1200 | K25: 1200 | L25: 1200 | M25: 1200
A26: 22 | B26: Public | C26: Scena Mare | D26: Muzeul Satului | E26: Flight Festival | F26: 640 | G26: 600 | H26: RON | I26: 600 | J26: 600 | K26: 600 | L26: 600 | M26: 600
A27: 23 | B27: Privat | C27: Corporate | D27: Corpul diplomatic @ Bucuresti | F27: 2526 | G27: 2500 | H27: RON | I27: 2500 | J27: 2500 | K27: 2500 | L27: 2500 | M27: 2500
A28: Iulie
A29: 5 | B29: Privat | C29: Corporate | D29: Hotel Timisoara | F29: 1420 | G29: 1250 | H29: RON | I29: 1250 | J29: 1250 | K29: 1250 | L29: 1250 | M29: 1250
A30: 6 | B30: Privat | C30: Nunta | D30: Province | F30: 610 | G30: 500 | H30: EUR | I30: 500 | J30: 500 | K30: 500 | L30: 500 | M30: 500
A31: August
A32: 16 | B32: Privat | C32: Nunta | D32: Convention Center @ Timisoara | F32: 2870 | G32: 2500 | H32: RON | I32: 2500 | J32: 2500 | K32: 2500 | L32: 2500 | M32: 2500
A33: 30 | B33: Privat | C33: Nunta | D33: Hotel Tresor @ Timisoara | F33: 570 | G33: 500 | H33: EUR | I33: 500 | J33: 500 | K33: 500 | L33: 500 | M33: 500
A34: Septembrie
A35: 6 | B35: Privat | C35: Nunta | D35: Heaven Outdoor | F35: 1910 | G35: 1500 | H35: RON | I35: 1500 | J35: 1500 | K35: 1500 | L35: 1500 | M35: 1500
A36: 6 | B36: Public | C36: Scena Mare | D36: Giarmata | E36: Zilele Giarmata | F36: 1310 | G36: 1250 | H36: RON | I36: 1250 | J36: 1250 | K36: 1250 | L36: 1250 | M36: 1250
A37: 13 | B37: Privat | C37: Nunta | D37: Continental | F37: 550 | G37: 500 | H37: EUR | I37: 500 | J37: 500 | K37: 500 | L37: 500 | M37: 500
A38: 20 | B38: Privat | C38: Nunta | D38: Palazzo Events | F38: 3100 | G38: 2500 | H38: RON | I38: 2500 | J38: 2500 | K38: 2500 | L38: 2500 | M38: 2500
A39: 27 | B39: Privat | C39: Nunta | D39: Province | F39: 650 | G39: 500 | H39: EUR | I39: 500 | J39: 500 | K39: 500 | L39: 500 | M39: 500
A40: Octombrie
A41: 4 | B41: Privat | C41: Nunta | D41: Province | F41: 530 | G41: 500 | H41: EUR | I41: 500 | J41: 500 | K41: 500 | L41: 500 | M41: 500
A42: 11 | B42: Privat | C42: Nunta | D42: Queen Mary @ Oradea | F42: 520 | G42: 500 | H42: EUR | I42: 500 | J42: 500 | K42: 500 | L42: 500 | M42: 500
A43: 18 | B43: Public | C43: Scena Mare | D43: Shopping City | E43: Kuky | F43: 0 | G43: 0 | H43: RON | I43: 0 | J43: 0 | K43: 0 | L43: 0 | M43: 0
A44: Noiembrie
A45: 1 | B45: Privat | C45: Nunta | D45: Ivy | F45: 3250 | G45: 3250 | H45: RON | I45: 3250 | J45: 3250 | K45: 3250 | L45: 3250 | M45: 3250
A46: Decembrie

Sheet Situatie 2025
A1: Venituri RON | B1: =SUMIF('Tranzactii 2025'!H:H,'Tranzactii 2025'!H4,'Tranzactii 2025'!G:G) -> 395227.4 | E1: Total Events | F1: =COUNT('Evenimente 2025'!A:A) -> 37 | L1: Eur | M1: 5
A2: Venituri EUR | B2: =sumif('Tranzactii 2025'!H:H,'Tranzactii 2025'!H95,'Tranzactii 2025'!G:G) -> 29750
A3: Cheltuieli RON | B3: =SUMIF('Tranzactii 2025'!C:C,'Tranzactii 2025'!C4,'Tranzactii 2025'!B:B) -> 386524.11 | E3: Public | F3: =countif('Evenimente 2025'!B:B,E3) -> 14
A4: Cheltuieli EUR | B4: =sumif('Tranzactii 2025'!C:C,'Tranzactii 2025'!C98,'Tranzactii 2025'!B:B) -> 29750 | E4: Concert Phaser | F4: =COUNTIF('Evenimente 2025'!C:C,E4) -> 7
A5: Retrageri | B5: =sum('Tranzactii 2025'!L:L) -> 244150 | C5: ron | E5: Scena mare | F5: =COUNTIF('Evenimente 2025'!C:C,E5) -> 7
A6: Depuneri | B6: =sum('Tranzactii 2025'!N:N) -> 32400 | C6: ron
A9: Recuperari | B9: ='DatoriiRecuperari 2025'!A14 -> 0 | E9: Privat | F9: =COUNTIF('Evenimente 2025'!B:B,E9) -> 23
A10: Datorii | B10: ='DatoriiRecuperari 2025'!A2 -> 2400 | E10: Nunta | F10: =COUNTIF('Evenimente 2025'!C:C,E10) -> 16
E11: Corporate | F11: =countif('Evenimente 2025'!C:C,E11) -> 5
A12: Balanta RON | B12: =B1-B3 -> 8703.29 | E12: Aniversare | F12: =COUNTIF('Evenimente 2025'!C:C,E12) -> 0
A13: Balanta EUR | B13: =B2-B4 -> 0 | C13: =B13*M1 -> 0
A14: Balanta | B14: =B12+C13 -> 8703.29 | C14: ron
A15: Total w.datorii&recuperari | B15: =B14-B10+B9 -> 6303.29 | C15: ron | E15: Extra | F15: =COUNTIF('Evenimente 2025'!C:C,E15) -> 1
A19: Onorariu Real 2025 RON | B19: =SUMIF('Onorariu Artist 2025'!H:H,'Onorariu Artist 2025'!H5,'Onorariu Artist 2025'!G:G) -> 28150
A20: Onorariu Real 2025 EUR | B20: =sumif('Onorariu Artist 2025'!H:H,'Onorariu Artist 2025'!H10,'Onorariu Artist 2025'!G:G) -> 5450
A21: Total Onorariu Real 2024 | B21: =round(B20+B19/M1,0) -> 11080 | C21: euro | E21: Comision Retrageri | F21: =SUMIF('Tranzactii 2025'!D:D,"Comision Retrageri",'Tranzactii 2025'!B:B) -> 593.35
E22: Comision Operatiune | F22: =SUMIF('Tranzactii 2025'!D:D,"Comision Operatiune",'Tranzactii 2025'!B:B) -> 114.02
A23: Total Onorariu Posibil 2025 RON | B23: =sumif('Onorariu Artist 2025'!H:H,'Onorariu Artist 2025'!H4,'Onorariu Artist 2025'!F:F) -> 30956 | E23: Salariu | F23: =SUMIF('Tranzactii 2025'!D:D,"Salariu",'Tranzactii 2025'!B:B) -> 21139
A24: Total Onorariu Posibil 2025 EUR | B24: =sumif('Onorariu Artist 2025'!H:H,'Onorariu Artist 2025'!H10,'Onorariu Artist 2025'!F:F) -> 6150 | E24: TVA | F24: =SUMIF('Tranzactii 2025'!D:D,"TVA",'Tranzactii 2025'!B:B) -> 291
A25: Total Onorariu Posibil 2025 | B25: =round(B24+B23/M1,0) -> 12341 | C25: euro | E25: ING Card | F25: =SUMIF('Tranzactii 2025'!D:D,"ING Card",'Tranzactii 2025'!B:B) -> 400
E26: Drive | F26: =SUMIF('Tranzactii 2025'!D:D,"Drive",'Tranzactii 2025'!B:B) -> 838.94
A29: Momentan
A30: In banca
A31: Cash

Sheet Tranzactii 2025
B1: Cheltuieli | G1: Venituri | L1: Retrageri | N1: Depuneri
A2: Data | B2: Suma | C2: Valuta | D2: Categorie | E2: Descriere | F2: Mod | G2: Suma | H2: Valuta | I2: Categorie | J2: Descriere | K2: Mod | L2: Suma | M2: Descriere | N2: Suma | O2: Descriere
A3: 45660 | B3: 71.01 | C3: Ron | D3: Drive | F3: Banca
A4: 45663 | B4: 2500 | C4: Ron | D4: Arni | E4: suceava | F4: Cash | G4: 21140.4 | H4: Ron | I4: Altele | J4: Sold initial 2025 | L4: 5000
B5: 2500 | C5: Ron | D5: Carina | E5: suceava | F5: Cash | L5: 4000
B6: 16 | C6: Ron | D6: Comision Retrageri | F6: Banca
A7: 45665 | B7: 200 | C7: Ron | D7: Radu | E7: recuperare cantare concert fitt | F7: Cash | G7: 22138 | H7: Ron | I7: Event | J7: ranking coach | K7: Banca | L7: 3000
B8: 9500 | C8: Ron | D8: Sebi | E8: Cantari dec 2024 | F8: Cash | L8: 5000
B9: 40 | C9: Ron | D9: Comision Retrageri | F9: Banca | L9: 2000
A11: 45666 | B11: 20 | C11: Ron | D11: Comision Retrageri | F11: Banca | G11: 15668 | H11: Ron | I11: Event | J11: rotary | K11: Banca | L11: 5000
B12: 16 | C12: Ron | D12: Comision Retrageri | F12: Banca | L12: 4000
B13: 12 | C13: Ron | D13: Comision Retrageri | F13: Banca | L13: 3000
B14: 20 | C14: Ron | D14: Comision Retrageri | F14: Banca | L14: 5000
B15: 8 | C15: Ron | D15: Comision Retrageri | F15: Banca | L15: 2000
B16: 1250 | C16: Ron | D16: Prezent | F16: Banca
B17: 11840 | C17: Ron | D17: Lumini | E17: Flavius | F17: Cash
B18: 0.45 | C18: Ron | D18: Comision Operatiune | F18: Banca
A19: 45668 | B19: 20 | C19: Ron | D19: Comision Retrageri | F19: Banca | L19: 5000
B20: 16 | C20: Ron | D20: Comision Retrageri | F20: Banca | L20: 4000
A21: 45677 | B21: 7.6 | C21: Ron | D21: Comision Retrageri | F21: Banca | L21: 1900
A22: 45679 | B22: 3200 | C22: Ron | D22: Protocol | E22: livigno | F22: Cash | G22: 9950 | H22: Ron | I22: Event | J22: fitt 2024 | K22: Banca
B23: 700 | C23: Ron | D23: Radu | E23: kai | F23: Cash
B24: 700 | C24: Ron | D24: Radu | E24: soho | F24: Cash
B25: 2000 | C25: Ron | D25: Radu | E25: province | F25: Cash
B26: 2000 | C26: Ron | D26: Radu | E26: rotary | F26: Cash
B27: 2500 | C27: Ron | D27: Radu | E27: tg jiu | F27: Cash
B28: 2500 | C28: Ron | D28: Arni | E28: revelion | F28: Cash
B29: 1000 | C29: Ron | D29: Arni | E29: parte din tg jiu | F29: Cash
A30: 45684 | B30: 4011 | C30: Ron | D30: Salariu | F30: Banca | L30: 4000
B31: 0.51 | C31: Ron | D31: Comision Operatiune | F31: Banca
B32: 231 | C32: Ron | D32: Salariu | F32: Banca
B33: 0.51 | C33: Ron | D33: Comision Operatiune | F33: Banca
B34: 13 | C34: Ron | D34: TVA | F34: Banca
B35: 0.51 | C35: Ron | D35: Comision Operatiune | F35: Banca
B36: 16 | C36: Ron | D36: Comision Retrageri | F36: Banca
A37: 45686 | B37: 12 | C37: Ron | D37: Comision Retrageri | F37: Banca | L37: 3000
A38: 45687 | B38: 4200 | C38: Ron | D38: Contabila | F38: Banca
A39: 45688 | B39: 40 | C39: Ron | D39: ING Card | F39: Banca
B40: 500 | C40: Ron | D40: Tehnici | F40: Cash
B41: 500 | C41: Ron | D41: Tehnici | F41: Cash
B42: 50 | C42: Ron | D42: Tehnici | F42: Cash
A45: 45691 | B45: 71.07 | C45: Ron | D45: Drive | F45: Banca | L45: 2500
A46: 45693 | L46: 2000
A47: 45698 | B47: 700 | C47: Ron | D47: Carina | E47: kai ian 2025 | F47: Cash | L47: 4500
B48: 1400 | C48: Ron | D48: Carina | E48: kai + soho 2024 | F48: Cash
B49: 2500 | C49: Ron | D49: Carina | E49: revelion resita 2024 | F49: Cash
B50: 18 | C50: Ron | D50: Comision Retrageri | F50: Banca
A51: 45701 | B51: 1500 | C51: Ron | D51: Arni | E51: parte din tg jiu | F51: Cash | L51: 3000
B52: 300 | C52: Ron | D52: Arni | E52: benzina 2024 | F52: Cash
B53: 200 | C53: Ron | D53: Arni | E53: internet 2024 | F53: Cash
B54: 2500 | C54: Ron | D54: Luci | E54: suceava 2024 | F54: Cash
B55: 2500 | C55: Ron | D55: Luci | E55: revelion 2024 | F55: Cash
B56: 2500 | C56: Ron | D56: Luci | E56: tg jiu 2024 | F56: Cash
B57: 500 | C57: Ron | D57: Luci | E57: parte din kai 2024 noiembrie | F57: Cash
B58: 50 | C58: Ron | D58: Luci | E58: parte din rotary 2024 | F58: Cash
B59: 700 | C59: Ron | D59: Luci | E59: soho resita 2024 | F59: Cash
B60: 12 | C60: Ron | D60: Comision Retrageri | F60: Banca
A61: 45702 | B61: 24 | C61: Ron | D61: Comision Retrageri | F61: Banca | G61: 6000 | H61: Ron | I61: Event | J61: kai 2024 noi | K61: Banca | L61: 6000
A62: 45703 | B62: 1250 | C62: Ron | D62: Sebi | E62: casa tineretului 2024 | F62: Cash
B63: 700 | C63: Ron | D63: Sebi | E63: soho resita 2024 | F63: Cash
B64: 2000 | C64: Ron | D64: Sebi | E64: rotary resita 2024 | F64: Cash
B65: 700 | C65: Ron | D65: Sebi | E65: kai noiembrie 2024 | F65: Cash
B66: 700 | C66: Ron | D66: Sebi | E66: kai ianuarie 2025 | F66: Cash
B67: 200 | C67: Ron | D67: Promo Meta | F67: Cash
A68: 45704 | B68: 1250 | C68: Ron | D68: Carina | E68: casa tineretului 2024 | F68: Cash
B69: 300 | C69: Ron | D69: Radu | E69: Parte din kai noiembrie 2024 | F69: Cash
B71: 2000 | C71: Ron | D71: Carina | E71: rotoray | F71: Cash
B72: 2500 | C72: Ron | D72: Carina | E72: tg jiu | F72: Cash
B73: 2000 | C73: Ron | D73: Carina | E73: province | F73: Cash
A74: 45705 | B74: 1.2 | C74: Ron | D74: Comision Retrageri | F74: Banca | L74: 300
A75: 45712 | B75: 20 | C75: Ron | D75: Comision Retrageri | F75: Banca | G75: 16552 | H75: Ron | I75: Event | J75: resita revelion | L75: 5000
B76: 16 | C76: Ron | D76: Comision Retrageri | F76: Banca | L76: 4000
A77: 45713 | B77: 20 | C77: Ron | D77: Comision Retrageri | F77: Banca | L77: 5000
A78: 45715 | G78: 1742 | H78: Ron | I78: Avans | J78: avans nunta 30.08.2025
A79: 45716 | B79: 40 | C79: Ron | D79: ING Card | F79: Banca
B80: 150 | C80: Ron | D80: Altele | E80: roata carut | F80: Banca
A83: 45719 | B83: 71.07 | C83: Ron | D83: Drive | F83: Banca
A84: 45721 | B84: 13 | C84: Ron | D84: TVA | F84: Banca
B85: 0.51 | C85: Ron | D85: Comision Operatiune | F85: Banca
A86: 45724 | G86: 1742 | H86: Ron | I86: Avans | J86: avans nunta 11.05.2025 | L86: 3500
A87: 45730 | B87: 8.8 | C87: Ron | D87: Comision Retrageri | F87: Banca | L87: 2200
A88: 45734 | G88: 6000 | H88: Ron | I88: Event | J88: kai ianuarie
A89: 45735 | B89: 24 | C89: Ron | D89: Comision Retrageri | F89: Banca | L89: 6000
A90: 45737 | B90: 4400 | C90: Ron | D90: Arni | E90: tehnic arni | F90: Cash | G90: 1741 | H90: Ron | I90: Avans | J90: avans nunta 30.05.2025
B91: 100 | C91: Ron | D91: Arni | E91: arni internet | G91: 2200 | H91: Ron | I91: Altele | J91: recuperare cinele
B92: 700 | C92: Ron | D92: Luci | E92: kai ianuarie 2025 | F92: Cash
B93: 700 | C93: Ron | D93: Carina | E93: kai ianuarie 2025 | F93: Cash
A94: 45744 | B94: 0.45 | C94: Ron | D94: Comision Operatiune | F94: Banca | L94: 1500
A95: 45747 | B95: 13 | C95: Ron | D95: TVA | F95: Banca | G95: 1400 | H95: Euro | I95: Event | J95: VT + Les2Alpes
B96: 0.51 | C96: Ron | D96: Comision Operatiune | F96: Banca
B97: 40 | C97: Ron | D97: ING Card | F97: Banca
B98: 400 | C98: Euro | D98: Sebi | E98: concerte snow
B99: 300 | C99: Euro | D99: Arni | E99: concerte snow
B100: 300 | C100: Euro | D100: Radu | E100: concerte snow
B101: 200 | C101: Euro | D101: Luci | E101: concerte snow
B102: 200 | C102: Euro | D102: Carina | E102: concerte snow
B103: 700 | C103: Ron | D103: Radu | E103: kai ianuarie 2025 | F103: Cash
B104: 400 | C104: Ron | D104: Radu | E104: parte kai noiembrie | F104: Cash
B105: 700 | C105: Ron | D105: Radu | E105: soho resita 2024 | F105: Cash
B106: 2000 | C106: Ron | D106: Radu | E106: rotary resita 2024 | F106: Cash
...

Sheet DatoriiRecuperari 2025
A1: TOTAL DATORII | C1: Datorie Prezent | G1: Datorii persoane | H1: Carina Social 2025 | K1: Alte datorii | N1: Recuperari
A2: =A5+A8+A11 -> 2400 | H2: Arni Tehnic | I2: 2400
A4: Total Prezent
A5: =sum(E:E) -> 0
A7: Total Pesoane
A8: =sum(I:I) -> 2400
A10: Total alte datorii
A11: =sum(L:L) -> 0
A13: TOTAL RECUPERARI
A14: =sum(P:P) -> 0

Sheet Situatie 2024
A1: Venituri RON | B1: =SUMIF('Tranzactii 2024'!H:H,'Tranzactii 2024'!H3,'Tranzactii 2024'!G:G) -> 395162.23 | E1: Total Events | F1: =COUNT('Evenimente 2024'!A:A) -> 48 | L1: Eur | M1: 4.9
A2: Venituri EUR | B2: =sumif('Tranzactii 2024'!H:H,'Tranzactii 2024'!H24,'Tranzactii 2024'!G:G) -> 43940
A3: Cheltuieli RON | B3: =SUMIF('Tranzactii 2024'!C:C,'Tranzactii 2024'!C3,'Tranzactii 2024'!B:B) -> 374021.83 | E3: Public | F3: =countif('Evenimente 2024'!B:B,E3) -> 23
A4: Cheltuieli EUR | B4: =sumif('Tranzactii 2024'!C:C,'Tranzactii 2024'!C24,'Tranzactii 2024'!B:B) -> 43940 | E4: Concert Phaser | F4: =COUNTIF('Evenimente 2024'!C:C,E4) -> 12
A5: Retrageri | B5: =sum('Tranzactii 2024'!L:L) -> 233490 | C5: ron | E5: Scena mare | F5: =COUNTIF('Evenimente 2024'!C:C,E5) -> 8
A6: Depuneri | B6: =sum('Tranzactii 2023'!N:N) -> 4750 | C6: ron
A9: Recuperari | B9: ='DatoriiRecuperari 2024'!A14 -> 0 | E9: Privat | F9: =COUNTIF('Evenimente 2024'!B:B,E9) -> 25
A10: Datorii | B10: ='DatoriiRecuperari 2024'!A2 -> 0 | E10: Nunta | F10: =COUNTIF('Evenimente 2024'!C:C,E10) -> 17
E11: Corporate | F11: =countif('Evenimente 2024'!C:C,E11) -> 7
A12: Balanta RON | B12: =B1-B3 -> 21140.4 | E12: Aniversare | F12: =COUNTIF('Evenimente 2024'!C:C,E12) -> 0
A13: Balanta EUR | B13: =B2-B4 -> 0 | C13: =B13*M1 -> 0
A14: Balanta | B14: =B12+C13 -> 21140.4 | C14: ron
A15: Total w.datorii&recuperari | B15: =B14-B10+B9 -> 21140.4 | C15: ron | E15: Extra | F15: =COUNTIF('Evenimente 2024'!C:C,E15) -> 3
A19: Onorariu Real 2024 RON | B19: =SUMIF('Onorariu Artist 2024'!H:H,'Onorariu Artist 2024'!H5,'Onorariu Artist 2024'!G:G) -> 37400
A20: Onorariu Real 2024 EUR | B20: =sumif('Onorariu Artist 2024'!H:H,'Onorariu Artist 2024'!H4,'Onorariu Artist 2024'!G:G) -> 6850
A21: Total Onorariu Real 2024 | B21: =round(B20+B19/M1,0) -> 14483 | C21: euro | E21: Comision Retrageri | F21: =SUMIF('Tranzactii 2024'!D:D,"Comision Retrageri",'Tranzactii 2024'!B:B) -> 749.25
E22: Comision Operatiune | F22: =SUMIF('Tranzactii 2024'!D:D,"Comision Operatiune",'Tranzactii 2024'!B:B) -> 15.33
A23: Total Onorariu Posibil 2024 RON | B23: =sumif('Onorariu Artist 2024'!H:H,'Onorariu Artist 2024'!H5,'Onorariu Artist 2024'!F:F) -> 41070 | E23: Salariu | F23: =SUMIF('Tranzactii 2024'!D:D,"Salariu",'Tranzactii 2024'!B:B) -> 16644
A24: Total Onorariu Posibil 2024 EUR | B24: =sumif('Onorariu Artist 2024'!H:H,'Onorariu Artist 2024'!H4,'Onorariu Artist 2024'!F:F) -> 7300 | E24: TVA | F24: =SUMIF('Tranzactii 2024'!D:D,"TVA",'Tranzactii 2024'!B:B) -> 669
A25: Total Onorariu Posibil 2024 | B25: =round(B24+B23/M1,0) -> 15682 | C25: euro | E25: ING Card | F25: =SUMIF('Tranzactii 2024'!D:D,"ING Card",'Tranzactii 2024'!B:B) -> 415
E26: Drive | F26: =SUMIF('Tranzactii 2024'!D:D,"Drive",'Tranzactii 2024'!B:B) -> 2157.05
A29: Momentan
A30: In banca | B30: =#REF!+B31+B32 -> #REF!
A31: Cash

Sheet Evenimente 2024
AA1: Cheltuieli
A2: Data | B2: Tip Event | C2: Specific | D2: Locatie | E2: Descriere | F2: Nr. Ctr. | G2: Total | H2: Valuta | I2: Avans | J2: Valuta | K2: 0.01 | L2: TCH | M2: Profit | N2: Fond | O2: %fond | P2: DivPH | Q2: AlteDiv | R2: %DIV | S2: Phaser | T2: Calcul Artist | U2: Artist Real | V2: Restul | W2: Valuta | Y2: Detalii | AA2: Prezent | AB2: Pret | AC2: Tehnici | AD2: Pret | AE2: Drum | AF2: Pret | AG2: Lumini | AH2: Pret | AI2: DJ | AJ2: Pret | AK2: Extra | AL2: Pret
A3: Ianuarie
A4: 27 | B4: Privat | C4: Nunta | D4: Flonta (Lakeside) | F4: 192 | G4: 3300 | H4: EUR | I4: 300 | J4: EUR | K4: =round(I4*1%,0) -> 3 | L4: =sum(AB4+AD4+AF4+AH4+AJ4+AL4) -> 350 | M4: =G4-K4-L4 -> 2947 | N4: =round(O4*M4+I4,0) -> 447 | O4: 0.05 | P4: =round(R4*(M4-N4),0) -> 0 | Q4: =round(R4*AD4,0) -> 0 | R4: 0 | S4: =round(M4-N4-P4-Q4,0) -> 2500 | T4: =S4/5 -> 500 | U4: =round(T4,-1) -> 500 | V4: =5*(T4-U4) -> 0 | W4: RON | AA4: Sunet Full | AB4: 350
A5: 29 | B5: Public | C5: Extra | D5: Radio Resita | E5: Concert in Studio Radio Resita | G5: 0 | H5: RON | I5: 0 | J5: RON | K5: =round(G5*1%,0) -> 0 | L5: =sum(AB5+AD5+AF5+AH5+AJ5+AL5) -> 250 | M5: =G5-K5-L5 -> -250 | N5: =round(O5*M5+I5,0) -> 0 | O5: 0 | P5: =round(R5*(M5-N5),0) -> 0 | Q5: =round(R5*AD5,0) -> 0 | R5: 0 | S5: =round(M5-N5-P5-Q5,0) -> -250 | T5: 0 | U5: 0 | V5: =5*(T5-U5) -> 0 | W5: RON | AA5: Backline | AB5: 0 | AC5: Misu Aurel | AD5: 250
A6: Februarie
A7: 2 | B7: Public | C7: Concert Phaser | D7: Kai @ Timisoara | G7: 6000 | H7: RON | I7: 0 | J7: RON | K7: =round(G7*1%,0) -> 60 | L7: =sum(AB7+AD7+AF7+AH7+AJ7+AL7) -> 2750 | M7: =G7-K7-L7 -> 3190 | N7: =round(O7*M7+I7,0) -> 0 | O7: 0 | P7: =round(R7*(M7-N7),0) -> 319 | Q7: =round(R7*AD7,0) -> 125 | R7: 0.1 | S7: =round(M7-N7-P7-Q7,0) -> 2746 | T7: =S7/5 -> 549.2 | U7: 600 | V7: =5*(T7-U7) -> -254 | W7: RON | AA7: Backline | AB7: 1000 | AC7: marcel + levi | AD7: 1250 | AK7: Dean | AL7: 500
A8: 29 | B8: Public | C8: Concert Phaser | D8: Flying Circus @ Cluj | G8: 0 | H8: RON | I8: 0 | J8: RON | K8: =round(G8*1%,0) -> 0 | L8: =sum(AB8+AD8+AF8+AH8+AJ8+AL8) -> 750 | M8: =G8-K8-L8 -> -750 | N8: =round(O8*M8+I8,0) -> 0 | O8: 0 | P8: =round(R8*(M8-N8),0) -> 0 | Q8: =round(R8*AD8,0) -> 0 | R8: 0 | S8: =round(M8-N8-P8-Q8,0) -> -750 | T8: =S8/5 -> -150 | U8: 0 | V8: =5*(T8-U8) -> -750 | W8: RON | AA8: Backline | AB8: 0 | AC8: levi | AD8: 750
A9: Martie
A10: 1 | B10: Public | C10: Extra | D10: Radio Tg Mures | G10: 0 | H10: RON | I10: 0 | J10: RON | K10: =round(G10*1%,0) -> 0 | L10: =sum(AB10+AD10+AF10+AH10+AJ10+AL10) -> 750 | M10: =G10-K10-L10 -> -750 | N10: =round(O10*M10+I10,0) -> 0 | O10: 0 | P10: =round(R10*(M10-N10),0) -> 0 | Q10: =round(R10*AD10,0) -> 0 | R10: 0 | S10: =round(M10-N10-P10-Q10,0) -> -750 | T10: =S10/5 -> -150 | U10: 0 | V10: =5*(T10-U10) -> -750 | W10: RON | AA10: Backline | AB10: 0 | AC10: levi | AD10: 750
A11: 1 | B11: Public | C11: Concert Phaser | D11: Republic Hub @ Tg Mures | G11: 880 | H11: RON | I11: 0 | J11: RON | K11: 0 | L11: =sum(AB11+AD11+AF11+AH11+AJ11+AL11) -> 750 | M11: =G11-K11-L11 -> 130 | N11: =round(O11*M11+I11,0) -> 0 | O11: 0 | P11: =round(R11*(M11-N11),0) -> 0 | Q11: =round(R11*AD11,0) -> 0 | R11: 0 | S11: =round(M11-N11-P11-Q11,0) -> 130 | T11: =S11/5 -> 26 | U11: 0 | V11: =5*(T11-U11) -> 130 | W11: RON | AA11: Backline | AB11: 0 | AC11: levi | AD11: 750
A12: 2 | B12: Public | C12: Concert Phaser | D12: NooVo @ Oradea | G12: 1000 | H12: RON | I12: 0 | J12: RON | K12: 0 | L12: =sum(AB12+AD12+AF12+AH12+AJ12+AL12) -> 750 | M12: =G12-K12-L12 -> 250 | N12: =round(O12*M12+I12,0) -> 0 | O12: 0 | P12: =round(R12*(M12-N12),0) -> 0 | Q12: =round(R12*AD12,0) -> 0 | R12: 0 | S12: =round(M12-N12-P12-Q12,0) -> 250 | T12: =S12/5 -> 50 | U12: 0 | V12: =5*(T12-U12) -> 250 | W12: RON | AA12: Backline | AB12: 0 | AC12: levi | AD12: 750
A13: 8 | B13: Public | C13: Concert Phaser | D13: Soho @ Resita | F13: 197 | G13: 7000 | H13: RON | I13: 2000 | J13: RON | K13: =round(G13*1%,0) -> 70 | L13: =sum(AB13+AD13+AF13+AH13+AJ13+AL13) -> 4210 | M13: =G13-K13-L13 -> 2720 | N13: 0 | O13: 0 | P13: =round(R13*(M13-N13),0) -> 0 | Q13: =round(R13*AD13,0) -> 0 | R13: 0 | S13: =round(M13-N13-P13-Q13,0) -> 2720 | T13: =S13/5 -> 544 | U13: 700 | V13: =5*(T13-U13) -> -780 | W13: RON | AA13: Backline | AB13: 1000 | AC13: marcel + levi | AD13: 1250 | AF13: 500 | AG13: protocol | AH13: 260 | AI13: Dean | AJ13: 500 | AK13: comision manger | AL13: 700
A14: Aprilie
A15: 6 | B15: Public | C15: Concert Phaser | D15: Pixel @ Timisoara | G15: 1700 | H15: RON | I15: 0 | J15: RON | K15: 0 | L15: =sum(AB15+AD15+AF15+AH15+AJ15+AL15) -> 3400 | M15: =G15-K15-L15 -> -1700 | N15: =round(O15*M15+I15,0) -> 0 | O15: 0 | P15: =round(R15*(M15-N15),0) -> 0 | Q15: =round(R15*AD15,0) -> 0 | R15: 0 | S15: =round(M15-N15-P15-Q15,0) -> -1700 | T15: =S15/5 -> -340 | U15: 0 | V15: =5*(T15-U15) -> -1700 | W15: RON | AA15: Backline | AB15: 0 | AC15: marcel + levi | AD15: 1000 | AK15: cvartet | AL15: 2400
A16: 7 | B16: Public | C16: Scena Mare | D16: Parcul Padurice | G16: 6000 | H16: RON | I16: 0 | J16: RON | K16: =round(G16*1%,0) -> 60 | L16: =sum(AB16+AD16+AF16+AH16+AJ16+AL16) -> 1500 | M16: =G16-K16-L16 -> 4440 | N16: =round(O16*M16+I16,0) -> 222 | O16: 0.05 | P16: =round(R16*(M16-N16),0) -> 422 | Q16: =round(R16*AD16,0) -> 50 | R16: 0.1 | S16: =round(M16-N16-P16-Q16,0) -> 3746 | T16: =S16/5 -> 749.2 | U16: =round(T16,-1) -> 750 | V16: =5*(T16-U16) -> -4 | W16: RON | AA16: Backline | AB16: 1000 | AC16: levi | AD16: 500
A17: 26 | B17: Public | C17: Concert Phaser | D17: Kai @ Timisoara | G17: 6000 | H17: RON | I17: 0 | J17: RON | K17: =round(G17*1%,0) -> 60 | L17: =sum(AB17+AD17+AF17+AH17+AJ17+AL17) -> 2000 | M17: =G17-K17-L17 -> 3940 | N17: =round(O17*M17+I17,0) -> 0 | O17: 0 | P17: =round(R17*(M17-N17),0) -> 394 | Q17: =round(R17*AD17,0) -> 100 | R17: 0.1 | S17: =round(M17-N17-P17-Q17,0) -> 3446 | T17: =S17/5 -> 689.2 | U17: 700 | V17: =5*(T17-U17) -> -54 | W17: RON | AA17: Backline | AB17: 1000 | AC17: marcel + levi | AD17: 1000
A18: Mai
A19: 12 | B19: Public | C19: Scena Mare | D19: Parcul Bucovina | G19: 6000 | H19: RON | I19: 0 | J19: RON | K19: =round(G19*1%,0) -> 60 | L19: =sum(AB19+AD19+AF19+AH19+AJ19+AL19) -> 2000 | M19: =G19-K19-L19 -> 3940 | N19: =round(O19*M19+I19,0) -> 197 | O19: 0.05 | P19: =round(R19*(M19-N19),0) -> 374 | Q19: =round(R19*AD19,0) -> 100 | R19: 0.1 | S19: =round(M19-N19-P19-Q19,0) -> 3269 | T19: =S19/5 -> 653.8 | U19: =round(T19,-1) -> 650 | V19: =5*(T19-U19) -> 19 | W19: RON | AA19: Backline | AB19: 1000 | AC19: marcel + levi | AD19: 1000
A20: Iunie
A21: 7 | B21: Public | C21: Scena Mare | D21: Centru Civic @ Resita | E21: Aniversare UBB Resita | G21: 4000 | H21: RON | I21: 0 | J21: RON | K21: =round(G21*1%,0) -> 40 | L21: =sum(AB21+AD21+AF21+AH21+AJ21+AL21) -> 2000 | M21: =G21-K21-L21 -> 1960 | N21: =round(O21*M21+I21,0) -> 1960 | O21: 1 | P21: =round(R21*(M21-N21),0) -> 0 | Q21: =round(R21*AD21,0) -> 100 | R21: 0.1 | S21: =round(M21-N21-P21-Q21,0) -> -100 | T21: =S21/5 -> -20 | U21: =round(T21,-1) -> -20 | V21: =5*(T21-U21) -> 0 | W21: RON | AA21: Backline | AB21: 1000 | AC21: marcel + levi | AD21: 1000
A22: 7 | B22: Public | C22: Extra | D22: Radio Resita | E22: Concert in Studio Radio Resita | G22: 0 | H22: RON | I22: 0 | J22: RON | K22: =round(G22*1%,0) -> 0 | L22: =sum(AB22+AD22+AF22+AH22+AJ22+AL22) -> 250 | M22: =G22-K22-L22 -> -250 | N22: =round(O22*M22+I22,0) -> 0 | O22: 0 | P22: =round(R22*(M22-N22),0) -> 0 | Q22: =round(R22*AD22,0) -> 0 | R22: 0 | S22: =round(M22-N22-P22-Q22,0) -> -250 | T22: 0 | U22: 0 | V22: =5*(T22-U22) -> 0 | W22: RON | AA22: Backline | AB22: 0 | AC22: marcel + levi | AD22: 250
A23: 8 | B23: Privat | C23: Nunta | D23: Province | F23: 183 | G23: 3550 | H23: EUR | I23: 300 | J23: EUR | K23: =round(I23*1%,0) -> 3 | L23: =sum(AB23+AD23+AF23+AH23+AJ23+AL23) -> 450 | M23: =G23-K23-L23 -> 3097 | N23: =round(O23*M23+I23,0) -> 579 | O23: 0.09 | P23: =round(R23*(M23-N23),0) -> 0 | Q23: =round(R23*AD23,0) -> 0 | R23: 0 | S23: =round(M23-N23-P23-Q23,0) -> 2518 | T23: =S23/5 -> 503.6 | U23: =round(T23,-1) -> 500 | V23: =5*(T23-U23) -> 18 | W23: EUR | AA23: Backline | AB23: 200 | AD23: 200 | AE23: Buz + Masini | AF23: 50
A24: 9 | B24: Privat | C24: Botez | D24: Province | G24: 21149 | H24: RON | I24: 1492 | J24: RON | K24: =round(G24*1%,0) -> 211 | L24: =sum(AB24+AD24+AF24+AH24+AJ24+AL24) -> 6950 | M24: =G24-K24-L24 -> 13988 | N24: =round(O24*M24+I24,0) -> 2751 | O24: 0.09 | P24: =round(R24*(M24-N24),0) -> 1124 | Q24: =round(R24*AD24,0) -> 100 | R24: 0.1 | S24: =round(M24-N24-P24-Q24,0) -> 10013 | T24: =S24/5 -> 2002.6 | U24: =round(T24,-1) -> 2000 | V24: =5*(T24-U24) -> 13 | W24: RON | AA24: Sunet Full | AB24: 1750 | AD24: 1000 | AE24: Buz + Masini | AF24: 250 | AG24: Flavius | AH24: 1750 | AI24: Flavius | AJ24: 2200
A25: 11 | B25: Privat | C25: Corporate | D25: Serenity @ Codlea | G25: 16920 | H25: RON | I25: 0 | J25: RON | K25: =round(G25*1%,0) -> 169 | L25: =sum(AB25+AD25+AF25+AH25+AJ25+AL25) -> 4750 | M25: =G25-K25-L25 -> 12001 | N25: =round(O25*M25+I25,0) -> 768 | O25: 0.064 | P25: =round(R25*(M25-N25),0) -> 1123 | Q25: =round(R25*AD25,0) -> 125 | R25: 0.1 | S25: =round(M25-N25-P25-Q25,0) -> 9985 | T25: =S25/5 -> 1997 | U25: =round(T25,-1) -> 2000 | V25: =5*(T25-U25) -> -15 | W25: RON | AA25: Backline | AB25: 1000 | AC25: marcel + levi | AD25: 1250 | AE25: Buz + Masini | AF25: 2000 | AL25: 500
A26: 15 | B26: Privat | C26: Nunta | D26: Palatul Brukenthal @ Avrig | G26: 3850 | H26: EUR | I26: 300 | J26: EUR | K26: =round(I26*1%,0) -> 3 | L26: =sum(AB26+AD26+AF26+AH26+AJ26+AL26) -> 570 | M26: =G26-K26-L26 -> 3277 | N26: =round(O26*M26+I26,0) -> 759 | O26: 0.14 | P26: =round(R26*(M26-N26),0) -> 0 | Q26: =round(R26*AD26,0) -> 0 | R26: 0 | S26: =round(M26-N26-P26-Q26,0) -> 2518 | T26: =S26/5 -> 503.6 | U26: =round(T26,-1) -> 500 | V26: =5*(T26-U26) -> 18 | W26: EUR | AA26: Sunet Full | AB26: 350 | AD26: 120 | AE26: Buz + Masini | AF26: 50 | AL26: 50
A27: 21 | B27: Public | C27: Scena Mare | D27: Muzeul Satului | E27: Flight Festival | G27: 7465 | H27: RON | I27: 0 | J27: RON | K27: =round(G27*1%,0) -> 75 | L27: =sum(AB27+AD27+AF27+AH27+AJ27+AL27) -> 1500 | M27: =G27-K27-L27 -> 5890 | N27: =round(O27*M27+I27,0) -> 295 | O27: 0.05 | P27: =round(R27*(M27-N27),0) -> 560 | Q27: =round(R27*AD27,0) -> 50 | R27: 0.1 | S27: =round(M27-N27-P27-Q27,0) -> 4985 | T27: =S27/5 -> 997 | U27: =round(T27,-1) -> 1000 | V27: =5*(T27-U27) -> -15 | W27: RON | AA27: Backline | AB27: 1000 | AD27: 500
A28: 21 | B28: Privat | C28: Nunta | D28: Province | F28: 195 | G28: 4050 | H28: EUR | I28: 300 | J28: EUR | K28: =round(I28*1%,0) -> 3 | L28: =sum(AB28+AD28+AF28+AH28+AJ28+AL28) -> 1100 | M28: =G28-K28-L28 -> 2947 | N28: =round(O28*M28+I28,0) -> 447 | O28: 0.05 | P28: =round(R28*(M28-N28),0) -> 0 | Q28: =round(R28*AD28,0) -> 0 | R28: 0 | S28: =round(M28-N28-P28-Q28,0) -> 2500 | T28: =S28/5 -> 500 | U28: =round(T28,-1) -> 500 | V28: =5*(T28-U28) -> 0 | W28: EUR | AA28: Backline | AB28: 350 | AD28: 200 | AE28: Buz + Masini | AF28: 50 | AG28: Flavius | AH28: 500
A29: 27 | B29: Privat | C29: Corporate | D29: Galla | G29: 12940 | H29: RON | I29: 0 | J29: RON | K29: =round(G29*1%,0) -> 129 | L29: =sum(AB29+AD29+AF29+AH29+AJ29+AL29) -> 2750 | M29: =G29-K29-L29 -> 10061 | N29: =round(O29*M29+I29,0) -> 503 | O29: 0.05 | P29: =round(R29*(M29-N29),0) -> 956 | Q29: =round(R29*AD29,0) -> 100 | R29: 0.1 | S29: =round(M29-N29-P29-Q29,0) -> 8502 | T29: =S29/5 -> 1700.4 | U29: =round(T29,-1) -> 1700 | V29: =5*(T29-U29) -> 2 | W29: RON | AA29: Sunet Full | AB29: 1750 | AD29: 1000
A30: 29 | B30: Privat | C30: Nunta | D30: Province | F30: 184 | G30: 3450 | H30: EUR | I30: 300 | J30: EUR | K30: =round(I30*1%,0) -> 3 | L30: =sum(AB30+AD30+AF30+AH30+AJ30+AL30) -> 450 | M30: =G30-K30-L30 -> 2997 | N30: =round(O30*M30+I30,0) -> 480 | O30: 0.06 | P30: =round(R30*(M30-N30),0) -> 0 | Q30: =round(R30*AD30,0) -> 0 | R30: 0 | S30: =round(M30-N30-P30-Q30,0) -> 2517 | T30: =S30/5 -> 503.4 | U30: =round(T30,-1) -> 500 | V30: =5*(T30-U30) -> 17 | W30: EUR | AA30: Backline | AB30: 200 | AD30: 200 | AE30: Buz + Masini | AF30: 50
A31: Iulie
A32: 5 | B32: Privat | C32: Nunta | D32: Province | F32: 198 | G32: 3600 | H32: EUR | I32: 300 | J32: EUR | K32: =round(I32*1%,0) -> 3 | L32: =sum(AB32+AD32+AF32+AH32+AJ32+AL32) -> 850 | M32: =G32-K32-L32 -> 2747 | N32: =round(O32*M32+I32,0) -> 492 | O32: 0.07 | P32: =round(R32*(M32-N32),0) -> 0 | Q32: =round(R32*AD32,0) -> 0 | R32: 0 | S32: =round(M32-N32-P32-Q32,0) -> 2255 | T32: =S32/5 -> 451 | U32: =round(T32,-1) -> 450 | V32: =5*(T32-U32) -> 5 | W32: EUR | AA32: Backline | AB32: 200 | AD32: 200 | AE32: Buz + Masini | AF32: 50 | AG32: Beni | AH32: 400
A33: 12 | B33: Privat | C33: Nunta | D33: Galla Events | F33: 177 | G33: 2750 | H33: EUR | I33: 300 | J33: EUR | K33: =round(I33*1%,0) -> 3 | L33: =sum(AB33+AD33+AF33+AH33+AJ33+AL33) -> 400 | M33: =G33-K33-L33 -> 2347 | N33: =round(O33*M33+I33,0) -> 323 | O33: 0.01 | P33: =round(R33*(M33-N33),0) -> 0 | Q33: =round(R33*AD33,0) -> 0 | R33: 0 | S33: =round(M33-N33-P33-Q33,0) -> 2024 | T33: =S33/5 -> 404.8 | U33: =round(T33,-1) -> 400 | V33: =5*(T33-U33) -> 24 | W33: EUR | AA33: Backline | AB33: 200 | AD33: 200
A34: 20 | B34: Public | C34: Scena Mare | D34: Deta | E34: Zilele Deta | G34: 7500 | H34: RON | I34: 0 | J34: RON | K34: =round(G34*1%,0) -> 75 | L34: =sum(AB34+AD34+AF34+AH34+AJ34+AL34) -> 2200 | M34: =G34-K34-L34 -> 5225 | N34: =round(O34*M34+I34,0) -> 0 | O34: 0 | P34: =round(R34*(M34-N34),0) -> 523 | Q34: =round(R34*AD34,0) -> 70 | R34: 0.1 | S34: =round(M34-N34-P34-Q34,0) -> 4632 | T34: =S34/5 -> 926.4 | U34: 950 | V34: =5*(T34-U34) -> -118 | W34: RON | AA34: Backline | AB34: 1000 | AD34: 700 | AE34: Buz + Masini | AF34: 500
A35: 25 | B35: Public | C35: Concert Phaser | D35: In spatele Casei | E35: Public/Privat VSU Liceu | G35: 9952 | H35: RON | I35: 0 | J35: RON | K35: =round(G35*1%,0) -> 100 | L35: =sum(AB35+AD35+AF35+AH35+AJ35+AL35) -> 2000 | M35: =G35-K35-L35 -> 7852 | N35: =round(O35*M35+I35,0) -> 236 | O35: 0.03 | P35: =round(R35*(M35-N35),0) -> 762 | Q35: =round(R35*AD35,0) -> 100 | R35: 0.1 | S35: =round(M35-N35-P35-Q35,0) -> 6754 | T35: =S35/5 -> 1350.8 | U35: =round(T35,-1) -> 1350 | V35: =5*(T35-U35) -> 4 | W35: RON | AA35: Backline | AB35: 1000 | AD35: 1000
A36: August
A37: 15 | B37: Public | C37: Scena Mare | D37: Gotlob | E37: Zilele orasului | G37: 9940 | H37: RON | I37: 0 | J37: RON | K37: =round(G37*1%,0) -> 99 | L37: =sum(AB37+AD37+AF37+AH37+AJ37+AL37) -> 3500 | M37: =G37-K37-L37 -> 6341 | N37: =round(O37*M37+I37,0) -> 698 | O37: 0.11 | P37: =round(R37*(M37-N37),0) -> 564 | Q37: =round(R37*AD37,0) -> 100 | R37: 0.1 | S37: =round(M37-N37-P37-Q37,0) -> 4979 | T37: =S37/5 -> 995.8 | U37: =round(T37,-1) -> 1000 | V37: =5*(T37-U37) -> -21 | W37: RON | AA37: Backline | AB37: 1000 | AD37: 1000 | AE37: Buz + Masini | AF37: 500 | AK37: Comision manger | AL37: 1000
A38: 17 | B38: Public | C38: Scena Mare | D38: Dudestii Vechi | E38: Zilele orasului | G38: 9940 | H38: RON | I38: 0 | J38: RON | K38: =round(G38*1%,0) -> 99 | L38: =sum(AB38+AD38+AF38+AH38+AJ38+AL38) -> 2500 | M38: =G38-K38-L38 -> 7341 | N38: =round(O38*M38+I38,0) -> 587 | O38: 0.08 | P38: =round(R38*(M38-N38),0) -> 675 | Q38: =round(R38*AD38,0) -> 100 | R38: 0.1 | S38: =round(M38-N38-P38-Q38,0) -> 5979 | T38: =S38/5 -> 1195.8 | U38: =round(T38,-1) -> 1200 | V38: =5*(T38-U38) -> -21 | W38: RON | AA38: Backline | AB38: 1000 | AD38: 1000 | AE38: Buz + Masini | AF38: 500
A39: 25 | B39: Privat | C39: Nunta | D39: Venue | G39: 12434 | H39: RON | I39: 0 | J39: RON | K39: =round(G39*1%,0) -> 124 | L39: =sum(AB39+AD39+AF39+AH39+AJ39+AL39) -> 2000 | M39: =G39-K39-L39 -> 10310 | N39: =round(O39*M39+I39,0) -> 464 | O39: 0.045 | P39: =round(R39*(M39-N39),0) -> 985 | Q39: =round(R39*AD39,0) -> 100 | R39: 0.1 | S39: =round(M39-N39-P39-Q39,0) -> 8761 | T39: =S39/5 -> 1752.2 | U39: =round(T39,-1) -> 1750 | V39: =5*(T39-U39) -> 11 | W39: RON | AA39: Backline | AB39: 1000 | AD39: 1000
A40: 30 | B40: Public | C40: Scena Mare | D40: Centru Civic @ Resita | E40: Aniversare Banatul Montan | G40: 8700 | H40: RON | I40: 0 | J40: RON | K40: =round(G40*1%,0) -> 87 | L40: =sum(AB40+AD40+AF40+AH40+AJ40+AL40) -> 2500 | M40: =G40-K40-L40 -> 6113 | N40: =round(O40*M40+I40,0) -> 428 | O40: 0.07 | P40: =round(R40*(M40-N40),0) -> 569 | Q40: =round(R40*AD40,0) -> 100 | R40: 0.1 | S40: =round(M40-N40-P40-Q40,0) -> 5016 | T40: =S40/5 -> 1003.2 | U40: =round(T40,-1) -> 1000 | V40: =5*(T40-U40) -> 16 | W40: RON | AA40: Backline | AB40: 1000 | AD40: 1000 | AF40: 500
A41: 31 | B41: Privat | C41: Nunta | D41: Palazzo Luxury | F41: 171 | G41: 2950 | H41: EUR | I41: 300 | J41: EUR | K41: =round(I41*1%,0) -> 3 | L41: =sum(AB41+AD41+AF41+AH41+AJ41+AL41) -> 400 | M41: =G41-K41-L41 -> 2547 | N41: =round(O41*M41+I41,0) -> 300 | O41: 0 | P41: =round(R41*(M41-N41),0) -> 0 | Q41: =round(R41*AD41,0) -> 0 | R41: 0 | S41: =round(M41-N41-P41-Q41,0) -> 2247 | T41: =S41/5 -> 449.4 | U41: 450 | V41: =5*(T41-U41) -> -3 | W41: EUR | AA41: Backline | AB41: 200 | AD41: 200
A42: Septembrie
A43: 1 | B43: Privat | C43: Corporate | D43: L'iziera | E43: dm aniversare | G43: 10949 | H43: RON | I43: 0 | J43: RON | K43: =round(G43*1%,0) -> 109 | L43: =sum(AB43+AD43+AF43+AH43+AJ43+AL43) -> 2000 | M43: =G43-K43-L43 -> 8840 | N43: =round(O43*M43+I43,0) -> 398 | O43: 0.045 | P43: =round(R43*(M43-N43),0) -> 844 | Q43: =round(R43*AD43,0) -> 100 | R43: 0.1 | S43: =round(M43-N43-P43-Q43,0) -> 7498 | T43: =S43/5 -> 1499.6 | U43: =round(T43,-1) -> 1500 | V43: =5*(T43-U43) -> -2 | W43: RON | AA43: Backline | AB43: 1000 | AD43: 1000
A44: 14 | B44: Privat | C44: Nunta | D44: Plaja Noua | G44: 17250 | H44: RON | I44: 0 | J44: RON | K44: =round(I44*1%,0) -> 0 | L44: =sum(AB44+AD44+AF44+AH44+AJ44+AL44) -> 2250 | M44: =G44-K44-L44 -> 15000 | N44: =round(O44*M44+I44,0) -> 3000 | O44: 0.2 | P44: =round(R44*(M44-N44),0) -> 0 | Q44: =round(R44*AD44,0) -> 0 | R44: 0 | S44: =round(M44-N44-P44-Q44,0) -> 12000 | T44: =S44/5 -> 2400 | U44: =round(T44,-1) -> 2400 | V44: =5*(T44-U44) -> 0 | W44: RON | AA44: Backline | AB44: 1000 | AD44: 1000 | AF44: 250
A45: 15 | B45: Privat | C45: Nunta | D45: Flonta | F45: 186 | G45: 3800 | H45: EUR | I45: 300 | J45: EUR | K45: =round(I45*1%,0) -> 3 | L45: =sum(AB45+AD45+AF45+AH45+AJ45+AL45) -> 550 | M45: =G45-K45-L45 -> 3247 | N45: =round(O45*M45+I45,0) -> 755 | O45: 0.14 | P45: =round(R45*(M45-N45),0) -> 0 | Q45: =round(R45*AD45,0) -> 0 | R45: 0 | S45: =round(M45-N45-P45-Q45,0) -> 2492 | T45: =S45/5 -> 498.4 | U45: =round(T45,-1) -> 500 | V45: =5*(T45-U45) -> -8 | W45: EUR | AA45: Sunet Full | AB45: 350 | AD45: 200
A46: 22 | B46: Privat | C46: Nunta | D46: Venue | F46: 185 | G46: 3450 | H46: EUR | I46: 300 | J46: EUR | K46: =round(I46*1%,0) -> 3 | L46: =sum(AB46+AD46+AF46+AH46+AJ46+AL46) -> 400 | M46: =G46-K46-L46 -> 3047 | N46: =round(O46*M46+I46,0) -> 529 | O46: 0.075 | P46: =round(R46*(M46-N46),0) -> 0 | Q46: =round(R46*AD46,0) -> 0 | R46: 0 | S46: =round(M46-N46-P46-Q46,0) -> 2518 | T46: =S46/5 -> 503.6 | U46: =round(T46,-1) -> 500 | V46: =5*(T46-U46) -> 18 | W46: EUR | AA46: Backline | AB46: 200 | AD46: 200
A47: 28 | B47: Privat | C47: Nunta | D47: Plaja Noua | G47: 3000 | H47: EUR | I47: 300 | J47: EUR | K47: =round(I47*1%,0) -> 3 | L47: =sum(AB47+AD47+AF47+AH47+AJ47+AL47) -> 400 | M47: =G47-K47-L47 -> 2597 | N47: =round(O47*M47+I47,0) -> 352 | O47: 0.02 | P47: =round(R47*(M47-N47),0) -> 0 | Q47: =round(R47*AD47,0) -> 0 | R47: 0 | S47: =round(M47-N47-P47-Q47,0) -> 2245 | T47: =S47/5 -> 449 | U47: =round(T47,-1) -> 450 | V47: =5*(T47-U47) -> -5 | W47: EUR | AA47: Backline | AB47: 200 | AD47: 200
A48: 29 | B48: Privat | C48: Nunta | D48: Phoenix by the Lake @ Bucuresti | F48: 196 | G48: 6600 | H48: EUR | I48: 660 | J48: EUR | K48: =round(I48*1%,0) -> 7 | L48: =sum(AB48+AD48+AF48+AH48+AJ48+AL48) -> 2650 | M48: =G48-K48-L48 -> 3943 | N48: =round(O48*M48+I48,0) -> 936 | O48: 0.07 | P48: =round(R48*(M48-N48),0) -> 0 | Q48: =round(R48*AD48,0) -> 0 | R48: 0 | S48: =round(M48-N48-P48-Q48,0) -> 3007 | T48: =S48/5 -> 601.4 | U48: =round(T48,-1) -> 600 | V48: =5*(T48-U48) -> 7 | W48: EUR | AA48: Sunet Full | AB48: 350 | AD48: 400 | AE48: 2 buzuri | AF48: 650 | AG48: Flavius | AH48: 600 | AI48: Flavius | AJ48: 500 | AK48: podium | AL48: 150
A49: Octombrie
A50: 5 | B50: Privat | C50: Nunta | D50: Plaja Noua | G50: 3450 | H50: EUR | I50: 300 | J50: EUR | K50: =round(I50*1%,0) -> 3 | L50: =sum(AB50+AD50+AF50+AH50+AJ50+AL50) -> 400 | M50: =G50-K50-L50 -> 3047 | N50: =round(O50*M50+I50,0) -> 544 | O50: 0.08 | P50: =round(R50*(M50-N50),0) -> 0 | Q50: =round(R50*AD50,0) -> 0 | R50: 0 | S50: =round(M50-N50-P50-Q50,0) -> 2503 | T50: =S50/5 -> 500.6 | U50: =round(T50,-1) -> 500 | V50: =5*(T50-U50) -> 3 | W50: EUR | AA50: Backline | AB50: 200 | AD50: 200
A51: 12 | B51: Privat | C51: Nunta | D51: Venue | F51: 173 | G51: 16166 | H51: RON | I51: 1492 | J51: RON | K51: =round(G51*1%,0) -> 162 | L51: =sum(AB51+AD51+AF51+AH51+AJ51+AL51) -> 2000 | M51: =G51-K51-L51 -> 14004 | N51: =round(O51*M51+I51,0) -> 2780 | O51: 0.092 | P51: =round(R51*(M51-N51),0) -> 1122 | Q51: =round(R51*AD51,0) -> 100 | R51: 0.1 | S51: =round(M51-N51-P51-Q51,0) -> 10002 | T51: =S51/5 -> 2000.4 | U51: =round(T51,-1) -> 2000 | V51: =5*(T51-U51) -> 2 | W51: RON | AA51: Backline | AB51: 1000 | AD51: 1000
A52: Noiembrie
A53: 8 | B53: Privat | C53: Nunta | D53: Galla | G53: 2950 | H53: EUR | I53: 0 | J53: EUR | K53: =round(I53*1%,0) -> 0 | L53: =sum(AB53+AD53+AF53+AH53+AJ53+AL53) -> 400 | M53: =G53-K53-L53 -> 2550 | N53: =round(O53*M53+I53,0) -> 26 | O53: 0.01 | P53: =round(R53*(M53-N53),0) -> 0 | Q53: =round(R53*AD53,0) -> 0 | R53: 0 | S53: =round(M53-N53-P53-Q53,0) -> 2524 | T53: =S53/5 -> 504.8 | U53: =round(T53,-1) -> 500 | V53: =5*(T53-U53) -> 24 | W53: EUR | AA53: Backline | AB53: 200 | AD53: 200
A54: 21 | B54: Public | C54: Concert Phaser | D54: Casa Tineretului | E54: Gala Tinerilor | G54: 9950 | H54: RON | I54: 0 | J54: RON | K54: =round(G54*1%,0) -> 100 | L54: =sum(AB54+AD54+AF54+AH54+AJ54+AL54) -> 2250 | M54: =G54-K54-L54 -> 7600 | N54: =round(O54*M54+I54,0) -> 532 | O54: 0.07 | P54: =round(R54*(M54-N54),0) -> 707 | Q54: =round(R54*AD54,0) -> 100 | R54: 0.1 | S54: =round(M54-N54-P54-Q54,0) -> 6261 | T54: =S54/5 -> 1252.2 | U54: =round(T54,-1) -> 1250 | V54: =5*(T54-U54) -> 11 | W54: RON | AA54: Backline | AB54: 1250 | AD54: 1000
A55: 22 | B55: Public | C55: Concert Phaser | D55: Kai @ Timisoara | G55: 6000 | H55: RON | I55: 0 | J55: RON | K55: =round(G55*1%,0) -> 60 | L55: =sum(AB55+AD55+AF55+AH55+AJ55+AL55) -> 2000 | M55: =G55-K55-L55 -> 3940 | N55: =round(O55*M55+I55,0) -> -39 | O55: -0.01 | P55: =round(R55*(M55-N55),0) -> 398 | Q55: =round(R55*AD55,0) -> 100 | R55: 0.1 | S55: =round(M55-N55-P55-Q55,0) -> 3481 | T55: =S55/5 -> 696.2 | U55: =round(T55,-1) -> 700 | V55: =5*(T55-U55) -> -19 | W55: RON | AA55: Backline | AB55: 1000 | AD55: 1000
A56: 23 | B56: Privat | C56: Corporate | D56: Hotel Rogge @ Resita | E56: Rotary | G56: 15920 | H56: RON | I56: 0 | J56: RON | K56: =round(G56*1%,0) -> 159 | L56: =sum(AB56+AD56+AF56+AH56+AJ56+AL56) -> 3500 | M56: =G56-K56-L56 -> 12261 | N56: =round(O56*M56+I56,0) -> 1042 | O56: 0.085 | P56: =round(R56*(M56-N56),0) -> 1122 | Q56: =round(R56*AD56,0) -> 100 | R56: 0.1 | S56: =round(M56-N56-P56-Q56,0) -> 9997 | T56: =S56/5 -> 1999.4 | U56: =round(T56,-1) -> 2000 | V56: =5*(T56-U56) -> -3 | W56: RON | AA56: Sunet Full | AB56: 2000 | AD56: 1000 | AF56: 500
A57: 30 | B57: Public | C57: Concert Phaser | D57: Soho @ Resita | G57: 7000 | H57: RON | I57: 0 | J57: RON | K57: =round(G57*1%,0) -> 70 | L57: =sum(AB57+AD57+AF57+AH57+AJ57+AL57) -> 3700 | M57: =G57-K57-L57 -> 3230 | N57: =round(O57*M57+I57,0) -> -743 | O57: -0.23 | P57: =round(R57*(M57-N57),0) -> 397 | Q57: =round(R57*AD57,0) -> 100 | R57: 0.1 | S57: =round(M57-N57-P57-Q57,0) -> 3476 | T57: =S57/5 -> 695.2 | U57: =round(T57,-1) -> 700 | V57: =5*(T57-U57) -> -24 | W57: RON | AA57: Backline | AB57: 1750 | AD57: 1000 | AF57: 500 | AL57: 450
A58: Decembrie
A59: 14 | B59: Privat | C59: Corporate | D59: Pensiunea "La FIluta" @ Suceava | E59: Euskdai | G59: 28858 | H59: RON | I59: 2488 | J59: RON | K59: =round(G59*1%,0) -> 289 | L59: =sum(AB59+AD59+AF59+AH59+AJ59+AL59) -> 11250 | M59: =G59-K59-L59 -> 17319 | N59: =round(O59*M59+I59,0) -> 3267 | O59: 0.045 | P59: =round(R59*(M59-N59),0) -> 1405 | Q59: =round(R59*AD59,0) -> 150 | R59: 0.1 | S59: =round(M59-N59-P59-Q59,0) -> 12497 | T59: =S59/5 -> 2499.4 | U59: =round(T59,-1) -> 2500 | V59: =5*(T59-U59) -> -3 | AA59: Sunet Full | AB59: 1750 | AD59: 1500 | AE59: 2 buzuri | AF59: 3000 | AG59: Flavius | AH59: 2500 | AI59: Flavius | AJ59: 2500
A60: 17 | B60: Privat | C60: Corporate | D60: Province | E60: Ranking Coach | G60: 24630 | H60: RON | I60: 0 | J60: RON | K60: =round(G60*1%,0) -> 246 | L60: =sum(AB60+AD60+AF60+AH60+AJ60+AL60) -> 8600 | M60: =G60-K60-L60 -> 15784 | N60: =round(O60*M60+I60,0) -> 4577 | O60: 0.29 | P60: =round(R60*(M60-N60),0) -> 1121 | Q60: =round(R60*AD60,0) -> 100 | R60: 0.1 | S60: =round(M60-N60-P60-Q60,0) -> 9986 | T60: =S60/5 -> 1997.2 | U60: =round(T60,-1) -> 2000 | V60: =5*(T60-U60) -> -14 | AA60: Sunet Full | AB60: 1750 | AD60: 1000 | AF60: 100 | AG60: Flavius | AH60: 2500 | AI60: Flavius | AJ60: 2500 | AK60: proiector | AL60: 750
A61: 21 | B61: Privat | C61: Corporate | D61: DolceVita Ballroom @ Tg. Jiu | E61: Farbum | F61: 222 | G61: 24380 | H61: RON | I61: 2239 | J61: RON | K61: =round(G61*1%,0) -> 244 | L61: =sum(AB61+AD61+AF61+AH61+AJ61+AL61) -> 6250 | M61: =G61-K61-L61 -> 17886 | N61: =round(O61*M61+I61,0) -> 3885 | O61: 0.092 | P61: =round(R61*(M61-N61),0) -> 1400 | Q61: =round(R61*AD61,0) -> 100 | R61: 0.1 | S61: =round(M61-N61-P61-Q61,0) -> 12501 | T61: =S61/5 -> 2500.2 | U61: =round(T61,-1) -> 2500 | V61: =5*(T61-U61) -> 1 | AA61: Sunet Full | AB61: 1750 | AD61: 1000 | AF61: 1000 | AG61: Flavius | AH61: 2500
A62: 31 | B62: Public | C62: Concert Phaser | D62: Resita | E62: Revelion | G62: 17400 | H62: RON | I62: 0 | J62: RON | K62: =round(G62*1%,0) -> 174 | L62: =sum(AB62+AD62+AF62+AH62+AJ62+AL62) -> 2500 | M62: =G62-K62-L62 -> 14726 | N62: =round(O62*M62+I62,0) -> 736 | O62: 0.05 | P62: =round(R62*(M62-N62),0) -> 1399 | Q62: =round(R62*AD62,0) -> 100 | R62: 0.1 | S62: =round(M62-N62-P62-Q62,0) -> 12491 | T62: =S62/5 -> 2498.2 | U62: =round(T62,-1) -> 2500 | V62: =5*(T62-U62) -> -9 | AA62: Backline | AB62: 1000 | AD62: 1000 | AF62: 500
A64: TEST | K64: =round(G64*1%,0) -> 0 | L64: =sum(AB64+AD64+AF64+AH64+AJ64+AL64) -> 0 | M64: =G64-K64-L64 -> 0 | N64: =round(O64*M64+I64,0) -> 0 | O64: 0.15 | P64: =round(R64*(M64-N64),0) -> 0 | Q64: =round(R64*AD64,0) -> 0 | R64: 0.1 | S64: =round(M64-N64-P64-Q64,0) -> 0 | T64: =S64/5 -> 0 | U64: =round(T64,-1) -> 0 | V64: =5*(T64-U64) -> 0

Sheet Onorariu Artist 2024
F1: Onorariu Artist
A2: Data | B2: Tip Event | C2: Specific | D2: Locatie | E2: Descriere | F2: POSIBIL | G2: REAL | H2: Valuta | I2: Carina | J2: Arni | K2: Radu | L2: Sebi | M2: Luci
A3: Ianuarie
A4: 27 | B4: Privat | C4: Nunta | D4: Flonta (Lakeside) | F4: 530 | G4: 500 | H4: EUR | I4: 500 | J4: 500 | K4: 500 | L4: 500 | M4: 500
A5: 29 | B5: Public | C5: Extra | D5: Radio Resita | E5: Concert in Studio Radio Resita | F5: 0 | G5: 0 | H5: RON | I5: 0 | J5: 0 | K5: 0 | L5: 0 | M5: 0
A6: Februarie
A7: 2 | B7: Public | C7: Concert Phaser | D7: Kai @ Timisoara | F7: 550 | G7: 600 | H7: RON | I7: 600 | J7: 600 | K7: 600 | L7: 600 | M7: 600
A8: 29 | B8: Public | C8: Concert Phaser | D8: Flying Circus @ Cluj | F8: 0 | G8: 0 | H8: RON | I8: 0 | J8: 0 | K8: 0 | L8: 0 | M8: 0
A9: Martie
A10: 1 | B10: Public | C10: Extra | D10: Radio Tg Mures | F10: 0 | G10: 0 | H10: RON | I10: 0 | J10: 0 | K10: 0 | L10: 0 | M10: 0
A11: 1 | B11: Public | C11: Concert Phaser | D11: Republic Hub @ Tg Mures | F11: 0 | G11: 0 | H11: RON | I11: 0 | J11: 0 | K11: 0 | L11: 0 | M11: 0
A12: 2 | B12: Public | C12: Concert Phaser | D12: NooVo @ Oradea | F12: 0 | G12: 0 | H12: RON | I12: 0 | J12: 0 | K12: 0 | L12: 0 | M12: 0
A13: 8 | B13: Public | C13: Concert Phaser | D13: Soho @ Resita | F13: 550 | G13: 700 | H13: RON | I13: 700 | J13: 700 | K13: 700 | L13: 700 | M13: 700
A14: Aprilie
A15: 6 | B15: Public | C15: Concert Phaser | D15: Pixel @ Timisoara | F15: 0 | G15: 0 | H15: RON | I15: 0 | J15: 0 | K15: 0 | L15: 0 | M15: 0
A16: 7 | B16: Public | C16: Scena Mare | D16: Parcul Padurice | F16: 790 | G16: 750 | H16: RON | I16: 750 | J16: 750 | K16: 750 | L16: 750 | M16: 750
A17: 26 | B17: Public | C17: Concert Phaser | D17: Kai @ Timisoara | F17: 690 | G17: 700 | H17: RON | I17: 700 | J17: 700 | K17: 700 | L17: 700 | M17: 700
A18: Mai
A19: 12 | B19: Public | C19: Scena Mare | D19: Parcul Bucovina | F19: 690 | G19: 650 | H19: RON | I19: 650 | J19: 650 | K19: 650 | L19: 650 | M19: 650
A20: Iunie
A21: 7 | B21: Public | C21: Scena Mare | D21: Centru Civic @ Resita | E21: Aniversare UBB Resita | F21: 330 | G21: 0 | H21: RON | I21: 0 | J21: 0 | K21: 0 | L21: 0 | M21: 0
A22: 7 | B22: Public | C22: Extra | D22: Radio Resita | E22: Concert in Studio Radio Resita | F22: 0 | G22: 0 | H22: RON | I22: 0 | J22: 0 | K22: 0 | L22: 0 | M22: 0
A23: 8 | B23: Privat | C23: Nunta | D23: Province | F23: 560 | G23: 500 | H23: EUR | I23: 500 | J23: 500 | K23: 500 | L23: 500 | M23: 500
A24: 9 | B24: Privat | C24: Botez | D24: Province | F24: 2230 | G24: 2000 | H24: RON | I24: 2000 | J24: 2000 | K24: 2000 | L24: 2000 | M24: 2000
A25: 11 | B25: Privat | C25: Corporate | D25: Serenity @ Codlea | F25: 2140 | G25: 2000 | H25: RON | I25: 2000 | J25: 2000 | K25: 2000 | L25: 2000 | M25: 2000
A26: 15 | B26: Privat | C26: Nunta | D26: Palatul Brukental @ Avrig | F26: 500 | G26: 500 | H26: EUR | I26: 500 | J26: 500 | K26: 500 | L26: 500 | M26: 500
A27: 21 | B27: Public | C27: Scena Mare | D27: Muzeul Satului | F27: 1050 | G27: 1000 | H27: RON | I27: 1000 | J27: 1000 | K27: 1000 | L27: 1000 | M27: 1000
A28: 21 | B28: Privat | C28: Nunta | D28: Province | F28: 530 | G28: 500 | H28: EUR | I28: 500 | J28: 500 | K28: 500 | L28: 500 | M28: 500
A29: 27 | B29: Privat | C29: Corporate | D29: Galla | F29: 1790 | G29: 1700 | H29: RON | I29: 1700 | J29: 1700 | K29: 1700 | L29: 1700 | M29: 1700
A30: 29 | B30: Privat | C30: Nunta | D30: Province | F30: 540 | G30: 500 | H30: EUR | I30: 500 | J30: 500 | K30: 500 | L30: 500 | M30: 500
A31: Iulie
A32: 5 | B32: Privat | C32: Nunta | D32: Province | F32: 480 | G32: 450 | H32: EUR | I32: 450 | J32: 450 | K32: 450 | L32: 450 | M32: 450
A33: 12 | B33: Privat | C33: Nunta | D33: Galla Events | F33: 400 | G33: 400 | H33: EUR | I33: 400 | J33: 400 | K33: 400 | L33: 400 | M33: 400
A34: 20 | B34: Public | C34: Scena Mare | D34: Deta | E34: =AVERAGE(G44:G51) -> 992.85714 | F34: 950 | G34: 950 | H34: RON | I34: 950 | J34: 950 | K34: 950 | L34: 950 | M34: 950
A35: 25 | B35: Public | C35: Concert Phaser | D35: In spatele Casei | E35: Public/Privat VSU Liceu | F35: 1390 | G35: 1350 | H35: RON | I35: 1350 | J35: 1350 | K35: 1350 | L35: 1350 | M35: 1350
A36: August
A37: 15 | B37: Public | C37: Scena Mare | D37: Gotlob | E37: Zilele orasului | F37: 1120 | G37: 1000 | H37: RON | I37: 1000 | J37: 1000 | K37: 1000 | L37: 1000 | M37: 1000
A38: 17 | B38: Public | C38: Scena Mare | D38: Dudestii Vechi | E38: Zilele orasului | F38: 1300 | G38: 1200 | H38: RON | I38: 1200 | J38: 1200 | K38: 1200 | L38: 1200 | M38: 1200
A39: 25 | B39: Privat | C39: Nunta | D39: Venue | F39: 1840 | G39: 1750 | H39: RON | I39: 1750 | J39: 1750 | K39: 1750 | L39: 1750 | M39: 1750
A40: 30 | B40: Public | C40: Scena Mare | D40: Centru Civic @ Resita | E40: Aniversare Banatul Montan | F40: 1080 | G40: 1000 | H40: RON | I40: 1000 | J40: 1000 | K40: 1000 | L40: 1000 | M40: 1000
A41: 31 | B41: Privat | C41: Nunta | D41: Palazzo Luxury | F41: 440 | G41: 450 | H41: EUR | I41: 450 | J41: 450 | K41: 450 | L41: 450 | M41: 450
A42: Septembrie
A43: 1 | B43: Privat | C43: Corporate | D43: L'iziera | E43: DM | F43: 1570 | G43: 1500 | H43: RON | I43: 1500 | J43: 1500 | K43: 1500 | L43: 1500 | M43: 1500
A44: 14 | B44: Privat | C44: Nunta | D44: Plaja Noua | F44: 3000 | G44: 2400 | H44: RON | I44: 2400 | J44: 2400 | K44: 2400 | L44: 2400 | M44: 2400
A45: 15 | B45: Privat | C45: Nunta | D45: Flonta | F45: 590 | G45: 500 | H45: EUR | I45: 500 | J45: 500 | K45: 500 | L45: 500 | M45: 500
A46: 22 | B46: Privat | C46: Nunta | D46: Venue | F46: 550 | G46: 500 | H46: EUR | I46: 500 | J46: 500 | K46: 500 | L46: 500 | M46: 500
A47: 28 | B47: Privat | C47: Nunta | D47: Plaja Noua | F47: 460 | G47: 450 | H47: EUR | I47: 450 | J47: 450 | K47: 450 | L47: 450 | M47: 450
A48: 29 | B48: Privat | C48: Nunta | D48: Phoenix by the Lake @ Bucuresti | F48: 660 | G48: 600 | H48: EUR | I48: 600 | J48: 600 | K48: 600 | L48: 600 | M48: 600
A49: Octombrie
A50: 5 | B50: Privat | C50: Nunta | D50: Plaja Noua | F50: 550 | G50: 500 | H50: EUR | I50: 500 | J50: 500 | K50: 500 | L50: 500 | M50: 500
A51: 12 | B51: Privat | C51: Nunta | D51: Venue | F51: 2330 | G51: 2000 | H51: RON | I51: 2000 | J51: 2000 | K51: 2000 | L51: 2000 | M51: 2000
A52: Noiembrie
A53: 8 | B53: Privat | C53: Nunta | D53: Galla | F53: 510 | G53: 500 | H53: EUR | I53: 500 | J53: 500 | K53: 500 | L53: 500 | M53: 500
A54: 21 | B54: Public | C54: Concert Phaser | D54: Casa Tineretului | F54: 1350 | G54: 1250 | H54: RON | I54: 1250 | J54: 1250 | K54: 1250 | L54: 1250 | M54: 1250
A55: 22 | B55: Public | C55: Concert Phaser | D55: Kai | F55: 690 | G55: 700 | H55: RON | I55: 700 | J55: 700 | K55: 700 | L55: 700 | M55: 700
A56: 23 | B56: Privat | C56: Corporate | D56: Hotel Rogge @ Resita | F56: 2190 | G56: 2000 | H56: RON | I56: 2000 | J56: 2000 | K56: 2000 | L56: 2000 | M56: 2000
A57: 30 | B57: Public | C57: Concert Phaser | D57: Soho @ Resita | F57: 560 | G57: 700 | H57: RON | I57: 700 | J57: 700 | K57: 700 | L57: 700 | M57: 700
A58: Decembrie
A59: 14 | B59: Privat | C59: Corporate | D59: Suceava | F59: 2640 | G59: 2500 | H59: RON | I59: 2500 | J59: 2500 | K59: 2500 | L59: 2500 | M59: 2500
A60: 17 | B60: Privat | C60: Corporate | D60: Province | F60: 2820 | G60: 2000 | H60: RON | I60: 2000 | J60: 2000 | K60: 2000 | L60: 2000 | M60: 2000
A61: 21 | B61: Privat | C61: Corporate | D61: Tg. Jiu | F61: 2800 | G61: 2500 | H61: RON | I61: 2500 | J61: 2500 | K61: 2500 | L61: 2500 | M61: 2500
A62: 31 | B62: Public | C62: Concert Phaser | D62: Resita | E62: Revelion | F62: 2630 | G62: 2500 | H62: RON | I62: 2500 | J62: 2500 | K62: 2500 | L62: 2500 | M62: 2500

Sheet Tranzactii 2024
B1: Cheltuieli | G1: Venituri | L1: Retrageri | N1: Depuneri
A2: Data | B2: Suma | C2: Valuta | D2: Categorie | E2: Descriere | F2: Mod | G2: Suma | H2: Valuta | I2: Categorie | J2: Descriere | K2: Mod | L2: Suma | M2: Descriere | N2: Suma | O2: Descriere
A3: 44927 | C3: Ron | G3: 626.46 | H3: Ron | J3: Sold initial 2024 | K3: Cash
G4: 40044.54 | H4: Ron | J4: Sold initial 2024 | K4: Banca
A8: 45293 | B8: 99.99 | C8: Ron | D8: Drive | F8: Banca
B9: 1244.81 | C9: Ron | D9: Promo Meta | F9: Banca
B10: 6750 | C10: Ron | D10: Prezent | F10: Banca
B11: 0.45 | C11: Ron | D11: Comision Operatiune | F11: Banca
A12: 45294 | B12: 160.64 | C12: Ron | D12: Drive | F12: Banca
A13: 45296 | L13: 5000
A14: 45300 | G14: 1491 | H14: Ron | I14: Avans | J14: party aprilie 2024 | K14: Banca
A15: 45302 | B15: 285.48 | C15: Ron | D15: Factureaza | F15: Banca
A16: 45307 | B16: 500 | C16: Ron | D16: Drum | E16: recuperari province 2023 | F16: Cash
A17: 45313 | B17: 3500 | C17: Ron | D17: Sala CS | E17: din 2023 restanta + 2024 full | F17: Cash | L17: 2500
B18: 8.75 | C18: Ron | D18: Comision Retrageri | F18: Banca
A19: 45314 | B19: 5 | C19: Ron | D19: Comision Retrageri | F19: Banca | G19: 5000 | H19: Ron | I19: Event | J19: ccs resita dec 2023 | K19: Banca | L19: 500
B20: 2.5 | C20: Ron | D20: Comision Retrageri | F20: Banca
A21: 45316 | B21: 3912 | C21: Ron | D21: Salariu | F21: Banca
B22: 222 | C22: Ron | D22: Salariu | F22: Banca
B23: 304 | C23: Ron | D23: TVA | F23: Banca
A24: 45319 | B24: 500 | C24: Euro | D24: Sebi | E24: event 27.01.2024 | F24: Cash | G24: 3000 | H24: Euro | I24: Event | J24: event 27.01.2024 | K24: Cash
B25: 500 | C25: Euro | D25: Luci | E25: event 27.01.2024 | F25: Cash
B26: 500 | C26: Euro | D26: Arni | E26: event 27.01.2024 | F26: Cash
B27: 500 | C27: Euro | D27: Radu | E27: event 27.01.2024 | F27: Cash
B28: 500 | C28: Euro | D28: Carina | E28: event 27.01.2024 | F28: Cash
B29: 350 | C29: Euro | D29: Prezent | E29: event 27.01.2024 | F29: Cash
B30: 100 | C30: Euro | D30: Altele | F30: Cash
A31: 45320 | B31: 250 | C31: Ron | D31: Tehnici | F31: Cash
A32: 45322 | L32: 10000
A35: 45323 | B35: 11350 | C35: Ron | D35: Sebi | E35: restul de cantari pe 2023 | F35: Cash | L35: 2500
B36: 300 | C36: Ron | D36: Drum | E36: arni drum recuperari 2023 | F36: Cash
B37: 300 | C37: Ron | D37: Drum | E37: carina drum recuperari 2023 + radio resita 2024 | F37: Cash
B38: 200 | C38: Ron | D38: Drum | E38: radu drum radio resita 2024 | F38: Cash
B39: 300 | C39: Ron | D39: Drum | E39: arni drum recuperari 2023 | F39: Cash
B40: 3350 | C40: Ron | D40: Luci | E40: restul de cantari 2022 | F40: Cash
B41: 700 | C41: Ron | D41: Drum | E41: luci drum 2023 + radio resita | F41: Cash
A42: 45324 | B42: 54 | C42: Ron | D42: Altele | E42: cartela telefon pentru nunti | F42: Cash | L42: 1500
A43: 45325 | B43: 500 | C43: Ron | D43: Tehnici | E43: kai event marci | F43: Cash | L43: 2000
B44: 750 | C44: Ron | D44: Tehnici | E44: kai event levi + sunet | F44: Cash
B45: 500 | C45: Ron | D45: Altele | E45: dean kai event | F45: Cash
B46: 50 | C46: Ron | D46: Altele | E46: parcare kai event | F46: Cash
B47: 60 | C47: Ron | D47: Altele | E47: splice | F47: Cash
B48: 50 | C48: Ron | D48: Drum | E48: buz | F48: Cash
B49: 160.58 | C49: Ron | D49: Drive | F49: Banca
B50: 7 | C50: Ron | D50: Comision Retrageri | F50: Banca
A51: 45326 | B51: 2.5 | C51: Ron | D51: Comision Retrageri | F51: Banca | L51: 900
B52: 9 | C52: Ron | D52: Comision Retrageri | F52: Banca
A53: 45328 | G53: 1491 | H53: Ron | I53: Avans | J53: avans nunta 21.06.2024 | K53: Banca
A54: 45330 | B54: 7 | C54: Ron | D54: Comision Retrageri | F54: Banca | L54: 2000
A55: 45333 | G55: 3282 | H55: Ron | I55: Avans | J55: avans nunta 29.09.2024 | K55: Banca
A56: 45334 | B56: 7 | C56: Ron | D56: Comision Retrageri | F56: Banca | L56: 2000
A57: 45337 | B57: 5.25 | C57: Ron | D57: Comision Retrageri | F57: Banca | L57: 1500
A58: 45338 | B58: 3.5 | C58: Ron | D58: Comision Retrageri | F58: Banca | G58: 1493 | H58: Ron | I58: Avans | J58: avans nunta 19.10.2024 | K58: Banca | L58: 1000
A59: 45342 | B59: 1900 | C59: Ron | D59: Arni | E59: zillele giarmata + anti bully | F59: Cash | L59: 2000
B60: 600 | C60: Ron | D60: Arni | E60: kai | F60: Cash
B61: 8.75 | C61: Ron | D61: Comision Retrageri | F61: Banca
A62: 45345 | B62: 30 | C62: Ron | D62: TVA | F62: Banca | L62: 800
B63: 0.51 | C63: Ron | D63: Comision Operatiune | F63: Banca
B64: 1000 | C64: Ron | D64: Altele | E64: avocati adr | F64: Banca
B65: 0.45 | C65: Ron | D65: Comision Operatiune | F65: Banca
A66: 45347 | B66: 1.4 | C66: Ron | D66: Comision Retrageri | F66: Banca | L66: 400
A67: 45348 | B67: 1450 | C67: Ron | D67: Altele | E67: huse thomann | F67: Cash
A68: 45350 | B68: 418.02 | C68: Ron | D68: Drum | E68: motorina buz turneu | F68: Cash | G68: 19000 | H68: Ron | I68: Event | J68: revelion 2023 + sala lira concert 2023 | K68: Banca | L68: 5000
B69: 17.5 | C69: Ron | D69: Comision Retrageri | F69: Banca
A70: 45351 | B70: 32.5 | C70: Ron | D70: Protocol | E70: covrigi apa | F70: Cash
B71: 86 | C71: Ron | D71: Protocol | E71: cafea etc | F71: Cash
B72: 500 | C72: Ron | D72: Protocol | E72: pranz cluj | F72: Cash
B73: 112 | C73: Ron | D73: Protocol | E73: doner cluj | F73: Cash
B74: 103 | C74: Ron | D74: Protocol | E74: mega image | F74: Cash
B75: 35 | C75: Ron | D75: ING Card | F75: Banca
A78: 45352 | B78: 36 | C78: Ron | D78: Protocol | E78: parcare cluj | F78: Cash
B79: 15 | C79: Ron | D79: Protocol | E79: mega cluj | F79: Cash
B80: 40 | C80: Ron | D80: Protocol | E80: mol benzinarie | F80: Cash
B81: 20 | C81: Ron | D81: Protocol | E81: biliard mures | F81: Cash
B82: 15 | C82: Ron | D82: Protocol | E82: sucuri mures | F82: Cash
A83: 45353 | B83: 455.7 | C83: Ron | D83: Drum | E83: motorina buz turneu | F83: Cash
B84: 310 | C84: Ron | D84: Protocol | E84: pranz oradea | F84: Cash
B85: 150 | C85: Ron | D85: Protocol | E85: mancare si supermarket | F85: Cash
A86: 45354 | B86: 160.44 | C86: Ron | D86: Drive | F86: Banca | L86: 2500
B87: 310 | C87: Ron | D87: Drum | E87: motorina buz | F87: Cash
A88: 45355 | B88: 1500 | C88: Ron | D88: Promo Meta | E88: promo miniturneu | F88: Cash | G88: 2000 | H88: Ron | I88: Avans | J88: concert resita soho | K88: Banca
A89: 45357 | B89: 1620 | C89: Ron | D89: Altele | E89: receiver | F89: Cash
A90: 45359 | G90: 5000 | H90: Ron | I90: Event | J90: concert resita soho | K90: Cash
A91: 45360 | B91: 700 | C91: Ron | D91: Carina | E91: concert resita soho | F91: Cash
B92: 700 | C92: Ron | D92: Arni | E92: concert resita soho | F92: Cash
B93: 700 | C93: Ron | D93: Radu | E93: concert resita soho | F93: Cash
B94: 700 | C94: Ron | D94: Sebi | E94: concert resita soho | F94: Cash
B95: 700 | C95: Ron | D95: Luci | E95: concert resita soho | F95: Cash
B96: 500 | C96: Ron | D96: Altele | E96: dean kai event | F96: Cash
B97: 269 | C97: Ron | D97: Protocol | E97: concert resita soho | F97: Cash
B98: 150 | C98: Ron | D98: Drum | E98: masina arni | F98: Cash
B99: 150 | C99: Ron | D99: Drum | E99: masina carina | F99: Cash
B100: 200 | C100: Ron | D100: Drum | E100: masina buz | F100: Cash
B101: 1250 | C101: Ron | D101: Tehnici | E101: levi si marcel | F101: Cash
A102: 45362 | G102: 1492 | H102: Ron | I102: Avans | J102: nunta 5 iulie | K102: Banca
A103: 45363 | B103: 17.5 | C103: Ron | D103: Comision Retrageri | F103: Banca | L103: 5000
A104: 45369 | G104: 6000 | H104: Ron | I104: Event | J104: concert Kai februarie | K104: Banca
A105: 45371 | B105: 17.5 | C105: Ron | D105: Comision Retrageri | F105: Banca | L105: 2500
A106: 45372 | B106: 4200 | C106: Ron | D106: Contabila | F106: Banca
A107: 45375 | B107: 8 | C107: Ron | D107: Comision Retrageri | F107: Banca | L107: 2000
...

Sheet DatoriiRecuperari 2024
A1: TOTAL DATORII | C1: Datorie Prezent | G1: Datorii persoane | K1: Alte datorii | N1: Recuperari
A2: =A5+A8+A11 -> 0
A4: Total Prezent
A5: =sum(E:E) -> 0
A7: Total Pesoane
A8: =sum(I:I) -> 0
A10: Total alte datorii
A11: =sum(L:L) -> 0
A13: TOTAL RECUPERARI
A14: =sum(P:P) -> 0

Sheet Situatie 2023
A1: Venituri RON | B1: =SUMIF('Tranzactii 2023'!H:H,'Tranzactii 2023'!H3,'Tranzactii 2023'!G:G)-'Tranzactii 2023'!G4+'Tranzactii 2023'!G3 -> 291910 | E1: Restul RON | F1: =sumif('Evenimente 2023'!W:W,'Evenimente 2023'!W14,'Evenimente 2023'!V:V) -> -677 | H1: Total Events | I1: =COUNT('Evenimente 2023'!A:A) -> 47 | L1: Eur | M1: 4.9
A2: Venituri EUR | B2: =sumif('Tranzactii 2023'!H:H,'Tranzactii 2023'!H100,'Tranzactii 2023'!G:G) -> 39700 | E2: Restul EUR | F2: =sumif('Evenimente 2023'!W:W,'Evenimente 2023'!W12,'Evenimente 2023'!V:V) -> -52
A3: Cheltuieli RON | B3: =SUMIF('Tranzactii 2023'!C:C,'Tranzactii 2023'!C3,'Tranzactii 2023'!B:B) -> 297822.55 | E3: Total Restul | F3: =round(F2+F1/M1,0) -> -190 | H3: Public | I3: =countif('Evenimente 2023'!B:B,H3) -> 22
A4: Cheltuieli EUR | B4: =sumif('Tranzactii 2023'!C:C,'Tranzactii 2023'!C101,'Tranzactii 2023'!B:B) -> 39700 | H4: Concert Phaser | I4: =COUNTIF('Evenimente 2023'!C:C,H4) -> 9
A5: Retrageri | B5: =sum('Tranzactii 2023'!L:L) -> 148090 | C5: ron | E5: Fond RON | F5: =sumif('Evenimente 2023'!W:W,'Evenimente 2023'!W5,'Evenimente 2023'!N:N) -> 54380 | H5: Scena mare | I5: =COUNTIF('Evenimente 2023'!C:C,H5) -> 13
A6: Depuneri | B6: =sum('Tranzactii 2023'!N:N) -> 4750 | C6: ron | E6: Fond EUR | F6: =sumif('Evenimente 2023'!W:W,'Evenimente 2023'!W12,'Evenimente 2023'!N:N) -> 5848
A7: Sold Initial | B7: ='Tranzactii 2023'!G3+'Tranzactii 2023'!G4 -> 46584 | C7: ron | E7: Total Fond | F7: =round(F6+F5/M1,0) -> 16946 | G7: Euro
E9: TCH RON | F9: =sumif('Evenimente 2023'!W:W,'Evenimente 2023'!W5,'Evenimente 2023'!L:L) -> 53050 | H9: Privat | I9: =COUNTIF('Evenimente 2023'!B:B,H9) -> 25
A10: Datorii | B10: ='DatoriiRecuperari 2023'!A2 -> 3250 | E10: TCH EUR | F10: =sumif('Evenimente 2023'!W:W,'Evenimente 2023'!W12,'Evenimente 2023'!L:L) -> 9491 | H10: Nunta | I10: =COUNTIF('Evenimente 2023'!C:C,H10) -> 16
E11: Total TCH | F11: =round(F10+F9/M1,0) -> 20318 | G11: Euro | H11: Corporate | I11: =countif('Evenimente 2023'!C:C,H11) -> 8
A12: Balanta RON | B12: =B1+B7-B3 -> 40671.45 | H12: Aniversare | I12: =COUNTIF('Evenimente 2023'!C:C,H12) -> 1
A13: Balanta EUR | B13: =B2-B4 -> 0 | C13: =B13*M1 -> 0 | E13: Prezent RON | F13: =sumif('Evenimente 2023'!W:W,'Evenimente 2023'!W5,'Evenimente 2023'!AB:AB) -> 24850
A14: Balanta | B14: =B12+C13 -> 40671.45 | C14: ron | E14: Prezent EUR | F14: =sumif('Evenimente 2023'!W:W,'Evenimente 2023'!W12,'Evenimente 2023'!AB:AB) -> 3800
A15: Total w.datorii | B15: =B14-B10 -> 37421.45 | C15: ron | E15: Total Prezent | F15: =round(F14+F13/M1,0) -> 8871 | G15: Euro
E17: Tehnici RON | F17: =sumif('Evenimente 2023'!W:W,'Evenimente 2023'!W5,'Evenimente 2023'!AD:AD) -> 18650
E18: Tehnici EUR | F18: =sumif('Evenimente 2023'!W:W,'Evenimente 2023'!W12,'Evenimente 2023'!AD:AD) -> 2441
A19: Onorariu Real 2023 RON | B19: =SUMIF('Onorariu Artist 2023'!H:H,'Onorariu Artist 2023'!H5,'Onorariu Artist 2023'!G:G) -> 22650 | E19: Total Tehnici | F19: =round(F18+F17/M1,0) -> 6247 | G19: Euro
A20: Onorariu Real 2023 EUR | B20: =sumif('Onorariu Artist 2023'!H:H,'Onorariu Artist 2023'!H12,'Onorariu Artist 2023'!G:G) -> 6000
A21: Total Onorariu Real 2023 | B21: =round(B20+B19/M1,0) -> 10622 | C21: euro | E21: Lumini RON
E22: Lumini EUR
A23: Total Onorariu Posibil 2023 RON | B23: =sumif('Onorariu Artist 2023'!H:H,'Onorariu Artist 2023'!H11,'Onorariu Artist 2023'!F:F) -> 29600 | E23: Total Lumini
A24: Total Onorariu Posibil 2023 EUR | B24: =sumif('Onorariu Artist 2023'!H:H,'Onorariu Artist 2023'!H12,'Onorariu Artist 2023'!F:F) -> 6000
A25: Total Onorariu Posibil 2023 | B25: =round(B24+B23/M1,0) -> 12041 | C25: euro | E25: Drum RON
E26: Drum EUR
A27: Total Venit Event 2023 RON | B27: =sumif('Evenimente 2023'!H:H,'Evenimente 2023'!H5,'Evenimente 2023'!G:G) -> 228814 | E27: Total Drum
A28: Total Venit Event 2023 EUR | B28: =sumif('Evenimente 2023'!J:J,'Evenimente 2023'!J12,'Evenimente 2023'!G:G) -> 45050
A29: Total Venit Event 2023 | B29: =round(B27/M1+B28,0) -> 91747 | E29: Extra RON
E30: Extra EUR
E31: Total Extra
E33: DJ RON
E34: DJ EUR
E35: Total DJ
E37: Avans RON | F37: =sumif('Evenimente 2023'!J:J,'Evenimente 2023'!J5,'Evenimente 2023'!I:I) -> 2947
E38: Avans EUR | F38: =sumif('Evenimente 2023'!J:J,'Evenimente 2023'!J12,'Evenimente 2023'!I:I) -> 4500
E39: Total Avans | F39: =round(F38+F37/M1,0) -> 5101
E41: Phaser RON | F41: =sumif('Evenimente 2023'!W:W,'Evenimente 2023'!W5,'Evenimente 2023'!S:S) -> 63070
E42: Phaser EUR | F42: =sumif('Evenimente 2023'!W:W,'Evenimente 2023'!W12,'Evenimente 2023'!S:S) -> 29630
E44: Profit RON | F44: =sumif('Evenimente 2023'!W:W,'Evenimente 2023'!W5,'Evenimente 2023'!M:M) -> 116664
E45: Profit EUR | F45: =sumif('Evenimente 2023'!W:W,'Evenimente 2023'!W12,'Evenimente 2023'!M:M) -> 35514

Sheet Onorariu Artist 2023
F1: Onorariu Artist
A2: Data | B2: Tip Event | C2: Specific | D2: Locatie | E2: Descriere | F2: POSIBIL | G2: REAL | H2: Valuta | I2: Descriere | J2: Carina | K2: Arni | L2: Radu | M2: Sebi | N2: Luci
A3: Ianuarie
A4: Februarie
A5: 17 | B5: Public | C5: Concert | D5: Kai | F5: 600 | G5: 0 | H5: RON | I5: au ramas banii in firma | J5: 0 | K5: 0 | L5: 0 | M5: 0 | N5: 0
A6: 28 | B6: Public | C6: Concert | D6: Filarmonica @ Arad | E6: Tour Vunk | F6: 0 | G6: 0 | H6: RON | I6: gratis | J6: 0 | K6: 0 | L6: 0 | M6: 0 | N6: 0
A7: Martie
A8: 1 | B8: Public | C8: Concert | D8: Filarmonica @ TM | E8: Tour Vunk | F8: 0 | G8: 0 | H8: RON | I8: gratis | J8: 0 | K8: 0 | L8: 0 | M8: 0 | N8: 0
A9: Aprilie
A10: 21 | B10: Public | C10: Concert | D10: Dr.Tr. Severin | E10: Zilele Severinului | F10: 600 | G10: 0 | H10: RON | I10: au ramas banii in firma | J10: 0 | K10: 0 | L10: 0 | M10: 0 | N10: 0
A11: 28 | B11: Privat | C11: Aniversare | D11: Congress Hall | F11: 1950 | G11: 1950 | H11: RON | J11: 1950 | K11: 1950 | L11: 1950 | M11: 1950 | N11: 1950
A12: 30 | B12: Privat | C12: Nunta | D12: Province (Hambar) | F12: 550 | G12: 550 | H12: EUR | J12: 550 | K12: 550 | L12: 550 | M12: 0 | N12: 550
A13: Mai
A14: 6 | B14: Public | C14: Concert | D14: In Spatele Casei | F14: 700 | G14: 0 | H14: RON | I14: am primit banii in 2022 | J14: 0 | K14: 0 | L14: 0 | M14: 0 | N14: 0
A15: 12 | B15: Public | C15: Concert | D15: Kai | F15: 600 | G15: 0 | H15: RON | J15: 0 | K15: 0 | L15: 0 | M15: 0 | N15: 0
A16: 20 | B16: Privat | C16: Nunta | D16: Province (Verde) | F16: 400 | G16: 400 | H16: EUR | J16: 400 | K16: 400 | L16: 400 | M16: 400 | N16: 400
A17: 27 | B17: Privat | C17: Corporate | D17: Herneacova | E17: Party Conti | F17: 2000 | G17: 2000 | H17: RON | J17: 2000 | K17: 2000 | L17: 2000 | M17: 2000 | N17: 2000
A18: Iunie
A19: 3 | B19: Privat | C19: Nunta | D19: Tresor | F19: 350 | G19: 350 | H19: EUR | J19: 350 | K19: 350 | L19: 350 | M19: 350 | N19: 350
A20: 8 | B20: Privat | C20: Corporate | D20: Ikea @ Timisoara | F20: 2150 | G20: 0 | H20: RON | J20: 0 | K20: 0 | L20: 0 | M20: 0 | N20: 0
A21: 10 | B21: Privat | C21: Nunta | D21: Province | F21: 500 | G21: 500 | H21: EUR | J21: 500 | K21: 500 | L21: 500 | M21: 500 | N21: 500
A22: 17 | B22: Public | C22: Concert | D22: Aerdrom Cioca @ TM | E22: Vest Fest District | F22: 500 | G22: 500 | H22: RON | J22: 500 | K22: 500 | L22: 500 | M22: 500 | N22: 500
A23: 23 | B23: Public | C23: Scena mare | D23: Parcul Rozelor | E23: Agronomie | F23: 750 | G23: 750 | H23: RON | J23: 750 | K23: 750 | L23: 750 | M23: 750 | N23: 0
A24: 25 | B24: Public | C24: Concert | D24: @ Margina | E24: brunch in lavanda | F24: 0 | G24: 0 | H24: RON | J24: 0 | K24: 0 | L24: 0 | M24: 0 | N24: 0
A25: Iulie
A26: 1 | B26: Public | C26: Concert | D26: Lugoj | E26: Aniversare Boch | F26: 900 | G26: 900 | H26: RON | J26: 900 | K26: 900 | L26: 900 | M26: 900 | N26: 900
A27: 2 | B27: Privat | C27: Nunta | D27: Villa Trevi @ Bazos | F27: 400 | G27: 400 | H27: EUR | J27: 400 | K27: 400 | L27: 400 | M27: 400 | N27: 400
A28: 8 | B28: Privat | C28: Nunta | D28: Galla | F28: 400 | G28: 400 | H28: EUR | J28: 400 | K28: 400 | L28: 400 | M28: 400 | N28: 400
A29: 15 | B29: Public | C29: Concert | D29: Timisoara | E29: Scena de acasa | F29: 800 | G29: 800 | H29: RON | J29: 800 | K29: 800 | L29: 800 | M29: 800 | N29: 800
A30: 15 | B30: Public | C30: Concert | D30: Timisoara | E30: OFF | F30: 0 | G30: 0 | H30: RON | J30: 0 | K30: 0 | L30: 0 | M30: 0 | N30: 0
A31: 28 | B31: Privat | C31: Nunta | D31: Province | F31: 350 | G31: 350 | H31: EUR | J31: 350 | K31: 350 | L31: 350 | M31: 350 | N31: 350
A32: 29 | B32: Privat | C32: Nunta | D32: Tresor | F32: 400 | G32: 400 | H32: EUR | J32: 400 | K32: 400 | L32: 400 | M32: 400 | N32: 400
A33: August
A34: 2 | B34: Public | C34: Concert | D34: Timisoara | E34: Zilele Timisoara | F34: 1200 | G34: 0 | H34: RON | J34: 0 | K34: 0 | L34: 0 | M34: 0 | N34: 0
A35: 5 | B35: Privat | C35: Nunta | D35: Province (Verde) | F35: 350 | G35: 350 | H35: EUR | J35: 350 | K35: 350 | L35: 350 | M35: 350 | N35: 350
A36: 20 | B36: Privat | C36: Nunta | D36: Province | F36: 400 | G36: 400 | H36: EUR | J36: 400 | K36: 400 | L36: 400 | M36: 400 | N36: 400
A37: 26 | B37: Privat | C37: Nunta | D37: Province | F37: 500 | G37: 500 | H37: EUR | J37: 500 | K37: 500 | L37: 500 | M37: 500 | N37: 500
A38: 26 | B38: Privat | C38: Corporate | D38: Muzeul Satului | F38: 2000 | G38: 2000 | H38: RON | J38: 2000 | K38: 2000 | L38: 2000 | M38: 2000 | N38: 2000
A39: Septembrie
A40: 8 | B40: Public | C40: Concert | D40: Jebel | E40: Youth Day | F40: 700 | G40: 0 | H40: RON | J40: 0 | K40: 0 | L40: 0 | M40: 0 | N40: 0
A41: 9 | B41: Privat | C41: Nunta | D41: Valery | F41: 250 | G41: 250 | H41: EUR | J41: 250 | K41: 250 | L41: 250 | M41: 250 | N41: 250
A42: 10 | B42: Public | C42: Concert | D42: Giarmata | E42: Zilele Giarmata | F42: 1000 | G42: 1000 | H42: RON | J42: 1000 | K42: 1000 | L42: 1000 | M42: 1000 | N42: 1000
A43: 15 | B43: Privat | C43: Corporate | D43: Diamonds | F43: 1500 | G43: 1500 | H43: RON | J43: 1500 | K43: 1500 | L43: 1500 | M43: 1500 | N43: 1500
A44: 17 | B44: Privat | C44: Nunta | D44: Valery | F44: 300 | G44: 300 | H44: EUR | J44: 300 | K44: 300 | L44: 300 | M44: 300 | N44: 300
A45: 23 | B45: Privat | C45: Nunta | D45: Venue | F45: 400 | G45: 400 | H45: EUR | J45: 400 | K45: 400 | L45: 400 | M45: 400 | N45: 400
A46: Octombrie
A47: 7 | B47: Privat | C47: Nunta | D47: Anna Summer @ Tg.Jiu | F47: 2500 | G47: 2500 | H47: RON | J47: 2500 | K47: 2500 | L47: 2500 | M47: 2500 | N47: 2500
A48: 20 | B48: Public | C48: Concert | D48: Sala Lira @ CCMT | E48: Anti Bullying | F48: 650 | G48: 450 | H48: RON | J48: 450 | K48: 450 | L48: 450 | M48: 450 | N48: 450
A49: 24 | B49: Public | C49: Concert | D49: Sala Lira @ CCMT | E49: Anti Bullying | F49: 650 | G49: 450 | H49: RON | J49: 450 | K49: 450 | L49: 450 | M49: 450 | N49: 450
A50: 28 | B50: Privat | C50: Nunta | D50: Province | F50: 450 | G50: 450 | H50: EUR | J50: 450 | K50: 450 | L50: 450 | M50: 450 | N50: 450
A51: Noiembrie
A52: Decembrie
A53: 9 | B53: Public | C53: Concert Phaser | D53: Hotel Rogge | E53: CS Resita | F53: 550 | G53: 550 | H53: RON | J53: 550 | K53: 550 | L53: 550 | M53: 550 | N53: 550
A54: 9 | B54: Privat | C54: Corporate | D54: J'Adore Lugoj | E54: Rotary Lugoj | F54: 1300 | G54: 1300 | H54: RON | J54: 1300 | K54: 1300 | L54: 1300 | M54: 1300 | N54: 1300
A55: 15 | B55: Public | C55: Concert Phaser | D55: Kai | F55: 850 | G55: 850 | H55: RON | J55: 850 | K55: 850 | L55: 850 | M55: 850 | N55: 850
A56: 16 | B56: Privat | C56: Corporate | D56: Hotel Timisoara | E56: Christmas Party | F56: 1250 | G56: 1250 | H56: RON | J56: 1250 | K56: 1250 | L56: 1250 | M56: 1250 | N56: 1250
A57: 16 | B57: Privat | C57: Corporate | D57: D'arc Timisoara | E57: Christmas Party | F57: 1250 | G57: 1250 | H57: RON | J57: 1250 | K57: 1250 | L57: 1250 | M57: 1250 | N57: 1250
A58: 16 | B58: Privat | C58: Corporate | D58: Congress Hall | E58: Smartfit | F58: 1150 | G58: 1150 | H58: RON | J58: 1150 | K58: 1150 | L58: 1150 | M58: 1150 | N58: 1150
A59: 17 | B59: Public | C59: Scena mare | D59: Centru @ Resita | E59: Radio Resita | F59: 0 | G59: 0 | H59: RON | J59: 0 | K59: 0 | L59: 0 | M59: 0 | N59: 0
A60: 17 | B60: Public | C60: Scena mare | D60: Dacus @ Resita | E60: Radio Resita | F60: 0 | G60: 0 | H60: RON | J60: 0 | K60: 0 | L60: 0 | M60: 0 | N60: 0
A61: 31 | B61: Public | C61: Scena mare | D61: Piata Operei Timisoara | F61: 1500 | G61: 1500 | H61: RON | J61: 1500 | K61: 1500 | L61: 1500 | M61: 1500 | N61: 1500

Sheet Evenimente 2023
AA1: Cheltuieli
A2: Data | B2: Tip Event | C2: Specific | D2: Locatie | E2: Descriere | F2: Nr. Ctr. | G2: Total | H2: Valuta | I2: Avans | J2: Valuta | K2: 0.01 | L2: TCH | M2: Profit | N2: Fond | O2: %fond | P2: DivPH | Q2: AlteDiv | R2: %DIV | S2: Phaser | T2: Calcul Artist | U2: Artist Real | V2: Restul | W2: Valuta | Y2: Detalii | AA2: Prezent | AB2: Pret | AC2: Tehnici | AD2: Pret | AE2: Drum | AF2: Pret | AG2: Lumini | AH2: Pret | AI2: DJ | AJ2: Pret | AK2: Extra | AL2: Pret
A3: Ianuarie
A4: Februarie
A5: 17 | B5: Public | C5: Concert Phaser | D5: Kai | F5: Fact. | G5: 5500 | H5: RON | I5: 0 | J5: RON | K5: =round(G5*1%,0) -> 55 | L5: =sum(AB5+AD5+AF5+AH5+AJ5+AL5) -> 1700 | M5: =G5-K5-L5 -> 3745 | N5: =round(O5*M5+I5,0) -> 3745 | O5: 1 | P5: =round(R5*(M5-N5),0) -> 0 | Q5: =round(R5*AD5,0) -> 80 | R5: 0.1 | S5: =round(M5-N5-P5-Q5,0) -> -80 | T5: =S5/5 -> -16 | U5: =round(T5,-2) -> 0 | V5: =5*(T5-U5) -> -80 | W5: RON | AA5: Backline | AB5: 900 | AC5: marcel+levi | AD5: 800
A6: 28 | B6: Public | C6: Scena mare | D6: Filarmonica @ Arad | E6: Tour Vunk | G6: 0 | H6: RON | I6: 0 | J6: RON | K6: =round(G6*1%,0) -> 0 | L6: =sum(AB6+AD6+AF6+AH6+AJ6+AL6) -> 2100 | M6: =G6-K6-L6 -> -2100 | N6: =0*M6+I6 -> 0 | P6: =0*(M6-N6) -> 0 | S6: 0 | T6: 0 | U6: 0 | V6: =5*(T6-U6) -> 0 | W6: RON | AA6: Backline | AB6: 700 | AC6: marcel+levi | AD6: 1000 | AE6: buz | AF6: 200 | AK6: protocol | AL6: 200
A7: Martie
A8: 1 | B8: Public | C8: Scena mare | D8: Filarmonica @ TM | E8: Tour Vunk | G8: 0 | H8: RON | I8: 0 | J8: RON | K8: =round(G8*1%,0) -> 0 | L8: =sum(AB8+AD8+AF8+AH8+AJ8+AL8) -> 1700 | M8: =G8-K8-L8 -> -1700 | N8: =0*M8+I8 -> 0 | P8: =0*(M8-N8) -> 0 | S8: 0 | T8: 0 | U8: 0 | V8: =5*(T8-U8) -> 0 | W8: RON | AA8: Backline | AB8: 700 | AC8: marcel+levi | AD8: 800 | AK8: protocol | AL8: 200
A9: Aprilie
A10: 21 | B10: Public | C10: Scena mare | D10: Dr.Tr. Severin | E10: Zilele Severinului | F10: 169 | G10: 7500 | H10: RON | I10: 0 | J10: RON | K10: =round(G10*1%,0) -> 75 | L10: =sum(AB10+AD10+AF10+AH10+AJ10+AL10) -> 3900 | M10: =G10-K10-L10 -> 3525 | N10: =round(O10*M10+I10,0) -> 3525 | O10: 1 | P10: =round(R10*(M10-N10),0) -> 0 | Q10: =round(R10*AD10,0) -> 105 | R10: 0.1 | S10: =round(M10-N10-P10-Q10,0) -> -105 | T10: =S10/5 -> -21 | U10: =round(T10,-2) -> 0 | V10: =5*(T10-U10) -> -105 | W10: RON | AA10: Backline | AB10: 1000 | AC10: marcel+luci | AD10: 1050 | AE10: toate | AF10: 1550 | AK10: protocol | AL10: 300
A11: 28 | B11: Privat | C11: Aniversare | D11: Congress Hall | F11: 167 | G11: 14167 | H11: RON | I11: 1467 | J11: RON | K11: =round(I11*1%,0) -> 15 | L11: =sum(AB11+AD11+AF11+AH11+AJ11+AL11) -> 2700 | M11: =G11-K11-L11 -> 11452 | N11: =round(O11*M11+I11,0) -> 1925 | O11: 0.04 | P11: =round(R11*(M11-N11),0) -> 0 | Q11: =round(R11*AD11,0) -> 0 | R11: 0 | S11: =round(M11-N11-P11-Q11,0) -> 9527 | T11: =S11/5 -> 1905.4 | U11: 1950 | V11: =5*(T11-U11) -> -223 | W11: RON | AA11: Sunet Full | AB11: 1950 | AC11: marcel+levi | AD11: 750
A12: 30 | B12: Privat | C12: Nunta | D12: Province (Hambar) | F12: 157 | G12: 4100 | H12: EUR | I12: 300 | J12: EUR | K12: =round(I12*1%,0) -> 3 | L12: =sum(AB12+AD12+AF12+AH12+AJ12+AL12) -> 1600 | M12: =G12-K12-L12 -> 2497 | N12: =round(O12*M12+I12,0) -> 425 | O12: 0.05 | P12: =round(R12*(M12-N12),0) -> 0 | Q12: =round(R12*AD12,0) -> 0 | R12: 0 | S12: =round(M12-N12-P12-Q12,0) -> 2072 | T12: =S12/4 -> 518 | U12: 550 | V12: =5*(T12-U12) -> -160 | W12: EUR | AA12: Sunet Full | AB12: 400 | AC12: luci+levi | AD12: 200 | AE12: buz | AF12: 50 | AG12: flavius | AH12: 500 | AI12: flavius | AJ12: 450
A13: Mai
A14: 6 | B14: Public | C14: Concert Phaser | D14: In Spatele Casei | G14: 0 | H14: RON | I14: 0 | J14: RON | K14: =round(G14*1%,0) -> 0 | L14: =sum(AB14+AD14+AF14+AH14+AJ14+AL14) -> 2000 | M14: =G14-K14-L14 -> -2000 | N14: =0*M14+I14 -> 0 | P14: =round(10%*(M14-N14),0)+round(10%*AD14,0) -> -120 | S14: 0 | T14: 0 | U14: 0 | V14: =5*(T14-U14) -> 0 | W14: RON | Y14: am primit banii anul trecut, am notat doar banii pt tehnici si backlinesa fie, dar nu scadem din profit | AA14: Backline | AB14: 1200 | AC14: marcel+levi | AD14: 800
A15: 12 | B15: Public | C15: Concert Phaser | D15: Kai | F15: Fact. | G15: 5500 | H15: RON | I15: 0 | J15: RON | K15: =round(G15*1%,0) -> 55 | L15: =sum(AB15+AD15+AF15+AH15+AJ15+AL15) -> 1700 | M15: =G15-K15-L15 -> 3745 | N15: =round(O15*M15+I15,0) -> 3745 | O15: 1 | P15: =round(R15*(M15-N15),0) -> 0 | Q15: =round(R15*AD15,0) -> 80 | R15: 0.1 | S15: =round(M15-N15-P15-Q15,0) -> -80 | T15: =S15/5 -> -16 | U15: =round(T15,-2) -> 0 | V15: =5*(T15-U15) -> -80 | W15: RON | AA15: Backline | AB15: 900 | AC15: marcel+marius | AD15: 800
A16: 20 | B16: Privat | C16: Nunta | D16: Province (Verde) | F16: 161 | G16: 3300 | H16: EUR | I16: 300 | J16: EUR | K16: =round(I16*1%,0) -> 3 | L16: =sum(AB16+AD16+AF16+AH16+AJ16+AL16) -> 1000 | M16: =G16-K16-L16 -> 2297 | N16: =round(O16*M16+I16,0) -> 300 | O16: 0 | P16: =round(R16*(M16-N16),0) -> 0 | Q16: =round(R16*AD16,0) -> 0 | R16: 0 | S16: =round(M16-N16-P16-Q16,0) -> 1997 | T16: =S16/5 -> 399.4 | U16: =round(T16,-1) -> 400 | V16: =5*(T16-U16) -> -3 | W16: EUR | AA16: Sunet Full | AB16: 350 | AC16: marcel+levi | AD16: 200 | AE16: buz | AF16: 50 | AG16: flavius | AH16: 400
A17: 27 | B17: Privat | C17: Corporate | D17: Herneacova | E17: Party Conti | G17: 14626 | H17: RON | I17: 0 | J17: RON | K17: =round(G17*1%,0) -> 146 | L17: =sum(AB17+AD17+AF17+AH17+AJ17+AL17) -> 2250 | M17: =G17-K17-L17 -> 12230 | N17: =round(O17*M17+I17,0) -> 1003 | O17: 0.082 | P17: =round(R17*(M17-N17),0) -> 1123 | Q17: =round(R17*AD17,0) -> 100 | R17: 0.1 | S17: =round(M17-N17-P17-Q17,0) -> 10004 | T17: =S17/5 -> 2000.8 | U17: =round(T17,-1) -> 2000 | V17: =5*(T17-U17) -> 4 | W17: RON | AA17: Backline | AB17: 1000 | AC17: marcel+levi | AD17: 1000 | AE17: buz | AF17: 250
A18: Iunie
A19: 3 | B19: Privat | C19: Nunta | D19: Tresor | F19: 166 | G19: 2700 | H19: EUR | I19: 300 | J19: EUR | K19: =round(I19*1%,0) -> 3 | L19: =sum(AB19+AD19+AF19+AH19+AJ19+AL19) -> 363 | M19: =G19-K19-L19 -> 2334 | N19: =round(O19*M19+I19,0) -> 557 | O19: 0.11 | P19: =round(R19*(M19-N19),0) -> 0 | Q19: =round(R62*AD19,0) -> 16 | R19: 0 | S19: =round(M19-N19-P19-Q19,0) -> 1761 | T19: =S19/5 -> 352.2 | U19: =round(T19,-1) -> 350 | V19: =5*(T19-U19) -> 11 | W19: EUR | AA19: Backline | AB19: 200 | AC19: marcel+levi | AD19: 163
A20: 8 | B20: Privat | C20: Corporate | D20: Ikea @ Timisoara | E20: Deschiderea Ikea | G20: 13872 | H20: RON | I20: 0 | J20: RON | K20: =round(G20*1%,0) -> 139 | L20: =sum(AB20+AD20+AF20+AH20+AJ20+AL20) -> 1800 | M20: =G20-K20-L20 -> 11933 | N20: =round(O20*M20+I20,0) -> 11933 | O20: 1 | P20: =round(R20*(M20-N20),0) -> 0 | Q20: =round(R20*AD20,0) -> 0 | R20: 0 | S20: =round(M20-N20-P20-Q20,0) -> 0 | T20: =S20/5 -> 0 | U20: =round(T20,-1) -> 0 | V20: =5*(T20-U20) -> 0 | W20: RON | AA20: Backline | AB20: 1000 | AC20: marcel+marius | AD20: 800
A21: 10 | B21: Privat | C21: Nunta | D21: Province | E21: Hambar | F21: 134 | G21: 4150 | H21: EUR | I21: 300 | J21: EUR | K21: =round(I21*1%,0) -> 3 | L21: =sum(AB21+AD21+AF21+AH21+AJ21+AL21) -> 1100 | M21: =G21-K21-L21 -> 3047 | N21: =round(O21*M21+I21,0) -> 513 | O21: 0.07 | P21: =round(R21*(M21-N21),0) -> 0 | Q21: =round(R62*AD21,0) -> 20 | R21: 0 | S21: =round(M21-N21-P21-Q21,0) -> 2514 | T21: =S21/5 -> 502.8 | U21: =round(T21,-1) -> 500 | V21: =5*(T21-U21) -> 14 | W21: EUR | AA21: Sunet Full | AB21: 200 | AC21: marcel+levi | AD21: 200 | AE21: buz | AF21: 50 | AG21: lumini | AH21: 500 | AK21: kuky | AL21: 150
A22: 17 | B22: Public | C22: Scena mare | D22: Aerdrom Cioca @ TM | E22: Vest Fest District | F22: 174 | G22: 4955 | H22: RON | I22: 0 | J22: RON | K22: =round(G22*1%,0) -> 50 | L22: =sum(AB22+AD22+AF22+AH22+AJ22+AL22) -> 1800 | M22: =G22-K22-L22 -> 3105 | N22: =round(O22*M22+I22,0) -> 248 | O22: 0.08 | P22: =round(R22*(M22-N22),0) -> 286 | Q22: =round(R22*AD22,0) -> 80 | R22: 0.1 | S22: =round(M22-N22-P22-Q22,0) -> 2491 | T22: =S22/5 -> 498.2 | U22: =round(T22,-1) -> 500 | V22: =5*(T22-U22) -> -9 | W22: RON | AA22: Backline | AB22: 1000 | AC22: bebi+adi | AD22: 800
A23: 23 | B23: Public | C23: Scena mare | D23: Parcul Rozelor | E23: Agronomie | G23: 6000 | H23: RON | I23: 0 | J23: RON | K23: =round(G23*1%,0) -> 60 | L23: =sum(AB23+AD23+AF23+AH23+AJ23+AL23) -> 1800 | M23: =G23-K23-L23 -> 4140 | N23: =round(O23*M23+I23,0) -> 704 | O23: 0.17 | P23: =round(R23*(M23-N23),0) -> 344 | Q23: =round(R23*AD23,0) -> 80 | R23: 0.1 | S23: =round(M23-N23-P23-Q23,0) -> 3012 | T23: =S23/4 -> 753 | U23: =round(T23,-1) -> 750 | V23: =5*(T23-U23) -> 15 | W23: RON | AA23: Backline | AB23: 1000 | AC23: bebi + marcel | AD23: 800
A24: 25 | B24: Public | C24: Scena mare | D24: @ Margina | E24: brunch in lavanda | G24: 3100 | H24: RON | I24: 0 | J24: RON | K24: 0 | L24: =sum(AB24+AD24+AF24+AH24+AJ24+AL24) -> 3100 | M24: =G24-K24-L24 -> 0 | N24: =round(O24*M24+I24,0) -> 0 | O24: 0 | P24: =round(R24*(M24-N24),0) -> 0 | Q24: =round(R24*AD24,0) -> 0 | R24: 0 | S24: =round(M24-N24-P24-Q24,0) -> 0 | T24: =S24/4 -> 0 | U24: =round(T24,-1) -> 0 | V24: =5*(T24-U24) -> 0 | W24: RON | AA24: Backline | AB24: 1500 | AC24: levi+marcel | AD24: 1000 | AF24: 300 | AK24: tobe arni | AL24: 300
A25: Iulie
A26: 1 | B26: Public | C26: Scena mare | D26: Lugoj | E26: Aniversare Boch | F26: 172 | G26: 7693 | H26: RON | I26: 0 | J26: RON | K26: =round(G26*1%,0) -> 77 | L26: =sum(AB26+AD26+AF26+AH26+AJ26+AL26) -> 2400 | M26: =G26-K26-L26 -> 5216 | N26: =round(O26*M26+I26,0) -> 104 | O26: 0.02 | P26: =round(R26*(M26-N26),0) -> 511 | Q26: =round(R26*AD26,0) -> 100 | R26: 0.1 | S26: =round(M26-N26-P26-Q26,0) -> 4501 | T26: =S26/5 -> 900.2 | U26: =round(T26,-1) -> 900 | V26: =5*(T26-U26) -> 1 | W26: RON | AA26: Backline | AB26: 1000 | AC26: levi+marcel | AD26: 1000 | AE26: masini | AF26: 400
A27: 2 | B27: Privat | C27: Nunta | D27: Villa Trevi @ Bazos | F27: 146 | G27: 3350 | H27: EUR | I27: 300 | J27: EUR | K27: =round(I27*1%,0) -> 3 | L27: =sum(AB27+AD27+AF27+AH27+AJ27+AL27) -> 1063 | M27: =G27-K27-L27 -> 2284 | N27: =round(O27*M27+I27,0) -> 300 | O27: 0 | P27: =round(R27*(M27-N27),0) -> 0 | Q27: =round(R27*AD27,0) -> 0 | R27: 0 | S27: =round(M27-N27-P27-Q27,0) -> 1984 | T27: =S27/5 -> 396.8 | U27: 400 | V27: =5*(T27-U27) -> -16 | W27: EUR | AA27: Sunet Full | AB27: 350 | AC27: levi+marcel | AD27: 163 | AE27: buz | AF27: 50 | AG27: flavius | AH27: 500
A28: 8 | B28: Privat | C28: Nunta | D28: Galla | F28: 132 | G28: 2800 | H28: EUR | I28: 300 | J28: EUR | K28: =round(I28*1%,0) -> 3 | L28: =sum(AB28+AD28+AF28+AH28+AJ28+AL28) -> 363 | M28: =G28-K28-L28 -> 2434 | N28: =round(O28*M28+I28,0) -> 422 | O28: 0.05 | P28: =round(R28*(M28-N28),0) -> 0 | Q28: =round(R28*AD28,0) -> 0 | R28: 0 | S28: =round(M28-N28-P28-Q28,0) -> 2012 | T28: =S28/5 -> 402.4 | U28: =round(T28,-1) -> 400 | V28: =5*(T28-U28) -> 12 | W28: EUR | AA28: Backline | AB28: 200 | AC28: levi+marcel | AD28: 163
A29: 15 | B29: Public | C29: Concert Phaser | D29: @ Dumbravita | E29: Scena de acasa | G29: 5000 | H29: RON | I29: 0 | J29: RON | K29: 0 | L29: =sum(AB29+AD29+AF29+AH29+AJ29+AL29) -> 1000 | M29: =G29-K29-L29 -> 4000 | N29: =round(O29*M29+I29,0) -> 0 | O29: 0 | P29: =round(R29*(M29-N29),0) -> 0 | Q29: =round(R29*AD29,0) -> 0 | R29: 0 | S29: =round(M29-N29-P29-Q29,0) -> 4000 | T29: =S29/5 -> 800 | U29: =round(T29,-1) -> 800 | V29: =5*(T29-U29) -> 0 | W29: RON | AA29: Backline | AB29: 1000 | AC29: bebimarius | AD29: 0
A30: 15 | B30: Public | C30: Concert Phaser | D30: Codru Urban Garden | E30: Off Fashion | G30: 2500 | H30: RON | I30: 0 | J30: RON | K30: =round(I30*1%,0) -> 0 | L30: =sum(AB30+AD30+AF30+AH30+AJ30+AL30) -> 2200 | M30: =G30-K30-L30 -> 300 | N30: =round(O30*M30+I30,0) -> 300 | O30: 1 | P30: =round(R30*(M30-N30),0) -> 0 | Q30: =round(R30*AD30,0) -> 0 | R30: 0 | S30: =round(M30-N30-P30-Q30,0) -> 0 | T30: =S30/5 -> 0 | U30: =round(T30,-1) -> 0 | V30: =5*(T30-U30) -> 0 | W30: RON | AA30: Backline | AB30: 1000 | AC30: bebimarius | AD30: 1200
A31: 28 | B31: Privat | C31: Nunta | D31: Province | F31: 168 | G31: 2450 | H31: EUR | I31: 300 | J31: EUR | K31: =round(I31*1%,0) -> 3 | L31: =sum(AB31+AD31+AF31+AH31+AJ31+AL31) -> 350 | M31: =G31-K31-L31 -> 2097 | N31: =round(O31*M31+I31,0) -> 300 | O31: 0 | P31: =round(R31*(M31-N31),0) -> 0 | Q31: =round(R31*AD31,0) -> 0 | R31: 0 | S31: =round(M31-N31-P31-Q31,0) -> 1797 | T31: =S31/5 -> 359.4 | U31: 350 | V31: =5*(T31-U31) -> 47 | W31: EUR | AA31: Backline | AB31: 200 | AC31: marcel | AD31: 100 | AE31: buz | AF31: 50
A32: 29 | B32: Privat | C32: Nunta | D32: Tresor | F32: 149 | G32: 2700 | H32: EUR | I32: 300 | J32: EUR | K32: =round(I32*1%,0) -> 3 | L32: =sum(AB32+AD32+AF32+AH32+AJ32+AL32) -> 363 | M32: =G32-K32-L32 -> 2334 | N32: =round(O32*M32+I32,0) -> 300 | O32: 0 | P32: =round(R32*(M32-N32),0) -> 0 | Q32: =round(R32*AD32,0) -> 0 | R32: 0 | S32: =round(M32-N32-P32-Q32,0) -> 2034 | T32: =S32/5 -> 406.8 | U32: =round(T32,-1) -> 410 | V32: =5*(T32-U32) -> -16 | W32: EUR | AA32: Backline | AB32: 200 | AC32: levi+marcel | AD32: 163
A33: August
A34: 2 | B34: Public | C34: Scena mare | D34: Timisoara | E34: Zilele Timisoarei | G34: 10000 | H34: RON | I34: 0 | J34: RON | K34: =round(G34*1%,0) -> 100 | L34: =sum(AB34+AD34+AF34+AH34+AJ34+AL34) -> 1800 | M34: =G34-K34-L34 -> 8100 | N34: =round(O34*M34+I34,0) -> 8100 | O34: 1 | P34: =round(R34*(M34-N34),0) -> 0 | Q34: =round(R34*AD34,0) -> 0 | R34: 0 | S34: =round(M34-N34-P34-Q34,0) -> 0 | T34: =S34/5 -> 0 | U34: =round(T34,-1) -> 0 | V34: =5*(T34-U34) -> 0 | W34: RON | AA34: Backline | AB34: 1000 | AC34: levi+marcel | AD34: 800
A35: 5 | B35: Privat | C35: Nunta | D35: Province (Verde) | F35: 160 | G35: 3000 | H35: EUR | I35: 300 | J35: EUR | K35: =round(I35*1%,0) -> 3 | L35: =sum(AB35+AD35+AF35+AH35+AJ35+AL35) -> 800 | M35: =G35-K35-L35 -> 2197 | N35: =round(O35*M35+I35,0) -> 410 | O35: 0.05 | P35: =round(R35*(M35-N35),0) -> 0 | Q35: =round(R35*AD35,0) -> 0 | R35: 0 | S35: =round(M35-N35-P35-Q35,0) -> 1787 | T35: =S35/5 -> 357.4 | U35: =round(T35,-1) -> 360 | V35: =5*(T35-U35) -> -13 | W35: EUR | AA35: Sunet Full | AB35: 350 | AC35: marcel | AD35: 100 | AE35: buz | AF35: 50 | AG35: flavius | AH35: 300
A36: 20 | B36: Privat | C36: Nunta | D36: Province | F36: 154 | G36: 2850 | H36: EUR | I36: 300 | J36: EUR | K36: =round(I36*1%,0) -> 3 | L36: =sum(AB36+AD36+AF36+AH36+AJ36+AL36) -> 450 | M36: =G36-K36-L36 -> 2397 | N36: =round(O36*M36+I36,0) -> 372 | O36: 0.03 | P36: =round(R36*(M36-N36),0) -> 0 | Q36: =round(R36*AD36,0) -> 0 | R36: 0 | S36: =round(M36-N36-P36-Q36,0) -> 2025 | T36: =S36/5 -> 405 | U36: =round(T36,-1) -> 410 | V36: =5*(T36-U36) -> -25 | W36: EUR | AA36: Backline | AB36: 200 | AD36: 200 | AE36: buz | AF36: 50
A37: 26 | B37: Privat | C37: Nunta | D37: Province | F37: 136 | G37: 3450 | H37: EUR | I37: 300 | J37: EUR | K37: =round(I37*1%,0) -> 3 | L37: =sum(AB37+AD37+AF37+AH37+AJ37+AL37) -> 500 | M37: =G37-K37-L37 -> 2947 | N37: =round(O37*M37+I37,0) -> 418 | O37: 0.04 | P37: =round(R37*(M37-N37),0) -> 0 | Q37: =round(R37*AD37,0) -> 0 | R37: 0 | S37: =round(M37-N37-P37-Q37,0) -> 2529 | T37: =S37/5 -> 505.8 | U37: 500 | V37: =5*(T37-U37) -> 29 | W37: EUR | AA37: Backline | AB37: 350 | AD37: 100 | AE37: buz | AF37: 50
A38: 26 | B38: Privat | C38: Corporate | D38: Muzeul Satului | F38: 136 | G38: 14076 | H38: RON | I38: 0 | J38: RON | K38: =round(G38*1%,0) -> 141 | L38: =sum(AB38+AD38+AF38+AH38+AJ38+AL38) -> 1800 | M38: =G38-K38-L38 -> 12135 | N38: =round(O38*M38+I38,0) -> 910 | O38: 0.075 | P38: =round(R38*(M38-N38),0) -> 1123 | Q38: =round(R38*AD38,0) -> 80 | R38: 0.1 | S38: =round(M38-N38-P38-Q38,0) -> 10022 | T38: =S38/5 -> 2004.4 | U38: =round(T38,-1) -> 2000 | V38: =5*(T38-U38) -> 22 | W38: RON | AA38: Backline | AB38: 1000 | AC38: levi | AD38: 800
A39: Septembrie
A40: 8 | B40: Public | C40: Scena mare | D40: Jebel | G40: 6452 | H40: RON | I40: 0 | J40: RON | K40: =round(G40*1%,0) -> 65 | L40: =sum(AB40+AD40+AF40+AH40+AJ40+AL40) -> 2200 | M40: =G40-K40-L40 -> 4187 | N40: =round(O40*M40+I40,0) -> 4187 | O40: 1 | P40: =round(R40*(M40-N40),0) -> 0 | Q40: =round(R40*AD40,0) -> 0 | R40: 0 | S40: =round(M40-N40-P40-Q40,0) -> 0 | T40: =S40/5 -> 0 | U40: =round(T40,-1) -> 0 | V40: =5*(T40-U40) -> 0 | W40: RON | AA40: Backline | AB40: 1000 | AD40: 1000 | AE40: buz | AF40: 200
A41: 9 | B41: Privat | C41: Nunta | D41: Valery | F41: 176 | G41: 2000 | H41: EUR | I41: 300 | J41: EUR | K41: =round(I41*1%,0) -> 3 | L41: =sum(AB41+AD41+AF41+AH41+AJ41+AL41) -> 363 | M41: =G41-K41-L41 -> 1634 | N41: =round(O41*M41+I41,0) -> 349 | O41: 0.03 | P41: =round(R41*(M41-N41),0) -> 0 | Q41: =round(R41*AD41,0) -> 0 | R41: 0 | S41: =round(M41-N41-P41-Q41,0) -> 1285 | T41: =S41/5 -> 257 | U41: =round(T41,-1) -> 260 | V41: =5*(T41-U41) -> -15 | W41: EUR | AA41: Backline | AB41: 200 | AD41: 163
A42: 10 | B42: Public | C42: Scena mare | D42: Giarmata | E42: Zilele Giarmata | G42: 7453 | H42: RON | I42: 0 | J42: RON | K42: =round(G42*1%,0) -> 75 | L42: =sum(AB42+AD42+AF42+AH42+AJ42+AL42) -> 2100 | M42: =G42-K42-L42 -> 5278 | N42: =round(O42*M42+I42,0) -> 5278 | O42: 1 | P42: =round(R42*(M42-N42),0) -> 0 | Q42: =round(R42*AD42,0) -> 0 | R42: 0 | S42: =round(M42-N42-P42-Q42,0) -> 0 | T42: =S42/5 -> 0 | U42: =round(T42,-1) -> 0 | V42: =5*(T42-U42) -> 0 | W42: RON | AA42: Backline | AB42: 1000 | AD42: 1000 | AE42: buz | AF42: 100
A43: 15 | B43: Privat | C43: Corporate | D43: Diamonds @ Scalaz | G43: 11117 | H43: RON | I43: 0 | J43: RON | K43: =round(G43*1%,0) -> 111 | L43: =sum(AB43+AD43+AF43+AH43+AJ43+AL43) -> 1900 | M43: =G43-K43-L43 -> 9106 | N43: =round(O43*M43+I43,0) -> 683 | O43: 0.075 | P43: =round(R43*(M43-N43),0) -> 842 | Q43: =round(R43*AD43,0) -> 80 | R43: 0.1 | S43: =round(M43-N43-P43-Q43,0) -> 7501 | T43: =S43/5 -> 1500.2 | U43: =round(T43,-1) -> 1500 | V43: =5*(T43-U43) -> 1 | W43: RON | AA43: Backline | AB43: 1000 | AD43: 800 | AE43: buz | AF43: 100
A44: 17 | B44: Privat | C44: Nunta | D44: Valery | F44: 169 | G44: 2400 | H44: EUR | I44: 300 | J44: EUR | K44: =round(I44*1%,0) -> 3 | L44: =sum(AB44+AD44+AF44+AH44+AJ44+AL44) -> 363 | M44: =G44-K44-L44 -> 2034 | N44: =round(O44*M44+I44,0) -> 503 | O44: 0.1 | P44: =round(R44*(M44-N44),0) -> 0 | Q44: =round(R44*AD44,0) -> 0 | R44: 0 | S44: =round(M44-N44-P44-Q44,0) -> 1531 | T44: =S44/5 -> 306.2 | U44: =round(T44,-2) -> 300 | V44: =5*(T44-U44) -> 31 | W44: EUR | AA44: Backline | AB44: 200 | AD44: 163
A45: 23 | B45: Privat | C45: Nunta | D45: Venue | F45: 165 | G45: 2700 | H45: EUR | I45: 300 | J45: EUR | K45: =round(I45*1%,0) -> 3 | L45: =sum(AB45+AD45+AF45+AH45+AJ45+AL45) -> 363 | M45: =G45-K45-L45 -> 2334 | N45: =round(O45*M45+I45,0) -> 300 | O45: 0 | P45: =round(R45*(M45-N45),0) -> 0 | Q45: =round(R45*AD45,0) -> 0 | R45: 0 | S45: =round(M45-N45-P45-Q45,0) -> 2034 | T45: =S45/5 -> 406.8 | U45: =round(T45,-2) -> 400 | V45: =5*(T45-U45) -> 34 | W45: EUR | AA45: Backline | AB45: 200 | AD45: 163
A46: Octombrie
A47: 7 | B47: Privat | C47: Nunta | D47: Anna Summer @ Tg.Jiu | F47: 148 | G47: 22472 | H47: RON | I47: 1480 | J47: RON | K47: =round(I47*1%,0) -> 15 | L47: =sum(AB47+AD47+AF47+AH47+AJ47+AL47) -> 8700 | M47: =G47-K47-L47 -> 13757 | N47: =round(O47*M47+I47,0) -> 1480 | O47: 0 | P47: =round(R47*(M47-N47),0) -> 0 | Q47: =round(R47*AD47,0) -> 0 | R47: 0 | S47: =round(M47-N47-P47-Q47,0) -> 12277 | T47: =S47/5 -> 2455.4 | U47: 2500 | V47: =5*(T47-U47) -> -223 | W47: RON | AA47: Sunet Full | AB47: 2000 | AD47: 1250 | AE47: toate | AF47: 2000 | AG47: flavius | AH47: 2450 | AI47: flavius | AJ47: 500 | AK47: Podium | AL47: 500
A48: 20 | B48: Public | C48: Concert Phaser | D48: Sala Lira @ CCMT | E48: Anti Bullying | G48: 4500 | H48: RON | I48: 0 | J48: RON | K48: =round(G48*1%,0) -> 45 | L48: =sum(AB48+AD48+AF48+AH48+AJ48+AL48) -> 1200 | M48: =G48-K48-L48 -> 3255 | N48: =round(O48*M48+I48,0) -> 3255 | O48: 1 | P48: =round(R48*(M48-N48),0) -> 0 | Q48: =round(R48*AD48,0) -> 0 | R48: 0 | S48: =round(M48-N48-P48-Q48,0) -> 0 | T48: =S48/5 -> 0 | U48: =round(T48,-1) -> 0 | V48: =5*(T48-U48) -> 0 | W48: RON | AA48: Backline | AB48: 1000 | AD48: 200
A49: 24 | B49: Public | C49: Concert Phaser | D49: Sala Lira @ CCMT | E49: Anti Bullying | G49: 4500 | H49: RON | I49: 0 | J49: RON | K49: =round(G49*1%,0) -> 45 | L49: =sum(AB49+AD49+AF49+AH49+AJ49+AL49) -> 1200 | M49: =G49-K49-L49 -> 3255 | N49: =round(O49*M49+I49,0) -> 3255 | O49: 1 | P49: =round(R49*(M49-N49),0) -> 0 | Q49: =round(R49*AD49,0) -> 0 | R49: 0 | S49: =round(M49-N49-P49-Q49,0) -> 0 | T49: =S49/5 -> 0 | U49: =round(T49,-1) -> 0 | V49: =5*(T49-U49) -> 0 | W49: RON | AA49: Backline | AB49: 1000 | AD49: 200
A50: 28 | B50: Privat | C50: Nunta | D50: Province | G50: 3100 | H50: EUR | I50: 300 | J50: EUR | K50: =round(I50*1%,0) -> 3 | L50: =sum(AB50+AD50+AF50+AH50+AJ50+AL50) -> 450 | M50: =G50-K50-L50 -> 2647 | N50: =round(O50*M50+I50,0) -> 379 | O50: 0.03 | P50: =round(R50*(M50-N50),0) -> 0 | Q50: =round(R50*AD50,0) -> 0 | R50: 0 | S50: =round(M50-N50-P50-Q50,0) -> 2268 | T50: =S50/5 -> 453.6 | U50: =round(T50,-1) -> 450 | V50: =5*(T50-U50) -> 18 | W50: EUR | AA50: Backline | AB50: 200 | AD50: 200 | AE50: buz | AF50: 50
A51: Decembrie
A52: 9 | B52: Public | C52: Concert Phaser | D52: Hotel Rogge | E52: CS Resita | G52: 5000 | H52: RON | I52: 0 | J52: RON | K52: =round(G52*1%,0) -> 50 | L52: =sum(AB52+AD52+AF52+AH52+AJ52+AL52) -> 1550 | M52: =G52-K52-L52 -> 3400 | N52: =round(O52*M52+I52,0) -> 272 | O52: 0.08 | P52: =round(R52*(M52-N52),0) -> 313 | Q52: =round(R52*AD52,0) -> 50 | R52: 0.1 | S52: =round(M52-N52-P52-Q52,0) -> 2765 | T52: =S52/5 -> 553 | U52: =round(T52,-1) -> 550 | V52: =5*(T52-U52) -> 15 | AA52: Backline | AB52: 800 | AD52: 500 | AF52: 250
A53: 9 | B53: Privat | C53: Corporate | D53: J'Adore Lugoj | E53: Rotary Lugoj | G53: 9935 | H53: RON | I53: 0 | J53: RON | K53: =round(G53*1%,0) -> 99 | L53: =sum(AB53+AD53+AF53+AH53+AJ53+AL53) -> 1750 | M53: =G53-K53-L53 -> 8086 | N53: =round(O53*M53+I53,0) -> 809 | O53: 0.1 | P53: =round(R53*(M53-N53),0) -> 728 | Q53: =round(R53*AD53,0) -> 50 | R53: 0.1 | S53: =round(M53-N53-P53-Q53,0) -> 6499 | T53: =S53/5 -> 1299.8 | U53: =round(T53,-1) -> 1300 | V53: =5*(T53-U53) -> -1 | AA53: Backline | AB53: 1000 | AD53: 500 | AF53: 250
A54: 15 | B54: Public | C54: Concert Phaser | D54: Kai | G54: 6000 | H54: RON | I54: 0 | J54: RON | K54: =round(G54*1%,0) -> 60 | L54: =sum(AB54+AD54+AF54+AH54+AJ54+AL54) -> 1000 | M54: =G54-K54-L54 -> 4940 | N54: =round(O54*M54+I54,0) -> 198 | O54: 0.04 | P54: =round(R54*(M54-N54),0) -> 474 | Q54: =round(R54*AD54,0) -> 0 | R54: 0.1 | S54: =round(M54-N54-P54-Q54,0) -> 4268 | T54: =S54/5 -> 853.6 | U54: =round(T54,-1) -> 850 | V54: =5*(T54-U54) -> 18 | AA54: Backline | AB54: 1000 | AD54: 0
A55: 16 | B55: Privat | C55: Corporate | D55: Hotel Timisoara | E55: Christmas Party | G55: 9196 | H55: RON | I55: 0 | J55: RON | K55: =round(G55*1%,0) -> 92 | L55: =sum(AB55+AD55+AF55+AH55+AJ55+AL55) -> 1650 | M55: =G55-K55-L55 -> 7454 | N55: =round(O55*M55+I55,0) -> 447 | O55: 0.06 | P55: =round(R55*(M55-N55),0) -> 701 | Q55: =round(R55*AD55,0) -> 40 | R55: 0.1 | S55: =round(M55-N55-P55-Q55,0) -> 6266 | T55: =S55/5 -> 1253.2 | U55: =round(T55,-1) -> 1250 | V55: =5*(T55-U55) -> 16 | AA55: Backline | AB55: 1200 | AD55: 400 | AF55: 50
A56: 16 | B56: Privat | C56: Corporate | D56: D'arc Timisoara | E56: Christmas Party | G56: 9200 | H56: RON | I56: 0 | J56: RON | K56: =round(G56*1%,0) -> 92 | L56: =sum(AB56+AD56+AF56+AH56+AJ56+AL56) -> 1650 | M56: =G56-K56-L56 -> 7458 | N56: =round(O56*M56+I56,0) -> 447 | O56: 0.06 | P56: =round(R56*(M56-N56),0) -> 701 | Q56: =round(R56*AD56,0) -> 40 | R56: 0.1 | S56: =round(M56-N56-P56-Q56,0) -> 6270 | T56: =S56/5 -> 1254 | U56: =round(T56,-1) -> 1250 | V56: =5*(T56-U56) -> 20 | AA56: Backline | AB56: 1200 | AD56: 400 | AF56: 50
A57: 16 | B57: Privat | C57: Corporate | D57: Congress Hall | E57: Christmas Party | G57: 8500 | H57: RON | I57: 0 | J57: RON | K57: =round(G57*1%,0) -> 85 | L57: =sum(AB57+AD57+AF57+AH57+AJ57+AL57) -> 1550 | M57: =G57-K57-L57 -> 6865 | N57: =round(O57*M57+I57,0) -> 412 | O57: 0.06 | P57: =round(R57*(M57-N57),0) -> 645 | Q57: =round(R57*AD57,0) -> 40 | R57: 0.1 | S57: =round(M57-N57-P57-Q57,0) -> 5768 | T57: =S57/5 -> 1153.6 | U57: =round(T57,-1) -> 1150 | V57: =5*(T57-U57) -> 18 | AA57: Backline | AB57: 1100 | AD57: 400 | AF57: 50
A58: 17 | B58: Public | C58: Scena mare | D58: Centru Resita | E58: Radio Resita | G58: 0 | H58: RON | I58: 0 | J58: RON | K58: =round(G58*1%,0) -> 0 | L58: =sum(AB58+AD58+AF58+AH58+AJ58+AL58) -> 1000 | M58: =G58-K58-L58 -> -1000 | N58: =round(O58*M58+I58,0) -> 0 | O58: 0 | P58: =round(R58*(M58-N58),0) -> 0 | Q58: =round(R58*AD58,0) -> 0 | R58: 0 | S58: =round(M58-N58-P58-Q58,0) -> -1000 | T58: =S58/5 -> -200 | U58: 0 | V58: =5*(T58-U58) -> -1000 | AA58: Backline | AB58: 600 | AD58: 400
A59: 17 | B59: Public | C59: Scena mare | D59: Parcare Dacus Resita | E59: Radio Resita | G59: 0 | H59: RON | I59: 0 | J59: RON | K59: =round(G59*1%,0) -> 0 | L59: =sum(AB59+AD59+AF59+AH59+AJ59+AL59) -> 1000 | M59: =G59-K59-L59 -> -1000 | N59: =round(O59*M59+I59,0) -> 0 | O59: 0 | P59: =round(R59*(M59-N59),0) -> 0 | Q59: =round(R59*AD59,0) -> 0 | R59: 0 | S59: =round(M59-N59-P59-Q59,0) -> -1000 | T59: =S59/5 -> -200 | U59: 0 | V59: =5*(T59-U59) -> -1000 | AA59: Backline | AB59: 600 | AD59: 400
A60: 31 | B60: Public | C60: Scena mare | D60: Piata Operei Timisoara | G60: 10000 | H60: RON | I60: 0 | J60: RON | K60: =round(G60*1%,0) -> 100 | L60: =sum(AB60+AD60+AF60+AH60+AJ60+AL60) -> 1200 | M60: =G60-K60-L60 -> 8700 | N60: =round(O60*M60+I60,0) -> 348 | O60: 0.04 | P60: =round(R60*(M60-N60),0) -> 835 | Q60: =round(R60*AD60,0) -> 0 | R60: 0.1 | S60: =round(M60-N60-P60-Q60,0) -> 7517 | T60: =S60/5 -> 1503.4 | U60: =round(T60,-1) -> 1500 | V60: =5*(T60-U60) -> 17 | AA60: Backline | AB60: 1200 | AD60: 0
A62: TEST | K62: =round(G62*1%,0) -> 0 | L62: =sum(AB62+AD62+AF62+AH62+AJ62+AL62) -> 0 | M62: =G62-K62-L62 -> 0 | N62: =round(O62*M62+I62,0) -> 0 | O62: 0.15 | P62: =round(R62*(M62-N62),0) -> 0 | Q62: =round(R62*AD62,0) -> 0 | R62: 0.1 | S62: =round(M62-N62-P62-Q62,0) -> 0 | T62: =S62/5 -> 0 | U62: =round(T62,-1) -> 0 | V62: =5*(T62-U62) -> 0

Sheet Tranzactii 2023
B1: Cheltuieli | G1: Venituri | L1: Retrageri | N1: Depuneri
A2: Data | B2: Suma | C2: Valuta | D2: Categorie | E2: Descriere | F2: Mod | G2: Suma | H2: Valuta | I2: Categorie | J2: Descriere | K2: Mod | L2: Suma | M2: Descriere | N2: Suma | O2: Descriere
A3: 44927 | B3: 1500 | C3: Ron | D3: Luci | E3: cantari extra 2022 | F3: Cash | G3: 600 | H3: Ron | J3: Sold initial 2022 | K3: Cash
B4: 1000 | C4: Ron | D4: Radu | E4: cantari extra 2022 | F4: Cash | G4: 45984 | H4: Ron | J4: Sold initial 2022 | K4: Banca
B5: 700 | C5: Ron | D5: Tehnici | E5: marius revelion | F5: Cash
B6: 500 | C6: Ron | D6: Drum | E6: motorina radu revelion | F6: Cash
B7: 150 | C7: Ron | D7: Recuperari | E7: protocol revelion luci | F7: Cash
A8: 44928 | B8: 100 | C8: Ron | D8: Drive | E8: google drive storage | F8: Banca
B9: 1425 | C9: Ron | D9: Promo Meta | F9: Banca
A10: 44929 | B10: 42.5 | C10: Ron | D10: Drive | E10: Gsuite | F10: Banca
A11: 44932 | B11: 200 | C11: Ron | D11: Drum | E11: masina sebi revelion | F11: Cash | G11: 2400 | H11: Ron | I11: Imprumut | J11: Radu | K11: Cash | L11: 5000
B12: 14500 | C12: Ron | D12: Sebi | E12: cantari extra 2022 | F12: Cash | L12: 5000
B13: 1000 | C13: Ron | D13: Arni | E13: cantari extra 2022 | F13: Cash
B14: 8000 | C14: Ron | D14: Arni | E14: cantari extra 2022 | F14: Cash
B15: 2000 | C15: Ron | D15: Radu | E15: cantari extra 2022 | F15: Cash
B16: 1800 | C16: Ron | D16: Carina | E16: cantari extra 2022 | F16: Cash
B17: 17.5 | C17: Ron | D17: Comision Retrageri | F17: Banca
A18: 44935 | B18: 2400 | C18: Ron | D18: Prezent | F18: Banca
B19: 0.51 | C19: Ron | D19: Comision Operatiune | F19: Banca
A20: 44936 | B20: 1460 | C20: Ron | D20: Radu | E20: cantari extra 2022 | F20: Cash | G20: 11755 | H20: Ron | I20: Event | J20: party privat 20.12.2022 | K20: Banca
A21: 44943 | B21: 14 | C21: Ron | D21: Comision Retrageri | F21: Banca | L21: 6000
B22: 21 | C22: Ron | D22: Comision Retrageri | F22: Banca | L22: 4000
A23: 44945 | B23: 9200 | C23: Ron | D23: Carina | E23: cantari extra 2022 | F23: Cash | G23: 4000 | H23: Ron | I23: Event | J23: concert kai 30 dec | K23: Banca
A24: 44951 | B24: 53 | C24: Ron | D24: Salariu | F24: Banca | G24: 1477 | H24: Ron | I24: Avans | J24: nunta 03.06.2023 | L24: 2000
B25: 0.51 | C25: Ron | D25: Comision Operatiune | F25: Banca
B26: 961 | C26: Ron | D26: Impozit | F26: Banca
B27: 0.51 | C27: Ron | D27: Comision Operatiune | F27: Banca
B28: 309 | C28: Ron | D28: TVA | F28: Banca
B29: 0.51 | C29: Ron | D29: Comision Operatiune | F29: Banca
B30: 3 | C30: Ron | D30: Salariu | F30: Banca
B31: 0.51 | C31: Ron | D31: Comision Operatiune | F31: Banca
B32: 7 | C32: Ron | D32: Comision Retrageri | F32: Banca
A33: 44954 | G33: 1480 | H33: Ron | I33: Avans | J33: nunta 29.07.2023 | K33: Banca
A34: 44957 | B34: 35 | C34: Ron | D34: ING Card | F34: Banca
A37: 44960 | B37: 42.22 | C37: Ron | D37: Drive | F37: Banca
A38: 44962 | L38: 2500
A39: 44967 | B39: 12.25 | C39: Ron | D39: Comision Retrageri | F39: Banca | L39: 3500
A40: 44971 | B40: 2400 | C40: Ron | D40: Recuperari | E40: radu imprumut 6 ian | F40: Cash | G40: 1467 | H40: Ron | I40: Avans | J40: nunta 28.04.2023 | K40: Banca
A41: 44972 | B41: 5.25 | C41: Ron | D41: Comision Retrageri | F41: Banca | L41: 1500
A42: 44974 | B42: 800 | C42: Ron | D42: Tehnici | E42: marcel + marius | F42: Cash
A43: 44976 | B43: 5.25 | C43: Ron | D43: Comision Retrageri | F43: Banca | L43: 1500
A44: 44977 | B44: 500 | C44: Ron | D44: Video | E44: video iubire mashup | F44: Cash | G44: 1470 | H44: Ron | I44: Avans | J44: nunta 28.07.2023 | K44: Banca
A45: 44979 | B45: 17.5 | C45: Ron | D45: Comision Retrageri | F45: Banca | L45: 5000
A46: 44982 | B46: 1.75 | C46: Ron | D46: Comision Retrageri | F46: Banca | L46: 500
A47: 44985 | B47: 17.5 | C47: Ron | D47: Comision Retrageri | F47: Banca | L47: 5000
B48: 35 | C48: Ron | D48: ING Card | F48: Banca
B49: 1000 | C49: Ron | D49: Tehnici | E49: marcel+levi concert vunk | F49: Cash
B50: 200 | C50: Ron | D50: Drum | E50: buz concert vunk | F50: Cash
B51: 300 | C51: Ron | D51: Protocol | E51: beri+mancare vunk | F51: Cash
A54: 44986 | B54: 800 | C54: Ron | D54: Tehnici | E54: marcel+levi concert vunk | F54: Cash
B55: 300 | C55: Ron | D55: Protocol | E55: beri+mancare vunk | F55: Cash
A56: 44988 | B56: 42.37 | C56: Ron | D56: Drive | F56: Banca
A57: 44991 | L57: 1500
A58: 44995 | L58: 750
L59: 450
A60: 44996 | B60: 2.5 | C60: Ron | D60: Comision Retrageri | F60: Banca | L60: 900
B61: 9 | C61: Ron | D61: Comision Retrageri | F61: Banca
A62: 44997 | B62: 2.5 | C62: Ron | D62: Comision Retrageri | F62: Banca | L62: 900
B63: 9 | C63: Ron | D63: Comision Retrageri | F63: Banca
A64: 45000 | G64: 5500 | H64: Ron | I64: Event | J64: concert kai | K64: Banca | L64: 2000
A65: 45001 | B65: 1.75 | C65: Ron | D65: Comision Retrageri | F65: Banca | L65: 500
A66: 45002 | B66: 5.25 | C66: Ron | D66: Comision Retrageri | F66: Banca | L66: 1500
A67: 45004 | G67: 1470 | H67: Ron | I67: Avans | J67: nunta 17.09.2023 | K67: Banca
A68: 45009 | B68: 7 | C68: Ron | D68: Comision Retrageri | F68: Banca | L68: 2000
B69: 10.5 | C69: Ron | D69: Comision Retrageri | F69: Banca | L69: 3000
A70: 45014 | B70: 8.75 | C70: Ron | D70: Comision Retrageri | F70: Banca | L70: 2500
A71: 45015 | B71: 1500 | C71: Ron | D71: Promo Meta | F71: Banca
B72: 3000 | C72: Ron | D72: Contabila | F72: Banca
A73: 45016 | B73: 35 | C73: Ron | D73: ING Card | F73: Banca
B74: 1010.24 | C74: Ron | D74: Promo TikTok | E74: radu card | F74: Cash
A77: 45018 | B77: 1500 | C77: Ron | D77: Promo Meta | F77: Banca
A78: 45019 | B78: 117.02 | C78: Ron | D78: Promo Google | F78: Banca
B79: 42.61 | C79: Ron | D79: Drive | F79: Banca
A80: 45024 | B80: 1500 | C80: Ron | D80: Promo Meta | F80: Banca
A81: 45031 | B81: 40.7 | C81: Ron | D81: Factureaza | F81: Banca
A82: 45037 | B82: 1200 | C82: Ron | D82: Tehnici | E82: luci + marcel concert severin | F82: Cash
B83: 700 | C83: Ron | D83: Drum | E83: buz radu severin | F83: Cash
B84: 350 | C84: Ron | D84: Drum | E84: arni severin | F84: Cash
B85: 250 | C85: Ron | D85: Drum | E85: sebi severin | F85: Cash
B86: 250 | C86: Ron | D86: Drum | E86: luci severin | F86: Cash
B87: 200 | C87: Ron | D87: Protocol | E87: sebi severin | F87: Cash
B88: 100 | C88: Ron | D88: Protocol | E88: radu marcel severin | F88: Cash
A89: 45040 | G89: 1481 | H89: Ron | I89: Avans | J89: nunta 31.08.2024 | K89: Banca
A90: 45041 | B90: 2500 | C90: Ron | D90: Promo Meta | F90: Banca
A91: 45042 | L91: 1500
A92: 45044 | B92: 1000 | C92: Ron | D92: Tehnici | E92: marcel+levi nunta 28.04.2023 | F92: Cash | G92: 12700 | H92: Ron | I92: Event | J92: nunta 28.04.2023 | K92: Cash
B93: 500 | C93: Ron | D93: Altele | E93: reparatie laptop | F93: Cash
B94: 1950 | C94: Ron | D94: Carina | E94: nunta 28.04.2023 | F94: Cash
B95: 1950 | C95: Ron | D95: Radu | E95: nunta 28.04.2023 | F95: Cash
B96: 1950 | C96: Ron | D96: Arni | E96: nunta 28.04.2023 | F96: Cash
B97: 1950 | C97: Ron | D97: Luci | E97: nunta 28.04.2023 | F97: Cash
B98: 1950 | C98: Ron | D98: Sebi | E98: nunta 28.04.2023 | F98: Cash
A99: 45045 | L99: 250
A100: 45046 | B100: 35 | C100: Ron | D100: ING Card | F100: Banca | G100: 2950 | H100: Euro | I100: Event | J100: nunta 30.04.2023 | K100: Cash
B101: 550 | C101: Euro | D101: Radu | E101: nunta 30.04.2023 | F101: Cash
B102: 550 | C102: Euro | D102: Carina | E102: nunta 30.04.2023 | F102: Cash
B103: 550 | C103: Euro | D103: Luci | E103: nunta 30.04.2023 | F103: Cash
B104: 550 | C104: Euro | D104: Arni | E104: nunta 30.04.2023 | F104: Cash
B105: 1000 | C105: Ron | D105: Tehnici | E105: luci + levi | F105: Cash
B106: 250 | C106: Ron | D106: Drum | E106: buz radu | F106: Cash
...

Sheet DatoriiRecuperari 2023
A1: TOTAL | C1: Datorie Prezent | G1: Datorii persoane | K1: Alte datorii | N1: Recuperari
A2: =A5+A8+A11 -> 3250 | G2: Luci | H2: cantari 2022 | I2: 1750 | K2: fitt | L2: 1500
A4: Total Prezent
A5: =sum(E:E) -> 0
A7: Total Pesoane
A8: =sum(I:I) -> 1750
A10: Total alte datorii
A11: =sum(L:L) -> 1500

Sheet Situatie 2022
B1: Ron | C1: Eur | E1: Event | F1: 21 | G1: Event | H1: 6 | I1: Event | J1: 20 | K1: Nr Event | L1: =F1+H1+J1 -> 47
A2: Total Incasari | E2: Concerte | F2: =sum(F3:F23) -> 8400 | G2: Party | H2: =sum(H3:H22) -> 7700 | I2: Nunti | J2: =sum(J3:J21) -> 36425
A3: Cheltuieli Sunet | B3: 33260 | E3: 9 ian | F3: 600 | G3: 4 noiembrie | H3: 1000 | I3: 7 mai | J3: 1600
A4: Cheltuieli Tehnici | B4: 18400 | E4: 12 mt | F4: 0 | G4: 26 noiembrie | H4: 1400 | I4: 14 mai | J4: 1600
A5: Impozit | E5: 1 aprilie | F5: 0 | G5: 9 dc | H5: 1000 | I5: 21 mai | J5: 1750
A6: Contabila | E6: 16 aprilie | F6: 0 | G6: 10 dc | H6: 1000 | I6: 28 mai | J6: 1750
A7: TVA | E7: 10 iunie | F7: 0 | G7: 16 dc | H7: 1800 | I7: 3 iunie | J7: 1750
A8: Comision Retrageri | E8: 17 iunie | F8: 500 | G8: 22 dc | H8: 1500 | I8: 4 iunie | J8: 1750
A9: ING | E9: 23 iulie | F9: 500 | I9: 11 iunie | J9: 2000
A10: Lumini | E10: 1 ag | F10: 500 | I10: 12 iunie | J10: 1750
A11: DJ | E11: 14 ag | F11: 500 | I11: 18 iunie | J11: 2200
A12: Alte Tehnica | E12: 26 ag | F12: 500 | I12: 9 iulie | J12: 2250
A13: Drum | E13: 28 ag | F13: 500 | I13: 16 iulie | J13: 2500
A14: Recuperari | E14: 2 sept | F14: 500 | I14: 6 ag | J14: 2000
A15: Video-uri | E15: 17 sept | F15: 800 | I15: 26 ag | J15: 2250
A16: Audio | E16: 24 sept | F16: 500 | I16: 27 ag | J16: 1600
A17: Album | E17: 11 noi | F17: 500 | I17: 3 sept | J17: 1750
A18: Altele | E18: 2 dc | F18: 0 | I18: 4 sept | J18: 1800
E19: 6 dc | F19: 500 | I19: 16 sept | J19: 1600
A20: Total Phaser | B20: =(F2+H2+J2)*5 -> 262625 | C20: =B20/5 -> 52525 | E20: 10 dc | F20: 0 | I20: 18 sept | J20: 2400
A21: Total persoana | B21: =B20/5 -> 52525 | C21: =B21/5 -> 10505 | E21: 18 dc | F21: 0 | I21: 22 ot | J21: 2125
E22: 30 dc | F22: 500 | I22: 23 ot | J22: 2125
E23: 31 dc | F23: 1500

Sheet Evenimente 2022 Extra (De primi
A1: Event | B1: Descriere | C1: Total | D1: 0.03 | E1: Prezent | F1: Alte Ch | G1: Cari | H1: Radu | I1: Luci | J1: Sebi | K1: Arni | M1: Persoana | N1: Total de primit | O1: Primit | P1: Rest de primit
A2: Concert | B2: Targ de Craciun Mall | C2: 3500 | D2: =C2*3% -> 105 | E2: 600 | F2: Trecuta | G2: 600 | H2: 600 | I2: 600 | J2: 600 | K2: 600 | M2: Carina | N2: =sum(G7:G28) -> 15000 | O2: 15000 | P2: =N2-O2 -> 0
A3: Concert | B3: Codru Pre Party | C3: 0 | D3: 0 | E3: 0 | F3: Fond | G3: 0 | H3: 0 | I3: 0 | J3: 0 | K3: 0 | M3: Radu | N3: =sum(G7:G28) -> 15000 | O3: 15000 | P3: =N3-O3 -> 0
A4: Concert | B4: Supriza Darc | C4: 0 | D4: 0 | E4: 0 | F4: Fond | G4: 0 | H4: 0 | I4: 0 | J4: 0 | K4: 0 | M4: Luci | N4: =sum(G7:G28) -> 15000 | O4: 11100 | P4: =N4-O4 -> 3900
A5: Concert | B5: Lansare Album | C5: 0 | D5: 0 | E5: 0 | F5: Fond | G5: 0 | H5: 0 | I5: 0 | J5: 0 | K5: 0 | M5: Sebi | N5: =sum(J7:J16)+sum(J18:J28) -> 14500 | O5: 14500 | P5: =N5-O5 -> 0
A6: Concert | B6: Eftimie Murgu Resita | C6: 0 | D6: 0 | E6: 0 | F6: Fond | G6: 0 | H6: 0 | I6: 0 | J6: 0 | K6: 0 | M6: Arni | N6: =sum(G7:G28) -> 15000 | O6: 15000 | P6: =N6-O6 -> 0
A7: Concert | B7: Take Off | C7: 4943 | D7: =C7*3% -> 148.29 | E7: 750 | F7: 1000 | G7: 500 | H7: 500 | I7: 500 | J7: 500 | K7: 500
A8: Concert | B8: Zilele Hunedoarei | C8: 4932 | D8: =C8*3% -> 147.96 | E8: 750 | F8: 1000 | G8: 500 | H8: 500 | I8: 500 | J8: 500 | K8: 500 | M8: Ing + Fond | N8: 25000 | P8: =sum(P2:P6) -> 3900
A9: Concert | B9: In spatele casei | C9: 6150 | D9: =C9*3% -> 184.5 | E9: 1500 | F9: 1000 | G9: 500 | H9: 500 | I9: 500 | J9: 500 | K9: 500 | M9: Mai e de primit | N9: =C12+C20+C22+C24 -> 33651
A10: Concert | B10: Zilele Lugojului | C10: 4890 | D10: =C10*3% -> 146.7 | E10: 750 | F10: 1000 | G10: 500 | H10: 500 | I10: 500 | J10: 500 | K10: 500 | N10: =N8+N9 -> 58651 | O10: =N10-P8 -> 54751
A11: Concert | B11: Deschidere Flight | C11: 0 | D11: 0 | E11: 0 | F11: Fond | G11: 0 | H11: 0 | I11: 0 | J11: 0 | K11: 0
A12: Concert | B12: Codru | C12: 6000 | D12: =C12*3% -> 180 | E12: 900 | F12: 1000 | G12: 500 | H12: 500 | I12: 500 | J12: 500 | K12: 500 | M12: 0.2 | N12: 35000
A13: Concert | B13: Flight | C13: 4924 | D13: =C13*3% -> 147.72 | E13: 750 | F13: 1000 | G13: 500 | H13: 500 | I13: 500 | J13: 500 | K13: 500
A14: Concert | B14: Sarbatorile Cetatii | C14: 8383 | D14: =C14*3% -> 251.49 | E14: 750 | F14: 1000 | G14: 800 | H14: 800 | I14: 800 | J14: 800 | K14: 800
A15: Concert | B15: Zilele Cenei | C15: 5911 | D15: =C15*3% -> 177.33 | E15: 700 | F15: 1000 | G15: 500 | H15: 500 | I15: 500 | J15: 500 | K15: 500
A16: Party Privat | B16: Topul Firmelor | C16: 9295 | D16: =C16*3% -> 278.85 | E16: 1000 | F16: 1000 | G16: 1000 | H16: 1000 | I16: 1000 | J16: 1000 | K16: 1000
A17: Concert | B17: Kai | C17: 4000 | D17: =C17*3% -> 120 | E17: 700 | F17: 1000 | G17: 500 | H17: 500 | I17: 500 | J17: 0 | K17: 500
A18: Party Privat | B18: Rotary | C18: 11490 | D18: =C18*3% -> 344.7 | E18: 1000 | F18: 1000 | G18: 1400 | H18: 1400 | I18: 1400 | J18: 1400 | K18: 1400
A19: Concert | B19: Lords | C19: 0 | D19: 0 | E19: 0 | F19: Fond | G19: 0 | H19: 0 | I19: 0 | J19: 0 | K19: 0
A20: Concert | B20: Targ de Craciun CJT | C20: 5000 | D20: =C20*3% -> 150 | E20: 700 | F20: 1000 | G20: 500 | H20: 500 | I20: 500 | J20: 500 | K20: 500
A21: Party Privat | B21: Dalli | C21: 8618 | D21: =C21*3% -> 258.54 | E21: 1000 | F21: 1000 | G21: 1000 | H21: 1000 | I21: 1000 | J21: 1000 | K21: 1000
A22: Party Privat | B22: Euroccoper | C22: 8383 | D22: =C22*3% -> 251.49 | E22: 1000 | F22: 1000 | G22: 1000 | H22: 1000 | I22: 1000 | J22: 1000 | K22: 1000
A23: Concert | B23: Retromaniacs | C23: 0 | D23: 0 | E23: 0 | F23: Fond | G23: 0 | H23: 0 | I23: 0 | J23: 0 | K23: 0
A24: Party Privat | B24: Gauss | C24: 14268 | D24: =C24*3% -> 428.04 | E24: 1000 | F24: 1000 | G24: 1800 | H24: 1800 | I24: 1800 | J24: 1800 | K24: 1800
A25: Concert | B25: Radio Resita | C25: 0 | D25: 0 | E25: 0 | F25: 0 | G25: 0 | H25: 0 | I25: 0 | J25: 0 | K25: 0
A26: Party Privat | B26: ADR | C26: 11755 | D26: =C26*3% -> 352.65 | E26: 1000 | F26: 1000 | G26: 1500 | H26: 1500 | I26: 1500 | J26: 1500 | K26: 1500
A27: Concert | B27: Kai | C27: 4000 | D27: =C27*3% -> 120 | E27: 700 | F27: 1000 | G27: 500 | H27: 500 | I27: 500 | J27: 500 | K27: 500
A28: Concert | B28: Lords | G28: 1500 | H28: 1500 | I28: 1500 | J28: 1500 | K28: 1500

Sheet Fond Extra 2022
A1: Incasari | E1: Cheltuieli
A3: Ron | B3: Euro | C3: Data | D3: Descriere | E3: Ron | F3: Euro | G3: Data | H3: Descriere
A4: 1850 | C4: 01.01.2022 | D4: Bani ramasi de pe 2021 | E4: 1125 | H4: PR Daiana Decembrie | J4: T C Ron | K4: =sum(E:E) -> 179210
A5: 300 | C5: 26.01.2022 | D5: Bani scosi degeaba | E5: 3325 | H5: PR Daiana Ianuarie, Februarie, Martie | J5: T V Ron | K5: =sum(A:A) -> 179810
A6: 2000 | C6: 18.02.2022 | D6: Retragere Bancomat | E6: 4185 | H6: Depunere Cont ING
A7: 200 | C7: 03.03.2022 | D7: Retragere Bancomat | E7: 2100 | H7: Cheltuieli Lansare Album | J7: Balanta Ron | K7: =K5-K4 -> 600
A8: 2000 | C8: 07.03.2022 | D8: Retragere Bancomat | E8: 2200 | H8: Cheltuieli Album Fizic
A9: 900 | C9: 08.03.2022 | D9: Retragere Bancomat | E9: 1125 | H9: PR Daiana Aprilie
A10: 2435 | C10: 07.05.2022 | D10: Avans Arni 7 mai 2022 + 20% 7 mai | E10: 1500 | H10: Cheltuieli Lansare Album | J10: T C Eur | K10: =sum(F:F) -> 37150
A11: 5000 | D11: Imprumut Radu | E11: 1500 | H11: Poze George Mihes | J11: T V Eur | K11: =sum(B:B) -> 37150
A12: 1500 | D12: Imprumut Sebi | E12: 1650 | H12: Sala de repetitii
A13: 3500 | D13: Imprumut Sebi | E13: 1000 | H13: recuperare sebi | J13: Balanta Eur | K13: =K11-K10 -> 0
A14: 560 | D14: Imprumut Sebi diferenta de la prima plata de 8000 | E14: 300 | H14: foto lansare album
A15: 1000 | D15: vanzare cd matusa sebi | E15: 3500 | H15: obiectiv anamorfic (flavius) armele jos
A16: 300 | D16: foto lansare album sebi | E16: 1500 | H16: oglinzi luci
A17: 300 | D17: Retragere Bancomat | E17: 300 | H17: kit racire terasa
A18: 1500 | D18: Retragere Bancomat | E18: 400 | H18: materiale clip armele jos
A19: 1500 | D19: imprumut luci | E19: 500 | H19: sacouri clip armele jos
A20: 700 | D20: imprumut carina | E20: 2400 | H20: moving heads parte schela vali potra
A21: 3500 | D21: imprumut radu | E21: 325 | H21: cuie capsator + macare arni
A22: 500 | D22: imprumut radu | E22: 1100 | H22: drum baia mare radu
A23: 13450 | D23: nunta baia mare 14.05.2022 | E23: 500 | H23: recuperare radu
A24: 325 | D24: imprumut arni | E24: 325 | H24: recuperare arni
A25: 500 | D25: Retragere Bancomat | E25: 1600 | H25: parte radu 14.05.2022
... A28: 50 | D28: vanzare album mihes | E28: 1600 | H28: parte sebi 14.05.2022
B29: 2500 | D29: nunta 21.05.2022 | E29: 1600 | H29: avans recuperat luci 14.05.2022
A30: 970 | D30: schimb valutar 200 | E30: 700 | H30: recuperare carina
B31: 2600 | D31: nunta 28.05.2022 | E31: 1500 | H31: recuperare luci
B32: 2400 | D32: nunta 03.06.2022 | E32: 700 | H32: tehnic bula lumini videoclip
B33: 2400 | D33: nunta 04.06.2022 | E33: 1050 | H33: recuperare sebi
B34: 2400 | D34: nunta 11.06.2022 | F34: 1750 | H34: trupa 21.05.2022
B35: 2150 | D35: nunta 12.06.2022 | F35: 200 | H35: schimb valutar
A36: 50 | D36: vanzare album racz | F36: 400 | H36: recuperare radu anamorfic
A37: 13430 | D37: nunta 18.06.2022 | F37: 150 | H37: recuperare luci flori, sucuri, apa dulciuri, pizza
A38: 1920 | D38: schimb valutar | E38: 300 | H38: adi tehnic armele jos
B39: 2600 | C39: 09.07.2022 | D39: nunta 09.07.2022 | E39: 400 | H39: drum oradea radu
B40: 3050 | C40: 16.07.2022 | D40: nunta 16.07.2022 | F40: 400 | H40: recuperare sebi diferenta + poze mihes
B41: 3300 | C41: 06.08.2022 | D41: nunta 06.08.2022 | F41: 1750 | H41: trupa 28.05.2022
A42: 2000 | C42: 08.08.2022 | D42: retrasi bancomat | F42: 50 | H42: drum radu resita
A43: 2000 | C43: 20.08.2022 | D43: retrasi bancomat | F43: 50 | H43: drum luci si arni resita
B44: 3700 | C44: 26.08.2022 | D44: nunta 26.08.2022 | F44: 100 | H44: luci recuperare clip
A45: 970 | C45: 30.08.2022 | D45: schimb valutar 30.08.2022 | F45: 1750 | H45: trupa 03.06.2022
A46: 1000 | B46: 2400 | D46: nunta 10.09.2022 | F46: 450 | H46: recuperare sebi
A47: 19050 | D47: nunta 18.09.2022 | F47: 1750 | H47: trupa 04.06.2022
B48: 2200 | D48: nunta 03.09.2022 | F48: 250 | H48: recuperare sebi
B49: 2400 | D49: nunta 22.10.2022 | F49: 2000 | H49: trupa 11.06.2022
B50: 2900 | D50: nunta 23.10.2022 | F50: 1750 | H50: trupa 12.06.2022
A51: 2000 | C51: 20.08.2022 | D51: retrasi bancomat | F51: 300 | H51: recuperare radu anamorfic
A52: 4000 | C52: 05.09.2022 | D52: retrasi bancomat | E52: 3000 | H52: recuperare radu imprumut
A53: 5000 | C53: 07.09.2022 | D53: retrasi bancomat | E53: 11000 | H53: trupa 18.06.2022
A54: 5000 | C54: 12.09.2022 | D54: retrasi bancomat | F54: 400 | H54: schimb valutar
A55: 5000 | C55: 14.09.2022 | D55: retrasi bancomat | E55: 2000 | H55: recuperare imprumut radu
A56: 3000 | C56: 14.09.2022 | D56: retrasi bancomat | E56: 500 | H56: recuperare microgrant radu
A57: 5000 | C57: 24.09.2022 | D57: retrasi bancomat | E57: 1400 | H57: am depus in ing
A58: 2000 | C58: 02.10.2022 | D58: retrasi bancomat | F58: 2250 | H58: trupa 09.07.2022
A59: 5000 | C59: 18.10.2022 | D59: retrasi bancomat | F59: 1300 | H59: sonorizari prezent ianuarie - iunie
A60: 6500 | C60: 13.11.2022 | D60: retrasi bancomat | E60: 500 | H60: parte recuperare radu
A61: 1550 | C61: 18.11.2022 | D61: retrasi bancomat | F61: 2500 | H61: trupa 16.07.2022
A62: 5000 | C62: 23.11.2022 | D62: retrasi bancomat | F62: 100 | H62: tehnic 16.07.2022
A63: 4000 | C63: 23.11.2022 | D63: retrasi bancomat | F63: 150 | H63: podium 16.07.2022
A64: 1500 | C64: 25.11.2022 | D64: retrasi bancomat | E64: 250 | H64: drum 16.07.2022
A65: 5000 | C65: 01.12.2022 | D65: retrasi bancomat | F65: 2000 | H65: trupa 06.08.2022
A66: 5000 | C66: 05.12.2022 | D66: retrasi bancomat | F66: 350 | H66: sunet 06.08.2022
A67: 3000 | C67: 09.12.2022 | D67: retrasi bancomat | F67: 700 | H67: flavius 06.08.2022
A68: 5000 | C68: 15.12.2022 | D68: retrasi bancomat | E68: 300 | H68: tehnic marius 06.08.2022
A69: 1000 | C69: 17.12.2022 | D69: retrasi bancomat | E69: 150 | H69: tehnic sorin 06.08.2022
B70: 150 | C70: rotary sunet | E70: 500 | H70: tehnic 23.07.2022
A71: 1000 | D71: lords concert | E71: 1400 | H71: Depunere ING
A72: 5000 | C72: 21.12.2022 | D72: retrasi bancomat | E72: 2050 | H72: tehnici 26.08-28.08
A73: 1800 | C73: 24.12.2022 | D73: retrasi bancomat | F73: 350 | H73: sunet 26.06.2022
A74: 4000 | C74: 28.12.2022 | D74: retrasi bancomat | F74: 850 | H74: flavius 26.08.2022
A75: 7500 | C75: 31.12.2022 | D75: concert lords | F75: 2250 | H75: trupa 26.08.2022
F76: 200 | G76: 30.08.2022 | H76: schimb valutar 30.08.2022
F77: 450 | H77: recuperare radu cazari + drum buc 2022
F78: 500 | H78: recuperare carina clip
F79: 2000 | H79: trupa 10.09.2022
F80: 400 | H80: sunet 10.09.2022
E81: 300 | H81: tehnic adi 02.09
E82: 1000 | H82: marcel 16-17.09
E83: 500 | H83: levi 16.09
F84: 1750 | H84: trupa 03.09.2022
E85: 12000 | H85: trupa 18.09.2022
E86: 2450 | H86: ghita dj
E87: 1300 | H87: buz
E88: 1300 | H88: sunet inchiriat 18.09.2022
F89: 350 | H89: sunet 03.09.2022
E90: 850 | H90: 10% carjan
F91: 4250 | H91: trupa 22-23.10.2022
F92: 400 | H92: tehnic 22-23.10.2022
F93: 550 | H93: sunet 22-23.10.2022
E94: 7000 | H94: luci cantari
E95: 5000 | H95: arni cantari
E96: 12500 | H96: teatru pentru tine
E97: 200 | H97: luci drum oradea
E98: 9000 | H98: trupa 04.09.2022
E99: 1200 | H99: concert bega tehnici
E100: 800 | H100: concert codru tehnici
E101: 800 | H101: 04.09.2022 tehnici
E102: 800 | H102: cenei tehnici
E103: 800 | H103: topu firmelor tehinici
...

Sheet Evenimente 2022
A1: Data | B1: Tip Event | C1: Specific | D1: Locatie | E1: Nr. Ctr. | F1: Descriere Event | I1: 0.03 | J1: Cheltuieli | S1: MP/Fond | T1: Phaser
G2: Total | H2: Avans | J2: TCH | K2: Sunet | L2: Pret | M2: Tehnici | N2: Pret | O2: Drum | P2: Pret | Q2: Exra | R2: Pret | S2: 0.2 | T2: De primit | V2: In firma | X2: Cari | Y2: Radu | Z2: Luci | AA2: Sebi | AB2: Arni
H3: Ron | T3: Ron | U3: Eur | V3: Ron | W3: Eur
A4: Ianuarie
A5: 9 | B5: Public | C5: Concert | D5: Iulius Town @ Timisoara | G5: 3500 | H5: 0 | I5: =round(3%*G5,0) -> 105 | J5: =sum(L5+N5+P5+R5) -> 600 | K5: Backline | L5: 600 | S5: 0 | T5: =G5-H5-I5-J5-S5 -> 2795 | V5: =round(T5-X5-Y5-Z5-AA5-AB5,0) -> 795 | X5: 400 | Y5: 400 | Z5: 400 | AA5: 400 | AB5: 400
A6: Februarie
A7: Martie
A8: 11 | B8: Public | C8: Concert | D8: Padurea Bistra | F8: Codru Festival | G8: 0 | H8: 0 | I8: =round(3%*G8,0) -> 0 | J8: =sum(L8+N8+P8+R8) -> 0 | K8: Backline | L8: 0 | S8: =round(20%*(G8-I8-J8),0) -> 0 | T8: =G8-H8-I8-J8-S8 -> 0 | V8: =round(T8-X8-Y8-Z8-AA8-AB8,0) -> 0 | X8: =round(T8/5,-2) -> 0 | Y8: =round(T8/5,-2) -> 0 | Z8: =round(T8/5,-2) -> 0 | AA8: =round(T8/5,-2) -> 0 | AB8: =round(T8/5,-2) -> 0
A9: Aprilie
A10: 1 | B10: Public | C10: Concert | D10: D'arc Timisoara | G10: 0 | H10: 0 | I10: =round(3%*G10,0) -> 0 | J10: =sum(L10+N10+P10+R10) -> 0 | K10: Backline | L10: 0 | S10: =round(20%*(G10-I10-J10),0) -> 0 | T10: =G10-H10-I10-J10-S10 -> 0 | V10: =round(T10-X10-Y10-Z10-AA10-AB10,0) -> 0 | X10: =round(T10/5,-2) -> 0 | Y10: =round(T10/5,-2) -> 0 | Z10: =round(T10/5,-2) -> 0 | AA10: =round(T10/5,-2) -> 0 | AB10: =round(T10/5,-2) -> 0
A11: 16 | B11: Public | C11: Concert | D11: D'arc Timisoara | G11: 0 | H11: 0 | I11: =round(3%*G11,0) -> 0 | J11: =sum(L11+N11+P11+R11) -> 0 | K11: Sunet Full | L11: 0 | S11: =round(20%*(G11-I11-J11),0) -> 0 | T11: =G11-H11-I11-J11-S11 -> 0 | V11: =round(T11-X11-Y11-Z11-AA11-AB11,0) -> 0 | X11: =round(T11/5,-2) -> 0 | Y11: =round(T11/5,-2) -> 0 | Z11: =round(T11/5,-2) -> 0 | AA11: =round(T11/5,-2) -> 0 | AB11: =round(T11/5,-2) -> 0
A12: Mai
A13: Iunie
A14: 10 | B14: Public | C14: Concert | D14: Centrul Civic @ Resita | G14: 0 | H14: 0 | I14: 0 | J14: 0 | K14: Backline | L14: 0 | S14: =round(20%*(G14-I14-J14),0) -> 0 | T14: =G14-H14-I14-J14-S14 -> 0 | V14: =round(T14-X14-Y14-Z14-AA14-AB14,0) -> 0 | X14: =round(T14/5,-2) -> 0 | Y14: =round(T14/5,-2) -> 0 | Z14: =round(T14/5,-2) -> 0 | AA14: =round(T14/5,-2) -> 0 | AB14: =round(T14/5,-2) -> 0
A15: 17 | B15: Public | C15: Concert | D15: Aeroport @ Caransebes | F15: Festival | G15: 4943 | H15: 0 | I15: =round(3%*G15,0) -> 148 | J15: =sum(L15+N15+P15+R15) -> 1350 | K15: Backline | L15: 750 | O15: Buz + Mica | P15: 600 | S15: 0 | T15: =G15-H15-I15-J15-S15 -> 3445 | V15: =round(T15-X15-Y15-Z15-AA15-AB15,0) -> 3445 | X15: 0 | Y15: 0 | Z15: 0 | AA15: 0 | AB15: 0
A16: Iulie
A17: 23 | B17: Public | C17: Concert | D17: Hunedoara | F17: Zilele Orasului | G17: 4943 | H17: 0 | I17: =round(3%*G17,0) -> 148 | J17: =sum(L17+N17+P17+R17) -> 1850 | K17: Backline | L17: 750 | M17: Tehnic | N17: 500 | O17: Drum | P17: 600 | S17: 0 | T17: =G17-H17-I17-J17-S17 -> 2945 | V17: =round(T17-X17-Y17-Z17-AA17-AB17,0) -> 2945 | X17: 0 | Y17: 0 | Z17: 0 | AA17: 0 | AB17: 0
A18: August
A19: 1 | B19: Public | C19: Concert | D19: In spatele casei @ Timisoara | E19: C141 | F19: Youth Fest | G19: 6200 | H19: 0 | I19: =round(3%*G19,0) -> 186 | J19: =sum(L19+N19+P19+R19) -> 2100 | K19: Sunet Full | L19: 1500 | M19: Tehnic | N19: 600 | S19: 0 | T19: =G19-H19-I19-J19-S19 -> 3914 | V19: =round(T19-X19-Y19-Z19-AA19-AB19,0) -> 3914 | X19: 0 | Y19: 0 | Z19: 0 | AA19: 0 | AB19: 0
A20: 14 | B20: Public | C20: Concert | D20: Lugoj | F20: Zilele Lugojului | G20: 4943 | H20: 0 | I20: =round(3%*G20,0) -> 148 | J20: =sum(L20+N20+P20+R20) -> 1750 | K20: Backline | L20: 750 | M20: Tehnic | N20: 400 | O20: Drum | P20: 600 | S20: 0 | T20: =G20-H20-I20-J20-S20 -> 3045 | V20: =round(T20-X20-Y20-Z20-AA20-AB20,0) -> 3045 | X20: 0 | Y20: 0 | Z20: 0 | AA20: 0 | AB20: 0
A21: 26 | B21: Public | C21: Concert | D21: Bega @ Timisora | F21: Flight Opening | G21: 0 | H21: 0 | I21: =round(3%*G21,0) -> 0 | J21: =sum(L21+N21+P21+R21) -> 1050 | K21: Backline | L21: 0 | M21: Tehnic | N21: 1050 | X21: 0 | Y21: 0 | Z21: 0 | AA21: 0 | AB21: 0
A22: 27 | B22: Privat | C22: Nunta | D22: Taverna Sarbului @ D.T.Severin | E22: C114 | G22: 14922 | H22: 1484 | I22: =round(3%*G22,0) -> 448 | J22: =sum(L22+N22+P22+R22) -> 2600 | K22: Sunet Full | L22: 1700 | O22: Buz + Mica | P22: 900 | S22: =round(20%*(G22-I22-J22),0) -> 2375 | T22: =G22-H22-I22-J22-S22 -> 8015 | V22: =round(T22-X22-Y22-Z22-AA22-AB22,0) -> 15 | X22: =round(T22/5,-2) -> 1600 | Y22: =round(T22/5,-2) -> 1600 | Z22: =round(T22/5,-2) -> 1600 | AA22: =round(T22/5,-2) -> 1600 | AB22: =round(T22/5,-2) -> 1600
A23: 28 | B23: Public | C23: Concert | D23: Padurea Bistra | F23: Codru Festival | G23: 6000 | H23: 0 | I23: =round(3%*G23,0) -> 180 | J23: =sum(L23+N23+P23+R23) -> 1700 | K23: Backline | L23: 900 | M23: Tehnic | N23: 800 | S23: 0 | T23: =G23-H23-I23-J23-S23 -> 4120 | V23: =round(T23-X23-Y23-Z23-AA23-AB23,0) -> 4120 | X23: 0 | Y23: 0 | Z23: 0 | AA23: 0 | AB23: 0
A24: Septembrie
A25: 2 | B25: Public | C25: Concert | D25: Aerodrom Cioca @ Timisoara | F25: Flight Festival | G25: 4943 | H25: 0 | L25: 750
A26: 4 | B26: Privat | C26: Nunta | D26: Venue @ Timisoara | E26: C122 | G26: 12068 | H26: 1477 | I26: =round(3%*G26,0) -> 362 | J26: =sum(L26+N26+P26+R26) -> 950 | K26: Backline | L26: 950 | S26: 1600 | T26: =G26-H26-I26-J26-S26 -> 7679 | V26: =round(T26-X26-Y26-Z26-AA26-AB26,0) -> 179 | X26: =round(T26/5,-2) -> 1500 | Y26: =round(T26/5,-2) -> 1500 | Z26: =round(T26/5,-2) -> 1500 | AA26: =round(T26/5,-2) -> 1500 | AB26: =round(T26/5,-2) -> 1500
A27: 16 | B27: Privat | C27: Nunta | D27: Province @ Pischia | E27: C135 | G27: 17229 | H27: 1484 | I27: =round(3%*G27,0) -> 517 | J27: =sum(L27+N27+P27+R27) -> 6300 | K27: Sunet Full | L27: 1700 | O27: Drum | P27: 200 | Q27: DJ + Lumini | R27: 4400 | S27: 1000 | T27: =G27-H27-I27-J27-S27 -> 7928 | V27: =round(T27-X27-Y27-Z27-AA27-AB27,0) -> -72 | X27: =round(T27/5,-2) -> 1600 | Y27: =round(T27/5,-2) -> 1600 | Z27: =round(T27/5,-2) -> 1600 | AA27: =round(T27/5,-2) -> 1600 | AB27: =round(T27/5,-2) -> 1600
A28: 17 | B28: Public | C28: Concert | D28: Caransebes | F28: Zilele Cetatii | G28: 8368 | H28: 0 | I28: =round(3%*G28,0) -> 251 | J28: =sum(L28+N28+P28+R28) -> 1250 | K28: Backline | L28: 750 | M28: Tehnic | N28: 500 | S28: =round(20%*(G28-I28-J28),0) -> 1373 | T28: =G28-H28-I28-J28-S28 -> 5494 | V28: =round(T28-X28-Y28-Z28-AA28-AB28,0) -> -6 | X28: =round(T28/5,-2) -> 1100 | Y28: =round(T28/5,-2) -> 1100 | Z28: =round(T28/5,-2) -> 1100 | AA28: =round(T28/5,-2) -> 1100 | AB28: =round(T28/5,-2) -> 1100
A29: 24 | B29: Public | C29: Concert | D29: Cenei | F29: Zilele Cenei | G29: 5911 | H29: 0
A30: Octombrie
A31: 22 | B31: Privat | C31: Nunta | D31: Restaurant Venue @ Timisoara | E31: C109 | G31: 13050 | H31: 1450 | I31: =round(3%*G31,0) -> 392 | J31: =sum(L31+N31+P31+R31) -> 950 | K31: Backline | L31: 950 | S31: =round(20%*(G31-I31-J31),0) -> 2342 | T31: =G31-H31-I31-J31-S31 -> 7916 | V31: =round(T31-X31-Y31-Z31-AA31-AB31,0) -> -84 | X31: =round(T31/5,-2) -> 1600 | Y31: =round(T31/5,-2) -> 1600 | Z31: =round(T31/5,-2) -> 1600 | AA31: =round(T31/5,-2) -> 1600 | AB31: =round(T31/5,-2) -> 1600
A32: 23 | B32: Privat | C32: Nunta | D32: Flonta Lake Side @ Giroc | G32: 14268 | H32: 1476 | I32: =round(3%*G32,0) -> 428 | J32: =sum(L32+N32+P32+R32) -> 1750 | K32: Sunet Full | L32: 1750 | S32: =round(20%*(G32-I32-J32),0) -> 2418 | T32: =G32-H32-I32-J32-S32 -> 8196 | V32: =round(T32-X32-Y32-Z32-AA32-AB32,0) -> 196 | X32: =round(T32/5,-2) -> 1600 | Y32: =round(T32/5,-2) -> 1600 | Z32: =round(T32/5,-2) -> 1600 | AA32: =round(T32/5,-2) -> 1600 | AB32: =round(T32/5,-2) -> 1600
A33: Noiembrie
A34: 4 | B34: Privat | C34: Party Privat | D34: Centrul de afaceri @ Timisoara | F34: Topul Firmelor
A35: Decembrie

Sheet Evenimente 2021
A1: Data | B1: Tip Event | C1: Specific | D1: Locatie | E1: Nr. Ctr. | F1: Descriere Event | G1: Onorariu | I1: 0.03 | J1: Cheltuieli | S1: MP/Fond | T1: Phaser
G2: Total | H2: Avans | J2: TCH | K2: Sunet | L2: Pret | M2: Tehnici | N2: Pret | O2: Drum | P2: Pret | Q2: Exra | R2: Pret | S2: 0.2 | T2: De primit | U2: In firma | V2: Cari | W2: Radu | X2: Luci | Y2: Sebi | Z2: Arni
A3: Ianuarie
A4: Februarie
A5: Martie
A6: Aprilie
A7: Mai
A8: Iunie
A9: 13 | B9: Privat | C9: Nunta | D9: Congress Hall @ Timisoara | E9: C88 | G9: 13717 | H9: 1419 | I9: =round(3%*H9,0) -> 43 | J9: =sum(L9+N9+P9+R9) -> 2250 | K9: Sunet Full | L9: 1650 | M9: Marius/Marcel | N9: 600 | S9: 0 | T9: =G9-H9-I9-J9-S9 -> 10005 | U9: =round(T9-V9-W9-X9-Y9-Z9,0) -> -495 | V9: 2100 | W9: 2100 | X9: 2100 | Y9: 2100 | Z9: 2100
A10: 19 | B10: Privat | C10: Nunta | D10: Complex Restaurant Flonta @ Giroc | E10: C87 | G10: 12534 | H10: 1420 | I10: =round(3%*H10,0) -> 43 | J10: =sum(L10+N10+P10+R10) -> 2250 | K10: Sunet Full | L10: 1650 | M10: Marius/Marcel | N10: 600 | S10: 0 | T10: =G10-H10-I10-J10-S10 -> 8821 | U10: =round(T10-V10-W10-X10-Y10-Z10,0) -> -179 | V10: =round(T10/5,-2) -> 1800 | W10: =round(T10/5,-2) -> 1800 | X10: =round(T10/5,-2) -> 1800 | Y10: =round(T10/5,-2) -> 1800 | Z10: =round(T10/5,-2) -> 1800
A11: 26 | B11: Privat | C11: Nunta | D11: Terasa Casina @ Deva | E11: C105 | G11: 13192 | H11: 1192 | I11: =round(3%*H11,0) -> 36 | J11: =sum(L11+N11+P11+R11) -> 1900 | K11: Sunet Full | L11: 1650 | O11: Buz+Mica | P11: 250 | S11: 0 | T11: =G11-H11-I11-J11-S11 -> 10064 | U11: =round(T11-V11-W11-X11-Y11-Z11,0) -> 64 | V11: =round(T11/5,-2) -> 2000 | W11: =round(T11/5,-2) -> 2000 | X11: =round(T11/5,-2) -> 2000 | Y11: =round(T11/5,-2) -> 2000 | Z11: =round(T11/5,-2) -> 2000
A12: Iulie
A13: 3 | B13: Privat | C13: Nunta | D13: Villa Trevi @ Bazosul Nou | E13: C107 | G13: 14036 | H13: 1452 | I13: =round(3%*G13,0) -> 421 | J13: =sum(L13+N13+P13+R13) -> 2250 | K13: Sunet Full | L13: 1650 | M13: Marius/Marcel | N13: 600 | S13: =round(20%*(G13-I13-J13),0) -> 2273 | T13: =G13-H13-I13-J13-S13 -> 7640 | U13: =round(T13-V13-W13-X13-Y13-Z13,0) -> 140 | V13: =round(T13/5,-2) -> 1500 | W13: =round(T13/5,-2) -> 1500 | X13: =round(T13/5,-2) -> 1500 | Y13: =round(T13/5,-2) -> 1500 | Z13: =round(T13/5,-2) -> 1500
A14: 4 | B14: Privat | C14: Nunta | D14: Club Forest @ Bucuresti | E14: C116 | G14: 16128 | H14: 1461 | I14: =round(3%*G14,0) -> 484 | J14: =sum(L14+N14+P14+R14) -> 4050 | K14: Backline | L14: 950 | M14: Marcel | N14: 800 | O14: Drum | P14: 600 | Q14: DJ | R14: 1700 | S14: =round(20%*(G14-I14-J14),0) -> 2319 | T14: =G14-H14-I14-J14-S14 -> 7814 | U14: =round(T14-V14-W14-X14-Y14-Z14,0) -> -186 | V14: =round(T14/5,-2) -> 1600 | W14: =round(T14/5,-2) -> 1600 | X14: =round(T14/5,-2) -> 1600 | Y14: =round(T14/5,-2) -> 1600 | Z14: =round(T14/5,-2) -> 1600
A15: 17 | B15: Privat | C15: Nunta | D15: Hotel Tresor @ Timisoara | F15: Nasii lui Arni | G15: 12500 | H15: 0 | J15: =sum(L15+N15+P15+R15) -> 1550 | K15: Backline | L15: 950 | M15: Marius/Marcel | N15: 600 | S15: 0 | T15: =G15-H15-I15-J15-S15 -> 10950 | U15: =round(T15-V15-W15-X15-Y15-Z15,0) -> -50 | V15: =round(T15/5,-2) -> 2200 | W15: =round(T15/5,-2) -> 2200 | X15: =round(T15/5,-2) -> 2200 | Y15: =round(T15/5,-2) -> 2200 | Z15: =round(T15/5,-2) -> 2200
A16: 22 | B16: Public | C16: Concert | D16: Iulius Town @ Timisoara | F16: Every Thursday Live | G16: 4500 | H16: 0 | I16: =round(3%*G16,0) -> 135 | J16: =sum(L16+N16+P16+R16) -> 1600 | K16: Backline | L16: 500 | M16: Marius/Marcel | N16: 600 | Q16: Reset | R16: 500 | S16: =round(20%*(G16-I16-J16),0) -> 553 | T16: =G16-H16-I16-J16-S16 -> 2212 | U16: =round(T16-V16-W16-X16-Y16-Z16,0) -> 212 | V16: =round(T16/5,-2) -> 400 | W16: =round(T16/5,-2) -> 400 | X16: =round(T16/5,-2) -> 400 | Y16: =round(T16/5,-2) -> 400 | Z16: =round(T16/5,-2) -> 400
A17: 27 | B17: Public | C17: Concert | D17: Piata Unirii @ Timisoara | F17: Zilele CJT | G17: 4500 | H17: 0 | I17: =round(3%*G17,0) -> 135 | J17: =sum(L17+N17+P17+R17) -> 1100 | K17: Backline | L17: 500 | M17: Marius/Seba | N17: 600 | Q17: Reset | R17: 0 | S17: =round(20%*(G17-I17-J17),0) -> 653 | T17: =G17-H17-I17-J17-S17 -> 2612 | U17: =round(T17-V17-W17-X17-Y17-Z17,0) -> 112 | V17: =round(T17/5,-2) -> 500 | W17: =round(T17/5,-2) -> 500 | X17: =round(T17/5,-2) -> 500 | Y17: =round(T17/5,-2) -> 500 | Z17: =round(T17/5,-2) -> 500
A18: 31 | B18: Privat | C18: Nunta | D18: Hotel Tresor (Symphonie) | E18: C100 | F18: Prietenul lui Sebi | G18: 12500 | H18: 0 | I18: =round(3%*G18,0) -> 375 | J18: =sum(L18+N18+P18+R18) -> 1600 | K18: Backline | L18: 1000 | M18: Marius/Marcel | N18: 600 | S18: 0 | T18: =G18-H18-I18-J18-S18 -> 10525 | U18: =round(T18-V18-W18-X18-Y18-Z18,0) -> 525 | V18: 2000 | W18: 2000 | X18: 2000 | Y18: 2000 | Z18: 2000
A19: August
A20: 13 | B20: Public | C20: Concert | D20: Ponton Casa Baraj @ Valiug | E20: Fact. | G20: 3800 | H20: 0 | I20: =round(3%*G20,0) -> 114 | J20: =sum(L20+N20+P20+R20) -> 2700 | K20: Sunet Full | L20: 900 | M20: Marius/Adi | N20: 900 | P20: 400 | Q20: Lumini | R20: 500 | S20: =round(20%*(G20-I20-J20),0) -> 197 | T20: =G20-H20-I20-J20-S20 -> 789 | U20: =round(T20-V20-W20-X20-Y20-Z20,0) -> -211 | V20: =round(T20/5,-2) -> 200 | W20: =round(T20/5,-2) -> 200 | X20: =round(T20/5,-2) -> 200 | Y20: =round(T20/5,-2) -> 200 | Z20: =round(T20/5,-2) -> 200
A21: 14 | B21: Privat | C21: Nunta | D21: Villa Trevi @ Bazosul Nou | E21: C97 | G21: 9000 | H21: 1420 | I21: =round(3%*G21,0) -> 270 | J21: =sum(L21+N21+P21+R21) -> 2450 | K21: Sunet Full | L21: 1650 | M21: Marius/Adi | N21: 600 | O21: Buz + Mica | P21: 200 | S21: =round(20%*(G21-I21-J21),0) -> 1256 | T21: =G21-H21-I21-J21-S21 -> 3604 | U21: =round(T21-V21-W21-X21-Y21-Z21,0) -> 104 | V21: =round(T21/5,-2) -> 700 | W21: =round(T21/5,-2) -> 700 | X21: =round(T21/5,-2) -> 700 | Y21: =round(T21/5,-2) -> 700 | Z21: =round(T21/5,-2) -> 700
A22: 21 | B22: Privat | C22: Nunta | D22: Annes Events Ballroom @ Mosnita Noua | E22: C84 | G22: 13800 | H22: 1427 | I22: =round(3%*H22,0) -> 43 | J22: =sum(L22+N22+P22+R22) -> 2350 | K22: Sunet Full | L22: 1650 | M22: Marius/Adi | N22: 600 | O22: Buz | P22: 100 | S22: 0 | T22: =G22-H22-I22-J22-S22 -> 9980 | U22: =round(T22-V22-W22-X22-Y22-Z22,0) -> -20 | V22: =round(T22/5,-2) -> 2000 | W22: =round(T22/5,-2) -> 2000 | X22: =round(T22/5,-2) -> 2000 | Y22: =round(T22/5,-2) -> 2000 | Z22: =round(T22/5,-2) -> 2000
A23: 28 | B23: Privat | C23: Nunta | D23: Venue Events @ Timisoara | E23: C123 | G23: 10838 | H23: 1477 | I23: =round(3%*H23,0) -> 44 | J23: =sum(L23+N23+P23+R23) -> 1550 | K23: Backline | L23: 950 | M23: Marius/Adi | N23: 600 | S23: 0 | T23: =G23-H23-I23-J23-S23 -> 7767 | U23: =round(T23-V23-W23-X23-Y23-Z23,0) -> 387 | V23: 1476 | W23: 1476 | X23: 1476 | Y23: 1476 | Z23: 1476
A24: Septembrie
A25: 10 | B25: Privat | C25: Nunta | D25: Villa Trevi @ Bazosul Nou | E25: C120 | G25: 18710 | H25: 1477 | I25: =round(3%*H25,0) -> 44 | J25: =sum(L25+N25+P25+R25) -> 7350 | K25: Sunet Full | L25: 1650 | M25: Marius/Seba | N25: 600 | O25: Buz | P25: 100 | Q25: DJ/Lumini | R25: 5000 | S25: 0 | T25: =G25-H25-I25-J25-S25 -> 9839 | U25: =round(T25-V25-W25-X25-Y25-Z25,0) -> -161 | V25: =round(T25/5,-2) -> 2000 | W25: =round(T25/5,-2) -> 2000 | X25: =round(T25/5,-2) -> 2000 | Y25: =round(T25/5,-2) -> 2000 | Z25: =round(T25/5,-2) -> 2000
A26: 11 | B26: Privat | C26: Nunta | D26: Congress Hall @ Timisoara | E26: C121 | G26: 14285 | H26: 1477 | I26: =round(3%*G26,0) -> 429 | J26: =sum(L26+N26+P26+R26) -> 2250 | K26: Sunet Full | L26: 1650 | M26: Marius/Seba | N26: 600 | S26: =round(20%*(G26-I26-J26),0) -> 2321 | T26: =G26-H26-I26-J26-S26 -> 7808 | U26: =round(T26-V26-W26-X26-Y26-Z26,0) -> -192 | V26: =round(T26/5,-2) -> 1600 | W26: =round(T26/5,-2) -> 1600 | X26: =round(T26/5,-2) -> 1600 | Y26: =round(T26/5,-2) -> 1600 | Z26: =round(T26/5,-2) -> 1600
A27: 17 | B27: Privat | C27: Nunta | D27: No Name @ Timisoara | E27: C126 | G27: 12864 | H27: 0 | I27: =round(3%*H27,0) -> 0 | J27: =sum(L27+N27+P27+R27) -> 2250 | K27: Sunet Full | L27: 1650 | M27: Marius/Seba | N27: 600 | S27: 0 | T27: =G27-H27-I27-J27-S27 -> 10614 | U27: =round(T27-V27-W27-X27-Y27-Z27,0) -> 114 | V27: =round(T27/5,-2) -> 2100 | W27: =round(T27/5,-2) -> 2100 | X27: =round(T27/5,-2) -> 2100 | Y27: =round(T27/5,-2) -> 2100 | Z27: =round(T27/5,-2) -> 2100
A28: 18 | B28: Privat | C28: Nunta | D28: Complex Restaurant Flonta @ Giroc | E28: C95 | G28: 13717 | H28: 1419 | I28: =round(3%*H28,0) -> 43 | J28: =sum(L28+N28+P28+R28) -> 2350 | K28: Sunet Full | L28: 1650 | M28: Marius/Seba | N28: 600 | O28: Buz | P28: 100 | S28: 0 | T28: =G28-H28-I28-J28-S28 -> 9905 | U28: =round(T28-V28-W28-X28-Y28-Z28,0) -> -95 | V28: =round(T28/5,-2) -> 2000 | W28: =round(T28/5,-2) -> 2000 | X28: =round(T28/5,-2) -> 2000 | Y28: =round(T28/5,-2) -> 2000 | Z28: =round(T28/5,-2) -> 2000
A29: 25 | B29: Privat | C29: Nunta | D29: Wonderland Cluj Resort @ Cluj | E29: C115 | G29: 13600 | H29: 1457 | I29: =round(3%*H29,0) -> 44 | J29: =sum(L29+N29+P29+R29) -> 1900 | K29: Backline | L29: 900 | O29: Buz + Mica | P29: 1000 | S29: 0 | T29: =G29-H29-I29-J29-S29 -> 10199 | U29: =round(T29-V29-W29-X29-Y29-Z29,0) -> 199 | V29: =round(T29/5,-2) -> 2000 | W29: =round(T29/5,-2) -> 2000 | X29: =round(T29/5,-2) -> 2000 | Y29: =round(T29/5,-2) -> 2000 | Z29: =round(T29/5,-2) -> 2000
A30: Octombrie
A31: 9 | B31: Privat | C31: Nunta | D31: Restaurant Venue @ Timisoara | E31: C91 | G31: 12800 | H31: 1416 | I31: =round(3%*H31,0) -> 42 | J31: =sum(L31+N31+P31+R31) -> 950 | K31: Backline | L31: 950 | S31: 0 | T31: =G31-H31-I31-J31-S31 -> 10392 | U31: =round(T31-V31-W31-X31-Y31-Z31,0) -> -108 | V31: =round(T31/5,-2) -> 2100 | W31: =round(T31/5,-2) -> 2100 | X31: =round(T31/5,-2) -> 2100 | Y31: =round(T31/5,-2) -> 2100 | Z31: =round(T31/5,-2) -> 2100
A32: 16 | B32: Privat | C32: Nunta | D32: Restaurant D.O.R. @ Tahonu de sus | E32: C112 | G32: 13862 | H32: 1450 | I32: =round(3%*G32,0) -> 416 | J32: =sum(L32+N32+P32+R32) -> 2050 | K32: Backline | L32: 950 | O32: Buz + Mica | P32: 1100 | S32: =round(20%*(G32-I32-J32),0) -> 2279 | T32: =G32-H32-I32-J32-S32 -> 7667 | U32: =round(T32-V32-W32-X32-Y32-Z32,0) -> 167 | V32: =round(T32/5,-2) -> 1500 | W32: =round(T32/5,-2) -> 1500 | X32: =round(T32/5,-2) -> 1500 | Y32: =round(T32/5,-2) -> 1500 | Z32: =round(T32/5,-2) -> 1500
A33: 23 | B33: Privat | C33: Nunta | D33: Restaurant Venue @ Timisoara | F33: Hora | G33: 7425 | H33: 0 | I33: =round(3%*H33,0) -> 0 | J33: =sum(L33+N33+P33+R33) -> 950 | K33: Backline | L33: 950 | S33: 0 | T33: =G33-H33-I33-J33-S33 -> 6475 | U33: =round(T33-V33-W33-X33-Y33-Z33,0) -> -25 | V33: =round(T33/5,-2) -> 1300 | W33: =round(T33/5,-2) -> 1300 | X33: =round(T33/5,-2) -> 1300 | Y33: =round(T33/5,-2) -> 1300 | Z33: =round(T33/5,-2) -> 1300
A34: Noiembrie
A35: Decembrie
A36: 18 | B36: Public | C36: Concert | D36: Piata Libertatii @ Timisoara | G36: 5000 | H36: 0 | I36: =round(3%*G36,0) -> 150 | J36: =sum(L36+N36+P36+R36) -> 900 | K36: Backline | L36: 900 | S36: =round(20%*(G36-I36-J36),0) -> 790 | T36: =G36-H36-I36-J36-S36 -> 3160 | U36: =round(T36-V36-W36-X36-Y36-Z36,0) -> 160 | V36: =round(T36/5,-2) -> 600 | W36: =round(T36/5,-2) -> 600 | X36: =round(T36/5,-2) -> 600 | Y36: =round(T36/5,-2) -> 600 | Z36: =round(T36/5,-2) -> 600
A37: Evenimente Anulate
A38: 30 MAI ANULAT | D38: Biavati Events @ Arad | E38: C75 | G38: 1398 | H38: 1398 | I38: =round(3%*G38,0) -> 42 | J38: =sum(L38+N38+P38+R38) -> 0 | S38: 0 | T38: =G38-H38-I38-J38-S38 -> -42 | U38: =round(T38-V38-W38-X38-Y38-Z38,0) -> -42 | V38: =round(T38/5,-2) -> 0 | W38: =round(T38/5,-2) -> 0 | X38: =round(T38/5,-2) -> 0 | Y38: =round(T38/5,-2) -> 0 | Z38: =round(T38/5,-2) -> 0
A39: Evenimente Amanate
A40: 21 AUG AMANAT | D40: Heaven Cort @ Timisoara | E40: C101 | G40: 6900 | H40: 1428 | I40: =round(3%*G40,0) -> 207 | J40: =sum(L40+N40+P40+R40) -> 900 | K40: Backline | L40: 900 | S40: =round(20%*(G40-I40-J40),0) -> 1159 | T40: =G40-H40-I40-J40-S40 -> 3206 | U40: =round(T40-V40-W40-X40-Y40-Z40,0) -> 206 | V40: =round(T40/5,-2) -> 600 | W40: =round(T40/5,-2) -> 600 | X40: =round(T40/5,-2) -> 600 | Y40: =round(T40/5,-2) -> 600 | Z40: =round(T40/5,-2) -> 600
A41: 4 SEP AMANAT | D41: Hotel Arta @ Timisoara | E41: C99 | G41: 14725 | H41: 1425 | I41: =round(3%*G41,0) -> 442 | J41: =sum(L41+N41+P41+R41) -> 1650 | K41: Sunet Full | L41: 1650 | S41: =round(20%*(G41-I41-J41),0) -> 2527 | T41: =G41-H41-I41-J41-S41 -> 8681 | U41: =round(T41-V41-W41-X41-Y41-Z41,0) -> 181 | V41: =round(T41/5,-2) -> 1700 | W41: =round(T41/5,-2) -> 1700 | X41: =round(T41/5,-2) -> 1700 | Y41: =round(T41/5,-2) -> 1700 | Z41: =round(T41/5,-2) -> 1700
A42: 2 OCT AMANAT | D42: Villa Trevi @ Bazosul Nou | E42: C91 | G42: 12771 | H42: 1419 | I42: =round(3%*G42,0) -> 383 | J42: =sum(L42+N42+P42+R42) -> 900 | K42: Backline | L42: 900 | S42: =round(20%*(G42-I42-J42),0) -> 2298 | T42: =G42-H42-I42-J42-S42 -> 7771 | U42: =round(T42-V42-W42-X42-Y42-Z42,0) -> -229 | V42: =round(T42/5,-2) -> 1600 | W42: =round(T42/5,-2) -> 1600 | X42: =round(T42/5,-2) -> 1600 | Y42: =round(T42/5,-2) -> 1600 | Z42: =round(T42/5,-2) -> 1600
D45: Statistici | K45: Legenda
D46: Descriere | E46: Nr. | F46: Descriere | G46: Ron | H46: Euro
D47: Numar Evenimente Publice Total | E47: =countif(B:B,"Public") -> 4 | F47: Total Venituri | G47: =sum(G1:G36) -> 253308 | H47: =round(G47/4.7,0) -> 53895 | L47: Achitat
D48: Numar Evenimente Private Total | E48: =countif(B:B,"Privat") -> 18 | F48: Bani Phaser | G48: =sum(T:T) -> 188458 | H48: =round(G48/4.7,0) -> 40097 | L48: Neachitat
D49: Numar Evenimente Private (Corporate) | E49: =COUNTIF(C:C,"Corporate") -> 0 | F49: Bani de persoana | G49: =sum(V1:V37) -> 33676 | H49: =round(G49/4.7,0) -> 7165
D50: Numar Evenimente Private (Nunta, Botez, Aniversare) | E50: =countif(C:C,"Nunta") + COUNTIF(C:C,"Botez") + countif(C:C,"Aniversare") -> 18 | F50: Bani ramasi in Firma/Fond | G50: =sum(U:U) -> 578 | H50: =round(G50/4.7,0) -> 123
D51: Numar Evenimente Private (Absolvire) | E51: =countif(C:C,"Absolvire") -> 0 | F51: Bani MP/Fond | G51: =round(sum(S:S),0) -> 18625 | H51: =round(G51/4.7,0) -> 3963
D52: Numar Evenimente Total | E52: =E47+E48 -> 22 | F52: Bani pe Impozit 3% | G52: =round(3%*G47,0) -> 7599 | H52: =round(G52/4.7,0) -> 1617
F53: Bani Cheltuiti Total | G53: =sum(J:J) -> 52000 | H53: =round(G53/4.7,0) -> 11064
F54: Bani Cheltuiti Sunet | G54: =sum(L:L) -> 30350 | H54: =round(G54/4.7,0) -> 6457
F55: Bani Cheltuiti Tehnic | G55: =sum(N:N) -> 10100 | H55: =round(G55/4.7,0) -> 2149
F56: Bani Cheltuiti Drum | G56: =sum(P:P) -> 3850 | H56: =round(G56/4.7,0) -> 819
F57: Bani Cheltuiti Extra | G57: =sum(R:R) -> 7700 | H57: =round(G57/4.7,0) -> 1638
D58: Extra Statistici
F59: Bani Phaser pe Evenimente
F60: Descriere | G60: Ron | H60: Euro
F61: Bani din Event. Publice Total | G61: =G48-G62 -> 28389 | H61: =round(G61/4.7,0) -> 6040
F62: Bani din Event. Private Total | G62: =G63+G64 -> 160069 | H62: =round(G62/4.7,0) -> 34057
F63: Bani din Corporate | G63: =SUMIF(C:C,"Corporate",G:G) -> 0 | H63: =round(G63/4.7,0) -> 0
F64: Bani din (Nunta/Botez/Aniversare) | G64: =SUMIF(C:C,"Nunta",T:T)+SUMIF(C:C,"Botez",T:T)+SUMIF(C:C,"Aniversare",T:T) -> 160069 | H64: =round(G64/4.7,0) -> 34057
F65: Bani de Pers. pe Evenimente
F66: Bani din Event. Publice Total | G66: =round(G61/5,0) -> 5678 | H66: =round(G66/4.7,0) -> 1208
F67: Bani din Event. Private Total | G67: =SUMIF(B:B,"Privat",Z:Z) -> 31976 | H67: =round(G67/4.7,0) -> 6803
F68: Bani din Corporate | G68: =sumif(B:B,"Corporate",Z:Z) -> 0 | H68: =round(G68/4.7,0) -> 0
F69: Bani din (Nunta/Botez/Aniversare) | G69: =SUMIF(C:C,"Nunta",Z:Z)+SUMIF(C:C,"Botez",Z:Z)+SUMIF(C:C,"Aniversare",Z:Z) -> 31976 | H69: =round(G69/4.7,0) -> 6803

Sheet Fond Extra 2021
A1: Incasari | D1: Cheltuieli
A3: Ron | B3: Data | C3: Descriere | D3: Ron | E3: Data | F3: Descriere
A4: 10980 | B4: 01.01.2021 | C4: Bani ramasi de pe 2020 | D4: 2700 | F4: Licenta Ableton | H4: T C Ron | I4: =sum(D:D) -> 174384
A5: 6850 | C5: Deschis "Fond plic" | D5: 70 | F5: Lumanari "Copilul lunii" Video | H5: T V Ron | I5: =sum(A:A) -> 176235
A6: 1500 | C6: Parte din PFA de la Concert Timisoara | D6: 33 | F6: Brichete + Sfoara "Copilul lunii" Video
A7: 2000 | C7: Parte din PFA de la Concert Timisoara | D7: 134 | F7: Banda+ Baterii+ Sanie + Lampa + Lumanari "Copilul lunii" Video | H7: Balanta Ron | I7: =I5-I4 -> 1851
A8: 1500 | C8: Pus avans inapoi 30.05.2021 (Radu) | D8: 750 | F8: Felinare "Copilul lunii" Video
A9: 1000 | C9: Parte din PFA de la Concert Timisoara | D9: 300 | F9: Rame Goale "Copilul lunii" Video
A10: 12300 | C10: Rest Nunta 13.06.2021 | D10: 7500 | F10: Renovare sala Depunere cont ING
A11: 11110 | C11: Rest Nunta 19.06.2021 | D11: 1700 | F11: Depunere cont ING
A12: 12000 | C12: Rest Nunta 26.06.2021 | D12: 700 | F12: Catering "Arni" - Copilul luniii
A13: 12500 | C13: Nunta 17.07.2021 | D13: 100 | F13: Benzina "Luci" - Copilul lunii
A14: 1500 | C14: a ramas in fond din retragere 25.06.2021 | D14: 50 | F14: Catering "Luci" - Copilul lunii
A15: 100 | C15: a ramas in fond din retragere 05.07.2021 | D15: 100 | F15: Benzina "Sebi" - Copilul lunii
A16: 12500 | C16: Nunta 31.07.2021 | D16: 150 | F16: Benda dublu adeziva "Renovare sala"
A17: 1100 | C17: a ramas in fond din retragere 18.08.2021 | D17: 250 | F17: Aspirator sala
A18: 12373 | C18: Nunta 21.08.2021 | D18: 150 | F18: Dibluri/Piulite
A19: 9384 | C19: Nunta 28.08.2021 | D19: 1500 | F19: Canapea, Covor, Lampadar, Cuier, Cos de gunoi
... A25: 12800 | C25: Nunta 09.10.2021 | D25: 1500 | F25: Depunere cont ING
D26: 450 | F26: Combustibil "Flavius" - Copilul lunii
D27: 1500 | F27: Cheltuieli "Carina" - Copilul lunii
D28: 980 | F28: Depunere cont ING
D29: 1000 | F29: Photo Session Ervin
D30: 450 | F30: ***Radu Licence
D31: 50 | F31: Dubluri Cheie
D32: 1650 | F32: Sunet Nunta 13.06.2021
D33: 600 | F33: Tehnici Nunta 13.06.2021
D34: 10500 | F34: Radu - 2100, Sebi - 2100, Luci - 2100, Arni - 2100, Carina - 2100 = Nunta 13.06.2021
D35: 1650 | F35: Sunet Nunta 19.06.2021
D36: 600 | F36: Tehnici Nunta 19.06.2021
D37: 9000 | F37: Radu - 1800, Sebi - 1800, Luci - 1800, Arni - 1800, Carina - 1800 = Nunta 19.06.2021
... D70: 1900 | F70: Sunet Prezent Restanta

Sheet Evenimente 2020
A1: Data | B1: Tip Event | C1: Specific | D1: Locatie | E1: Nr. Ctr. | F1: Descriere Event | G1: Onorariu | I1: 0.03 | J1: Cheltuieli | S1: MP/Fond | T1: Phaser
G2: Total | H2: Avans | J2: TCH | K2: Sunet | L2: Pret | M2: Tehnici | N2: Pret | O2: Drum | P2: Pret | Q2: Exra | R2: Pret | S2: 0.2 | T2: De primit | U2: In firma | V2: Cari | W2: Radu | X2: Luci | Y2: Sebi | Z2: Arni
A3: Ianuarie
A4: Februarie
A5: 8 | B5: Public | C5: Concert | D5: Partia Bradul @ Poiana Brasov | F5: "Live pe Partie" - Europa FM | G5: 0 | H5: 0 | I5: =round(3%*G5,0) -> 0 | J5: =sum(L5+N5+P5+R5) -> 0 | S5: =round(20%*(G5-I5-J5),0) -> 0 | T5: =G5-H5-I5-J5-S5 -> 0 | U5: =round(T5-V5-W5-X5-Y5-Z5,0) -> 0 | V5: =round(T5/5,0) -> 0 | W5: =round(T5/5,0) -> 0 | X5: =round(T5/5,0) -> 0 | Y5: =round(T5/5,0) -> 0 | Z5: =round(T5/5,0) -> 0
A6: 29 | B6: Public | C6: Concert | D6: Live in Tramvai @ Timisoara | F6: Phaser Live in Tramvai | G6: 0 | H6: 0 | I6: =round(3%*G6,0) -> 0 | J6: =sum(L6+N6+P6+R6) -> 0 | S6: =round(20%*(G6-I6-J6),0) -> 0 | T6: =G6-H6-I6-J6-S6 -> 0 | U6: =round(T6-V6-W6-X6-Y6-Z6,0) -> 0 | V6: =round(T6/5,0) -> 0 | W6: =round(T6/5,0) -> 0 | X6: =round(T6/5,0) -> 0 | Y6: =round(T6/5,0) -> 0 | Z6: =round(T6/5,0) -> 0
A7: Martie
A8: 7 | B8: Public | C8: Concert | D8: Club Soho @ Resita | G8: 3000 | H8: 0 | J8: =sum(L8+N8+P8+R8) -> 720 | K8: Sunet Full | L8: 500 | O8: Buz + Mica | P8: 220 | S8: 0 | T8: =G8-H8-I8-J8-S8 -> 2280 | U8: =round(T8-V8-W8-X8-Y8-Z8,0) -> -220 | V8: 500 | W8: 500 | X8: 500 | Y8: 500 | Z8: =round(T8/5,-2) -> 500
A9: Aprilie
A10: Mai
A11: Iunie
A12: Iulie
A13: 18 | B13: Public | C13: Concert | D13: Piata Libertatii @ Timisoara | F13: UVT Admitere | G13: 4500 | H13: 0 | I13: =round(3%*G13,0) -> 135 | J13: =sum(L13+N13+P13+R13) -> 700 | K13: Backline | L13: 700 | S13: 0 | T13: =G13-H13-I13-J13-S13 -> 3665 | U13: =round(T13-V13-W13-X13-Y13-Z13,0) -> -335 | V13: 800 | W13: 800 | X13: 800 | Y13: 800 | Z13: 800
A14: August
A15: 21 | B15: Public | C15: Concert | D15: Club Sportiv Torontalului | F15: Embargo Hub | G15: 1500 | H15: 0 | I15: =round(3%*G15,0) -> 45 | J15: =sum(L15+N15+P15+R15) -> 500 | K15: Backline | L15: 500 | S15: 0 | T15: =G15-H15-I15-J15-S15 -> 955 | U15: =round(T15-V15-W15-X15-Y15-Z15,0) -> 955 | V15: 0 | W15: 0 | X15: 0 | Y15: 0 | Z15: 0
A16: Septembrie
A17: 4 | B17: Public | C17: Concert | D17: Aerodrom @ Timisoara | F17: Flight Festival | G17: 4000 | H17: 0 | I17: =round(3%*G17,0) -> 120 | J17: =sum(L17+N17+P17+R17) -> 1000 | K17: Backline | L17: 700 | M17: Bebi | N17: 300 | S17: =round(20%*(G17-I17-J17),0) -> 576 | T17: =G17-H17-I17-J17-S17 -> 2304 | U17: =round(T17-V17-W17-X17-Y17-Z17,0) -> -196 | V17: =round(T17/5,-2) -> 500 | W17: =round(T17/5,-2) -> 500 | X17: =round(T17/5,-2) -> 500 | Y17: =round(T17/5,-2) -> 500 | Z17: =round(T17/5,-2) -> 500
A18: 4 | B18: Privat | C18: Nunta | D18: Galla Events @ Timisoara | E18: C102 | G18: 11680 | H18: 1430 | I18: =round(3%*G18,0) -> 350 | J18: =sum(L18+N18+P18+R18) -> 950 | K18: Backline | L18: 950 | S18: =round(20%*(G18-I18-J18),0) -> 2076 | T18: =G18-H18-I18-J18-S18 -> 6874 | U18: =round(T18-V18-W18-X18-Y18-Z18,0) -> -1 | V18: =round(T18/5,0) -> 1375 | W18: =round(T18/5,0) -> 1375 | X18: =round(T18/5,0) -> 1375 | Y18: =round(T18/5,0) -> 1375 | Z18: =round(T18/5,0) -> 1375
A19: 12 | B19: Privat | C19: Nutna | D19: Restaurant Flonta @ Timisoara | G19: 12100 | H19: 0 | J19: =sum(L19+N19+P19+R19) -> 3102 | K19: Sunet Full | L19: 1650 | Q19: DJ+Lumini | R19: 1452 | S19: 0 | T19: =G19-H19-I19-J19-S19 -> 8998 | U19: =round(T19-V19-W19-X19-Y19-Z19,0) -> -2 | V19: =round(T19/5,0) -> 1800 | W19: =round(T19/5,0) -> 1800 | X19: =round(T19/5,0) -> 1800 | Y19: =round(T19/5,0) -> 1800 | Z19: =round(T19/5,0) -> 1800
A20: 19 | B20: Privat | C20: Nunta | D20: Villa Trevi @ Bazosul Nou | E20: C98 | G20: 9470 | H20: 1420 | I20: =round(3%*G20,0) -> 284 | J20: =sum(L20+N20+P20+R20) -> 1400 | K20: Backline | L20: 950 | M20: Marcel | N20: 300 | O20: Buz + Mica | P20: 150 | S20: =round(20%*(G20-I20-J20),0) -> 1557 | T20: =G20-H20-I20-J20-S20 -> 4809 | U20: =round(T20-V20-W20-X20-Y20-Z20,0) -> -191 | V20: =round(T20/5,-2) -> 1000 | W20: =round(T20/5,-2) -> 1000 | X20: =round(T20/5,-2) -> 1000 | Y20: =round(T20/5,-2) -> 1000 | Z20: =round(T20/5,-2) -> 1000
A21: Octombrie
A22: Noiembrie
A23: 29 | B23: Public | C23: Concert | D23: Casa Tineretului @ Timisoara | F23: Aniversare FITT 30 de ani | G23: 4600 | H23: 0 | I23: =round(3%*G23,0) -> 138 | J23: =sum(L23+N23+P23+R23) -> 800 | K23: Backline | L23: 0 | M23: Marcel | N23: 300 | Q23: Lumini | R23: 500 | S23: 0 | T23: =G23-H23-I23-J23-S23 -> 3662 | U23: =round(T23-V23-W23-X23-Y23-Z23,0) -> 162 | V23: =round(T23/5,-2) -> 700 | W23: =round(T23/5,-2) -> 700 | X23: =round(T23/5,-2) -> 700 | Y23: =round(T23/5,-2) -> 700 | Z23: =round(T23/5,-2) -> 700
A24: Decembrie
D30: Statistici | K30: Legenda
D31: Descriere | E31: Nr. | F31: Descriere | G31: Ron | H31: Euro
D32: Numar Evenimente Publice Total | E32: =countif(B:B,"Public") -> 7 | F32: Total Venituri | G32: =sum(G1:G31) -> 50850 | H32: =round(G32/4.7,0) -> 10819 | L32: Achitat
D33: Numar Evenimente Private Total | E33: =countif(B:B,"Privat") -> 3 | F33: Bani Phaser | G33: =sum(T:T) -> 33547 | H33: =round(G33/4.7,0) -> 7138 | L33: Neachitat
D34: Numar Evenimente Private (Corporate) | E34: =COUNTIF(C:C,"Corporate") -> 0 | F34: Bani de persoana | G34: =sum(V:V) -> 6675 | H34: =round(G34/4.7,0) -> 1420
D35: Numar Evenimente Private (Nunta, Botez, Aniversare) | E35: =countif(C:C,"Nunta") + COUNTIF(C:C,"Botez") + countif(C:C,"Aniversare") -> 2 | F35: Bani ramasi in Firma/Fond | G35: =sum(U:U) -> 172 | H35: =round(G35/4.7,0) -> 37
D36: Numar Evenimente Private (Absolvire) | E36: =countif(C:C,"Absolvire") -> 0 | F36: Bani MP/Fond | G36: =round(sum(S:S),0) -> 4209 | H36: =round(G36/4.7,0) -> 896
D37: Numar Evenimente Total | E37: =E32+E33 -> 10 | F37: Bani pe Impozit 3% | G37: =round(3%*G32,0) -> 1526 | H37: =round(G37/4.7,0) -> 325
F38: Bani Cheltuiti Total | G38: =sum(J:J) -> 9172 | H38: =round(G38/4.7,0) -> 1951
F39: Bani Cheltuiti Sunet | G39: =sum(L:L) -> 5950 | H39: =round(G39/4.7,0) -> 1266
F40: Bani Cheltuiti Tehnic | G40: =sum(N:N) -> 900 | H40: =round(G40/4.7,0) -> 191
F41: Bani Cheltuiti Drum | G41: =sum(P:P) -> 370 | H41: =round(G41/4.7,0) -> 79
F42: Bani Cheltuiti Extra | G42: =sum(R:R) -> 1952 | H42: =round(G42/4.7,0) -> 415
D43: Extra Statistici
F44: Bani Phaser pe Evenimente
F45: Descriere | G45: Ron | H45: Euro
F46: Bani din Event. Publice Total | G46: =G33-G47 -> 21864 | H46: =round(G46/4.7,0) -> 4652
F47: Bani din Event. Private Total | G47: =G48+G49 -> 11683 | H47: =round(G47/4.7,0) -> 2486
F48: Bani din Corporate | G48: =SUMIF(C:C,"Corporate",G:G) -> 0 | H48: =round(G48/4.7,0) -> 0
F49: Bani din (Nunta/Botez/Aniversare) | G49: =SUMIF(C:C,"Nunta",T:T)+SUMIF(C:C,"Botez",T:T)+SUMIF(C:C,"Aniversare",T:T) -> 11683 | H49: =round(G49/4.7,0) -> 2486
F50: Bani de Pers. pe Evenimente
F51: Bani din Event. Publice Total | G51: =round(G46/5,0) -> 4373 | H51: =round(G51/4.7,0) -> 930
F52: Bani din Event. Private Total | G52: =SUMIF(B:B,"Privat",Z:Z) -> 4175 | H52: =round(G52/4.7,0) -> 888
F53: Bani din Corporate | G53: =sumif(B:B,"Corporate",Z:Z) -> 0 | H53: =round(G53/4.7,0) -> 0
F54: Bani din (Nunta/Botez/Aniversare) | G54: =SUMIF(C:C,"Nunta",Z:Z)+SUMIF(C:C,"Botez",Z:Z)+SUMIF(C:C,"Aniversare",Z:Z) -> 2375 | H54: =round(G54/4.7,0) -> 505

Sheet Fond Extra 2020
A1: Incasari | D1: Cheltuieli
A3: Ron | B3: Data | C3: Descriere | D3: Ron | E3: Data | F3: Descriere
A4: 20412 | B4: 01.01.2020 | C4: Bani ramasi de pe 2019 | D4: 220 | E4: 07.03.2020 | F4: Combustibil Soho Resita | H4: T C Ron | I4: =sum(D:D) -> 10932
A5: 50 | B5: 09.01.2020 | C5: "Scosi degeaba" | D5: 1500 | F5: 1500 - Radu = Nunti in avans: 14.08.2021; | H5: T V Ron | I5: =sum(A:A) -> 21912
A6: 1450 | C6: Avans 300 euro Bianca Azap si Dan purice | D6: 5100 | F6: 5100 - Luci = Nunti in avans: 31.10.2020; 21.05.2022; 18.09.2021;
D7: 50 | F7: Copie Chei | H7: Balanta Ron | I7: =I5-I4 -> 10980
D8: 2922 | F8: Flavius Video "Fast Forward"
D9: 1140 | F9: Cheltuieli Productie "Fast Forward" in afara de apartament

Sheet Evenimente 2019
B1: Tip Event | C1: Tip Event | D1: Locatie | E1: Nr. Contract | F1: Descriere Event | G1: Onorariu | I1: 0.03 | J1: Cheltuieli | Q1: MP/F | R1: Phaser
G2: Total | H2: Avans | J2: TCH | K2: Sunet | L2: Pret | M2: Tehnici | N2: Pret | O2: Extra | P2: Pret | Q2: 0.2 | R2: De primit | S2: In firma | T2: De Pers.
A3: Ianuarie
A4: Februarie
A5: 9 | B5: Privat | C5: Nunta | D5: Ivy Events @ Timisoara | E5: 70/01.11.2018 | G5: 11184 | H5: 0 | I5: =round(G5*3%,0) -> 336 | J5: =sum(L5+N5+P5) -> 950 | K5: PA + Backline | L5: 700 | M5: Bebi | N5: 250 | Q5: =round((G5-I5-J5)*20%,0) -> 1980 | R5: =round(sum(G5-I5-J5-Q5-H5),0) -> 7918 | S5: =5*(R5/5-T5) -> 418 | T5: 1500
A6: 14 | B6: Public | C6: Concert | D6: Heaven @ Timisoara | E6: Bilete | F6: Valentine's Day | G6: 0 | H6: 0 | I6: =round(G6*3%,0) -> 0 | J6: =sum(L6+N6+P6) -> 0 | K6: Backline | L6: 0 | Q6: =round((G6-I6-J6)*20%,0) -> 0 | R6: =round(sum(G6-I6-J6-Q6-H6),0) -> 0 | S6: =5*(R6/5-T6) -> 0 | T6: =round(R6/5,-2) -> 0
A7: Martie
A8: 1 | B8: Privat | C8: Botez | D8: Galla @ Timisoara | E8: 02/16.02.2019 | G8: 17279 | H8: 0 | I8: =round(G8*3%,0) -> 518 | J8: =sum(L8+N8+P8) -> 4670 | K8: PA + Backline | L8: 1870 | O8: Lights + DJ | P8: 2800 | Q8: =round((G8-I8-J8)*20%,0) -> 2418 | R8: =round(sum(G8-I8-J8-Q8-H8),0) -> 9673 | S8: =5*(R8/5-T8) -> 173 | T8: 1900
A9: Aprilie
A10: 4 | B10: Privat | C10: Corporate | D10: Fratelli @ Timisoara | E10: 83/01.04.2019 | F10: Wiz Mobile Party | G10: 7125 | H10: 0 | I10: =round(G10*3%,0) -> 214 | J10: =sum(L10+N10+P10) -> 1200 | K10: Backline | L10: 950 | M10: Luci | N10: 250 | Q10: =round((G10-I10-J10)*20%,0) -> 1142 | R10: =round(sum(G10-I10-J10-Q10-H10),0) -> 4569 | S10: =5*(R10/5-T10) -> -431 | T10: 1000
A11: Mai
A12: 11 | B12: Privat | C12: Nunta | D12: Valery 3 @ Mosnita Noua | E12: 65/09.09.2018 | G12: 12528 | H12: 1392 | I12: =round(H12*3%,0) -> 42 | J12: =sum(L12+N12+P12) -> 1180 | K12: Backline | L12: 930 | M12: Luci | N12: 250 | Q12: 0 | R12: =round(sum(G12-I12-J12-Q12-H12),0) -> 9914 | S12: =5*(R12/5-T12) -> 2414 | T12: 1500
A13: 18 | B13: Public | C13: Concert | D13: Dudestii Noi | E13: 83/07.05.2019 | F13: Embargo Festival | G13: 4500 | H13: 0 | I13: =round(G13*3%,0) -> 135 | J13: =sum(L13+N13+P13) -> 1000 | K13: Backline | L13: 600 | M13: Bebi | N13: 300 | O13: Drum | P13: 100 | Q13: =round((G13-I13-J13)*20%,0) -> 673 | R13: =round(sum(G13-I13-J13-Q13-H13),0) -> 2692 | S13: =5*(R13/5-T13) -> 192 | T13: 500
A14: 23 | B14: Public | C14: Concert | D14: Like Pub @ Timisoara | G14: 800 | I14: 0 | J14: =sum(L14+N14+P14) -> 1100 | K14: PA + Backline | L14: 500 | M14: Bebi/Marius | N14: 500 | O14: Podium | P14: 100 | Q14: =round((G14-I14-J14)*20%,0) -> -60 | R14: =round(sum(G14-I14-J14-Q14-H14),0) -> -240 | S14: =5*(R14/5-T14) -> -240 | T14: 0
A15: 25 | B15: Privat | C15: Nunta | D15: Galla @ Timisoara | E15: 49/04.04.2018 | G15: 13048 | H15: 1398 | I15: =round(H15*3%,0) -> 42 | J15: =sum(L15+N15+P15) -> 1230 | K15: Backline | L15: 930 | M15: Marius | N15: 300 | Q15: 0 | R15: =round(sum(G15-I15-J15-Q15-H15),0) -> 10378 | S15: =5*(R15/5-T15) -> -122 | T15: =round(R15/5,-2) -> 2100
A16: Iunie
A17: 1 | B17: Privat | C17: Nunta | D17: Hotel Tresor @ Timisoara | E17: 35/22.01.2018 | G17: 13058 | H17: 1400 | I17: =round(G17*3%,0) -> 392 | J17: =sum(L17+N17+P17) -> 930 | K17: Backline | L17: 930 | Q17: =round((G17-I17-J17)*20%,0) -> 2347 | R17: =round(sum(G17-I17-J17-Q17-H17),0) -> 7989 | S17: =5*(R17/5-T17) -> -11 | T17: =round(R17/5,-2) -> 1600
A18: 15 | B18: Privat | C18: Nunta | D18: Prestige @ Timisoara | E18: 48/01.04.2018 | G18: 13048 | H18: 1398 | I18: =round(H18*3%,0) -> 42 | J18: =sum(L18+N18+P18) -> 930 | K18: Backline | L18: 930 | Q18: 0 | R18: =round(sum(G18-I18-J18-Q18-H18),0) -> 10678 | S18: =5*(R18/5-T18) -> 178 | T18: =round(R18/5,-2) -> 2100
A19: 15 | B19: Privat | C19: Nunta | D19: Fratelli @ Timisoara | G19: 11637 | H19: 0 | I19: =round(G19*3%,0) -> 349 | J19: =sum(L19+N19+P19) -> 1600 | K19: PA + Backline | L19: 1600 | Q19: =round((G19-I19-J19)*20%,0) -> 1938 | R19: =round(sum(G19-I19-J19-Q19-H19),0) -> 7750 | S19: =5*(R19/5-T19) -> -250 | T19: =round(R19/5,-2) -> 1600
A20: 16 | B20: Privat | C20: Nunta | D20: Valery 3 @ Mosnita Noua | E20: 81/22.02.2018 | G20: 9243 | H20: 1430 | I20: =round(G20*3%,0) -> 277 | J20: =sum(L20+N20+P20) -> 930 | K20: Backline | L20: 930 | Q20: =round((G20-I20-J20)*20%,0) -> 1607 | R20: =round(sum(G20-I20-J20-Q20-H20),0) -> 4999 | S20: =5*(R20/5-T20) -> -1 | T20: =round(R20/5,-2) -> 1000
A21: 22 | B21: Privat | C21: Nunta | D21: Flonta @ Timisoara | E21: 67/09.10.2018 | G21: 13526 | H21: 1398 | I21: =round(G21*3%,0) -> 406 | J21: =sum(L21+N21+P21) -> 1600 | K21: Backline | L21: 1600 | Q21: =round((G21-I21-J21)*20%,0) -> 2304 | R21: =round(sum(G21-I21-J21-Q21-H21),0) -> 7818 | S21: =5*(R21/5-T21) -> -182 | T21: 1600
A22: 29 | B22: Privat | C22: Nunta | D22: Flonta @ Timisoara | E22: 58/19.06.2018 | G22: 12582 | H22: 1395 | I22: =round(H22*3%,0) -> 42 | J22: =sum(L22+N22+P22) -> 930 | K22: Backline | L22: 930 | Q22: 0 | R22: =round(sum(G22-I22-J22-Q22-H22),0) -> 10215 | S22: =5*(R22/5-T22) -> 215 | T22: =round(R22/5,-2) -> 2000
A23: Iulie
A24: 3 | B24: Public | C24: Concert | D24: Papa la Soni @ Vama Veche | G24: 0 | H24: 0 | I24: =round(G24*3%,0) -> 0 | J24: =sum(L24+N24+P24) -> 0 | K24: Backline | L24: 0 | Q24: =round((G24-I24-J24)*20%,0) -> 0 | R24: =round(sum(G24-I24-J24-Q24-H24),0) -> 0 | S24: =5*(R24/5-T24) -> 0 | T24: =round(R24/5,-2) -> 0
A25: 4 | B25: Public | C25: Concert | D25: White Horse @ Costinesti | G25: 0 | H25: 0 | I25: =round(G25*3%,0) -> 0 | J25: =sum(L25+N25+P25) -> 0 | K25: Backline | L25: 0 | Q25: =round((G25-I25-J25)*20%,0) -> 0 | R25: =round(sum(G25-I25-J25-Q25-H25),0) -> 0 | S25: =5*(R25/5-T25) -> 0 | T25: =round(R25/5,-2) -> 0
A26: 5 | B26: Public | C26: Concert | D26: Radio Vacanta @ Mamaia | F26: Inceputul Verii - Radio Vacanta | G26: 0 | H26: 0 | I26: =round(G26*3%,0) -> 0 | J26: =sum(L26+N26+P26) -> 0 | K26: Backline | L26: 0 | Q26: =round((G26-I26-J26)*20%,0) -> 0 | R26: =round(sum(G26-I26-J26-Q26-H26),0) -> 0 | S26: =5*(R26/5-T26) -> 0 | T26: =round(R26/5,-2) -> 0
A27: 6 | B27: Privat | C27: Nunta | D27: Tresor @ Timisoara | E27: 60/18.07.2018 | G27: 12555 | H27: 1395 | I27: =round(H27*3%,0) -> 42 | J27: =sum(L27+N27+P27) -> 1130 | K27: Backline | L27: 930 | M27: Andrei/Marius | N27: 200 | Q27: 0 | R27: =round(sum(G27-I27-J27-Q27-H27),0) -> 9988 | S27: =5*(R27/5-T27) -> -12 | T27: =round(R27/5,-2) -> 2000
A28: 13 | B28: Privat | C28: Nunta | D28: Galla @ Timisoara | E28: 79/11.01.2019 | G28: 13514 | H28: 1398 | I28: =round(G28*3%,0) -> 405 | J28: =sum(L28+N28+P28) -> 1660 | K28: PA + Backline | L28: 1660 | Q28: =round((G28-I28-J28)*20%,0) -> 2290 | R28: =round(sum(G28-I28-J28-Q28-H28),0) -> 7761 | S28: =5*(R28/5-T28) -> -239 | T28: =round(R28/5,-2) -> 1600
A29: 19 | B29: Privat | C29: Nunta | D29: Venue @ Timisoara | E29: 80/05.02.2019 | G29: 9975 | H29: 1425 | I29: =round(G29*3%,0) -> 299 | J29: =sum(L29+N29+P29) -> 900 | K29: Backline | L29: 900 | Q29: =round((G29-I29-J29)*20%,0) -> 1755 | R29: =round(sum(G29-I29-J29-Q29-H29),0) -> 5596 | S29: =5*(R29/5-T29) -> 96 | T29: =round(R29/5,-2) -> 1100
A30: 20 | B30: Privat | C30: Nunta | D30: Royal Oak Events @ Deva | E30: 82/15.03.2019 | G30: 13804 | H30: 1428 | I30: =round(G30*3%,0) -> 414 | J30: =sum(L30+N30+P30) -> 1600 | K30: PA + Backline | L30: 1600 | Q30: =round((G30-I30-J30)*20%,0) -> 2358 | R30: =round(sum(G30-I30-J30-Q30-H30),0) -> 8004 | S30: =5*(R30/5-T30) -> 4 | T30: =round(R30/5,-2) -> 1600
A31: 27 | B31: Privat | C31: Nunta | D31: Conacul Archia @ Deva | E31: 73/19.11.2018 | G31: 12582 | H31: 1400 | I31: =round(G31*3%,0) -> 377 | J31: =sum(L31+N31+P31) -> 900 | K31: Backline | L31: 900 | Q31: =round((G31-I31-J31)*20%,0) -> 2261 | R31: =round(sum(G31-I31-J31-Q31-H31),0) -> 7644 | S31: =5*(R31/5-T31) -> -356 | T31: 1600
A32: 28 | B32: Privat | C32: Botez | D32: Valery 3 @ Mosnita Noua | G32: 11515 | H32: 0 | I32: 0 | J32: =sum(L32+N32+P32) -> 900 | K32: Backline | L32: 900 | Q32: 0 | R32: =round(sum(G32-I32-J32-Q32-H32),0) -> 10615 | S32: =5*(R32/5-T32) -> 115 | T32: =round(R32/5,-2) -> 2100
A33: August
A34: 3 | B34: Public | C34: Concert | D34: Piata Victoriei @ Timisoara | F34: Concert Zilele Timisoarei | G34: 5600 | H34: 0 | J34: =sum(L34+N34+P34) -> 700 | K34: Backline | L34: 700 | Q34: 430 | R34: =round(sum(G34-I34-J34-Q34-H34),0) -> 4470 | S34: =5*(R34/5-T34) -> -80 | T34: 910
A35: 3 | B35: Privat | C35: Nunta | D35: Galla @ Timisoara | E35: 52/19.04.2018 | G35: 13717 | H35: 1395 | I35: =round(H35*3%,0) -> 42 | J35: =sum(L35+N35+P35) -> 1600 | K35: Backline | L35: 1600 | Q35: 0 | R35: =round(sum(G35-I35-J35-Q35-H35),0) -> 10680 | S35: =5*(R35/5-T35) -> 180 | T35: 2100
A36: 16 | B36: Public | C36: Concert | D36: Micalaca @ Arad | F36: Concert Zilele Aradului | G36: 3000 | H36: 0 | I36: =round(G36*3%,0) -> 90 | J36: =sum(L36+N36+P36) -> 800 | K36: Backline | L36: 600 | O36: Drum | P36: 200 | Q36: =round((G36-I36-J36)*20%,0) -> 422 | R36: =round(sum(G36-I36-J36-Q36-H36),0) -> 1688 | S36: =5*(R36/5-T36) -> -12 | T36: =round(R36/5,-1) -> 340
A37: 17 | B37: Privat | C37: Nunta | D37: Villa Trevi @ Bazosul Nou | E37: 47/23.03.2018 | G37: 13048 | H37: 1398 | I37: =round(H37*3%,0) -> 42 | J37: =sum(L37+N37+P37) -> 1030 | K37: Backline | L37: 930 | O37: Drum | P37: 100 | Q37: 0 | R37: =round(sum(G37-I37-J37-Q37-H37),0) -> 10578 | S37: =5*(R37/5-T37) -> 78 | T37: 2100
A38: 24 | B38: Privat | C38: Nunta | D38: Galla @ Timisoara | E38: 62/23.07.2018 | G38: 13285 | H38: 1315 | I38: =round(H38*3%,0) -> 39 | J38: =sum(L38+N38+P38) -> 1600 | K38: Backline | L38: 1600 | Q38: 0 | R38: =round(sum(G38-I38-J38-Q38-H38),0) -> 10331 | S38: =5*(R38/5-T38) -> -169 | T38: =round(R38/5,-2) -> 2100
A39: 30 | B39: Public | C39: Concert | D39: Papa la Soni @ Vama Veche | F39: Festivalul VSLO | G39: 0 | H39: 0 | I39: =round(G39*3%,0) -> 0 | J39: =sum(L39+N39+P39) -> 0 | K39: Backline | L39: 0 | T39: 0
A40: 31 | B40: Privat | C40: Nunta | D40: Vivlois Events @ Bucuresti | E40: 64/20.08.2018 | G40: 14448 | H40: 1395 | I40: =round(G40*3%,0) -> 433 | J40: =sum(L40+N40+P40) -> 2790 | K40: Backline | L40: 930 | O40: Drum | P40: 1860 | Q40: =round((G40-I40-J40)*20%,0) -> 2245 | R40: =round(sum(G40-I40-J40-Q40-H40),0) -> 7585 | S40: =5*(R40/5-T40) -> 85 | T40: 1500
A41: Septembrie
A42: 4 | B42: Public | C42: Concert | D42: D'arc pe mal @ Timisoara | F42: Concert | G42: 1200 | H42: 0 | I42: 0 | J42: =sum(L42+N42+P42) -> 1200 | K42: PA + Backline | L42: 0 | M42: Bebi/Marius | N42: 700 | O42: Light/Foto/Vid | P42: 500 | Q42: =round((G42-I42-J42)*20%,0) -> 0 | R42: =round(sum(G42-I42-J42-Q42-H42),0) -> 0 | S42: =5*(R42/5-T42) -> 0 | T42: 0
A43: 6 | B43: Privat | C43: Nunta | D43: Venue @ Timisoara | E43: 68/22.10.2018 | G43: 11417 | H43: 1398 | I43: =round(G43*3%,0) -> 343 | J43: =sum(L43+N43+P43) -> 930 | K43: Backline | L43: 930 | Q43: =round((G43-I43-J43)*20%,0) -> 2029 | R43: =round(sum(G43-I43-J43-Q43-H43),0) -> 6717 | S43: =5*(R43/5-T43) -> -33 | T43: 1350
A44: 7 | B44: Privat | C44: Nunta | D44: Ivy Events @ Timisoara | E44: 53/19.04.2018 | G44: 13020 | H44: 1380 | I44: =round(H44*3%,0) -> 41 | J44: =sum(L44+N44+P44) -> 930 | K44: Backline | L44: 930 | Q44: 0 | R44: =round(sum(G44-I44-J44-Q44-H44),0) -> 10669 | S44: =5*(R44/5-T44) -> -1166 | T44: 2367
A45: 13 | B45: Public | C45: Concert | D45: In saptele Casei @ Timisoara | F45: Organizat de FITT | G45: 2000 | H45: 0 | I45: 0 | J45: =sum(L45+N45+P45) -> 500 | K45: Backline | L45: 500 | Q45: 0 | R45: =round(sum(G45-I45-J45-Q45-H45),0) -> 1500 | S45: =5*(R45/5-T45) -> 0 | T45: =round(R45/5,-2) -> 300
A46: 21 | B46: Public | C46: Concert | D46: Bastion @ Timisoara | E46: 94/06.09.2019 | F46: Festivalul Bastion Glow | G46: 3500 | H46: 0 | I46: =round(G46*3%,0) -> 105 | J46: =sum(L46+N46+P46) -> 500 | K46: Backline | L46: 500 | Q46: =round((G46-I46-J46)*20%,0) -> 579 | R46: =round(sum(G46-I46-J46-Q46-H46),0) -> 2316 | S46: =5*(R46/5-T46) -> -184 | T46: =round(R46/5,-2) -> 500
A47: 21 | B47: Privat | C47: Nunta | D47: Venue @ Timisoara | E47: 61/22.07.2018 | G47: 12680 | H47: 1400 | I47: =round(H47*3%,0) -> 42 | J47: =sum(L47+N47+P47) -> 930 | K47: Backline | L47: 930 | Q47: 0 | R47: =round(sum(G47-I47-J47-Q47-H47),0) -> 10308 | S47: =5*(R47/5-T47) -> -267 | T47: 2115
A48: 27 | B48: Privat | C48: Nunta | D48: Ivy Events @ Timisoara | E48: 86/27.06.2019 | G48: 12750 | H48: 1417 | I48: =round(G48*3%,0) -> 383 | J48: =sum(L48+N48+P48) -> 1600 | K48: Backline | L48: 1600 | Q48: =round((G48-I48-J48)*20%,0) -> 2153 | R48: =round(sum(G48-I48-J48-Q48-H48),0) -> 7197 | S48: =5*(R48/5-T48) -> -3 | T48: =round(R48/5,-1) -> 1440
A49: 28 | B49: Privat | C49: Nunta | D49: Venue @ Timisoara | E49: 66/25.09.2018 | G49: 12675 | H49: 1395 | I49: =round(H49*3%,0) -> 42 | J49: =sum(L49+N49+P49) -> 930 | K49: Backline | L49: 930 | Q49: 0 | R49: =round(sum(G49-I49-J49-Q49-H49),0) -> 10308 | S49: =5*(R49/5-T49) -> -267 | T49: 2115
A50: 29 | B50: Privat | C50: Nunta | D50: Venue @ Timisoara | E50: 77/05.12.2018 | G50: 11505 | H50: 1400 | I50: =round(H50*3%,0) -> 42 | J50: =sum(L50+N50+P50) -> 930 | K50: Backline | L50: 930 | Q50: 0 | R50: =round(sum(G50-I50-J50-Q50-H50),0) -> 9133 | S50: =5*(R50/5-T50) -> -267 | T50: 1880
A51: Octombrie
A52: 12 | B52: Privat | C52: Nunta | D52: Congress Hall Iulius Town @ Timisoara | E52: 93/28.08.2019 | G52: 13723 | H52: 0 | I52: =round(H52*3%,0) -> 0 | J52: =sum(L52+N52+P52) -> 1600 | K52: PA + Backline | L52: 1600 | Q52: 0 | R52: =round(sum(G52-I52-J52-Q52-H52),0) -> 12123 | S52: =5*(R52/5-T52) -> 123 | T52: 2400
A53: 19 | B53: Privat | C53: Nunta | D53: Trio Events @ Timisoara | E53: 69/29.10.2018 | G53: 13514 | H53: 1398 | I53: =round(H53*3%,0) -> 42 | J53: =sum(L53+N53+P53) -> 1600 | K53: PA + Backline | L53: 1600 | Q53: 0 | R53: =round(sum(G53-I53-J53-Q53-H53),0) -> 10474 | S53: =5*(R53/5-T53) -> -276 | T53: 2150
A54: Noiembrie
A55: 1 | B55: Public | C55: Concert | D55: C'Pub @ Severin | G55: 2500 | H55: 0 | I55: 0 | J55: =sum(L55+N55+P55) -> 960 | K55: PA + Backline | L55: 500 | O55: Drum | P55: 460 | Q55: 0 | R55: =round(sum(G55-I55-J55-Q55-H55),0) -> 1540 | S55: =5*(R55/5-T55) -> -460 | T55: 400
A56: 19 | B56: Public | C56: Concert | D56: Mall Vitan @ Bucuresti | F56: City Vibes by BFM | G56: 0 | H56: 0 | I56: =round(G56*3%,0) -> 0 | J56: =sum(L56+N56+P56) -> 0 | K56: Backline | L56: 0 | Q56: 0 | R56: =round(sum(G56-I56-J56-Q56-H56),0) -> 0 | S56: =5*(R56/5-T56) -> 0 | T56: =round(R56/5,-1) -> 0
A57: Decembrie
A58: 11 | B58: Privat | C58: Corporate | D58: Venue @ Timisoara | F58: Firma Smartfit | G58: 0 | H58: 0 | I58: =round(G58*3%,0) -> 0 | J58: =sum(L58+N58+P58) -> 0 | K58: Backline | L58: 0 | Q58: =round((G58-I58-J58)*20%,0) -> 0 | R58: =round(sum(G58-I58-J58-Q58-H58),0) -> 0 | S58: =5*(R58/5-T58) -> 0 | T58: =round(R58/5,-1) -> 0
A59: 13 | B59: Privat | C59: Corporate | D59: Anturaj @ Timisoara | E59: C103 | F59: Firma Lindegaz | G59: 10000 | H59: 0 | I59: =round(G59*3%,0) -> 300 | J59: =sum(L59+N59+P59) -> 1410 | K59: Backline | L59: 950 | O59: Kuky | P59: 460 | Q59: =round((G59-I59-J59)*20%,0) -> 1658 | R59: =round(sum(G59-I59-J59-Q59-H59),0) -> 6632 | S59: =5*(R59/5-T59) -> -18 | T59: =round(R59/5,-1) -> 1330
A60: 14 | B60: Privat | C60: Corporate | D60: Congress Hall @ Timisoara | E60: PFA | F60: Firma Toluna | G60: 7155 | H60: 0 | I60: 0 | J60: =sum(L60+N60+P60) -> 950 | K60: Backline | L60: 950 | Q60: 0 | R60: =round(sum(G60-I60-J60-Q60-H60),0) -> 6205 | S60: =5*(R60/5-T60) -> 1355 | T60: 970
A61: 31 | B61: Public | C61: Concert | D61: Piata Victoriei @ Timisoara | F61: Revelion | G61: 7100 | H61: 0 | I61: =round(G61*3%,0) -> 213 | J61: =sum(L61+N61+P61) -> 700 | K61: Backline | L61: 700 | Q61: 0 | R61: =round(sum(G61-I61-J61-Q61-H61),0) -> 6187 | S61: =5*(R61/5-T61) -> -63 | T61: 1250
A62: 31 | B62: Public | C62: Concert | D62: Parcul Tricolorului @ Resita | E62: 96930/17.12.2019 | F62: Revelion | G62: 8000 | H62: 0 | I62: =round(G62*3%,0) -> 240 | J62: =sum(L62+N62+P62) -> 1450 | K62: Backline | L62: 950 | O62: Drum | P62: 500 | Q62: =round((G62-I62-J62)*20%,0) -> 1262 | R62: =round(sum(G62-I62-J62-Q62-H62),0) -> 5048 | S62: =5*(R62/5-T62) -> 48 | T62: 1000
D65: Statistici | K65: Legenda
D66: Descriere | E66: Nr. | F66: Descriere | G66: Ron | H66: Euro
D67: Numar Evenimente Publice Total | E67: =countif(B:B,"Public") -> 16 | F67: Total Venituri | G67: =sum(G3:G64) -> 419340 | H67: =round(G67/4.7,0) -> 89221 | L67: Achitat
D68: Numar Evenimente Private Total | E68: =countif(B:B,"Privat") -> 32 | F68: Bani Phaser | G68: =sum(R:R) -> 295650 | H68: =round(G68/4.7,0) -> 62904 | L68: Neachitat
D69: Numar Evenimente Private (Corporate) | E69: =COUNTIF(C:C,"Corporate") -> 4 | F69: Bani de persoana | G69: =sum(T:T) -> 59017 | H69: =round(G69/4.7,0) -> 12557
D70: Numar Evenimente Private (Nunta, Botez, Aniversare) | E70: =countif(C:C,"Nunta") + COUNTIF(C:C,"Botez") + countif(C:C,"Aniversare") -> 28 | F70: Bani ramasi in Firma/Fond | G70: =sum(S:S) -> 565 | H70: =round(G70/4.7,0) -> 120
D71: Numar Evenimente Total | E71: =E67+E68 -> 48 | F71: Bani MP/Fond | G71: =round(sum(Q:Q),0) -> 33791 | H71: =round(G71/4.7,0) -> 7190
F72: Bani pe Impozit 3% | G72: =round(3%*G67,0) -> 12580 | H72: =round(G72/4.7,0) -> 2677
F73: Bani Cheltuiti Total | G73: =sum(J:J) -> 50980 | H73: =round(G73/4.7,0) -> 10847
F74: Bani Cheltuiti Sunet | G74: =sum(L:L) -> 41150 | H74: =round(G74/4.7,0) -> 8755
F75: Bani Cheltuiti Tehnic | G75: =sum(N:N) -> 2750 | H75: =round(G75/4.7,0) -> 585
F76: Bani Cheltuiti Extra | G76: =sum(P:P) -> 7080 | H76: =round(G76/4.7,0) -> 1506
D77: Extra Statistici
F78: Bani Phaser pe Evenimente
F79: Descriere | G79: Ron | H79: Euro
F80: Bani din Event. Publice Total | G80: =G68-G81 -> 25201 | H80: =round(G80/4.7,0) -> 5362
F81: Bani din Event. Private Total | G81: =G82+G83 -> 270449 | H81: =round(G81/4.7,0) -> 57542
F82: Bani din Corporate | G82: =SUMIF(C:C,"Corporate",R:R) -> 17406 | H82: =round(G82/4.7,0) -> 3703
F83: Bani din (Nunta/Botez/Aniversare) | G83: =SUMIF(C:C,"Nunta",R:R)+SUMIF(C:C,"Botez",R:R)+SUMIF(C:C,"Aniversare",R:R) -> 253043 | H83: =round(G83/4.7,0) -> 53839
F84: Bani de Pers. pe Evenimente
F85: Bani din Event. Publice Total | G85: =round(G80/5,0) -> 5040 | H85: =round(G85/4.7,0) -> 1072
F86: Bani din Event. Private Total | G86: =round(G81/5,0) -> 54090 | H86: =round(G86/4.7,0) -> 11509
F87: Bani din Corporate | G87: =round(G82/5,0) -> 3481 | H87: =round(G87/4.7,0) -> 741
F88: Bani din (Nunta/Botez/Aniversare) | G88: =round(G83/5,0) -> 50609 | H88: =round(G88/4.7,0) -> 10768

Sheet Fond Extra 2019
A1: Incasari | D1: Cheltuieli
A3: Ron | B3: Data | C3: Descriere | D3: Ron | E3: Data | F3: Descriere
A4: -350 | B4: 01.01.2019 | C4: bani ramasi de pe 2018 | D4: 2500 | F4: Zbor Avion Flavius Japonia (Recup Radu) | H4: T C Ron | I4: =sum(D:D) -> 172435
A5: 11135 | B5: 11.05.2019 | C5: Bani Cash Event 11.05.2019 | D5: 200 | F5: Peta (Indestructibil) (Recup Radu) | H5: T V Ron | I5: =sum(A:A) -> 194747
